Workbook
Name ДаНет: Тех.Лист!$A$1:$A$2
Name С2: '01'!$C$2
Name число: '01'!$C$2

Sheet 01
C2: 46082
A4: ООО ТД РТПЗ | E4: =SUM(E5:E12) -> 0
A5: Волжский счёт СБ 7503
A6: Головной счёт СБ 13291
A7: ИП Коваленко СБ 17500
A8: счёт ЦМР Банк
A9: счёт РОСБАНК 1115
A10: счёт Райффайзенбанк 38867
A11: счёт Промсвязьбанк 5439
A12: счёт Альфа-Банк 10329
A14: № п/п | B14: Инициатор платежа | C14: Контрагент - Получатель | D14: Договор/Счет | E14: Сумма к оплате | F14: Назначение платежа | G14: Подразделение - плательщик | H14: Бюджет/Статья | I14: Наличие Договора | J14: Примечание | K14: Отметка об оплате | L14: Спец. Распоряжение
B15: Коммерческий отдел (ПОСТАВЩИКИ / ПОКУПАТЕЛИ)
A16: 1
A17: 2
A18: 3
A19: 4
A20: 5
A21: 6
A22: 7
A23: 8
A24: 9
A25: 10
A26: 11
A27: 12
... A35: 20
B36: Коммерческий отдел (ЛОГИСТИКА / Хранение / ПРР)
A37: 1
A38: 2
A39: 3
A40: 4
A41: 5
A42: 6
A43: 7
A44: 8
A45: 9
A46: 10
A47: 11
A48: 12
... A56: 20
B57: ПРОИЗВОДСТВЕННЫЙ комплекс / ТЕХ служба
A58: 1
A59: 2
A60: 3
A61: 4
A62: 5
A63: 6
A64: 7
A65: 8
A66: 9
A67: 10
A68: 11
A69: 12
... A72: 15
B73: РАСХОДЫ ПРОЧИЕ (Тех служба / Складской коммплекс / IT служба / Юр служба / Секретариат / Кадры / Маркетинг)
A74: 1
A75: 2
A76: 3
A77: 4
A78: 5
A79: 6
A80: 7
A81: 8
A82: 9
A83: 10
A84: 11
A85: 12
... A88: 15
B89: Бухгалтерия (Налоги / ЗП / ЕСН / прочие платежи бух. службы)
A90: 1
A91: 2
A92: 3
A93: 4
A94: 5
A95: 6
A96: 7
A97: 8
A98: 9
A99: 10
B100: ФЭО (Кредиты/ Лизинг / Проценты / прочие платежи)
A101: 1
A102: 2
A103: 3
A104: 4
A105: 5
A106: ИТОГО ТД РТПЗ РАСХОДЫ ПО РЕЕСТРУ | E106: =SUM(E15:E105) -> 0
A107: ДЕФИЦИТ / ПРОФИЦИТ с Остатка на начало дня | E107: =E4-E106 -> 0
A109: ООО ЖИВАЯ СТАЛЬ | E109: =SUM(E110:E113) -> 0
A110: счёт СБ 1125
A115: № п/п | B115: Инициатор платежа | C115: Контрагент - Получатель | D115: Договор/Счет | E115: Сумма к оплате | F115: Назначение платежа | G115: Подразделение - плательщик | H115: Бюджет/Статья | I115: Наличие Договора | J115: Примечание | K115: Отметка об оплате | L115: Спец. Распоряжение
B116: Коммерческий отдел (Закупка товара / Логистика / Снабжение/ ВЭД / Хранение / ПРР / Маркетинг)
A117: 1
A118: 2
A119: 3
A120: 4
A121: 5
A122: 6
A123: 7
A124: 8
A125: 9
A126: 10
...

Sheet 02
C2: =С2+1 -> 46083
A4: ООО ТД РТПЗ | E4: =SUM(E5:E12) -> 11618486 | F4: РЕЕСТР ЗАКРЫТ !!!
A5: Волжский счёт СБ 7503 | E5: 3979050.6
A6: Головной счёт СБ 13291 | E6: 2919755.7
A7: ИП Коваленко СБ 17500
A8: счёт ЦМР Банк | E8: 15821.6
A9: счёт РОСБАНК 1115 | E9: 5166.84
A10: счёт Райффайзенбанк 38867 | E10: 32595.97
A11: счёт Промсвязьбанк 5439 | E11: 2961193.6
A12: счёт Альфа-Банк 10329 | E12: 1704901.4
A14: № п/п | B14: Инициатор платежа | C14: Контрагент - Получатель | D14: Договор/Счет | E14: Сумма к оплате | F14: Назначение платежа | G14: Подразделение - плательщик | H14: Бюджет/Статья | I14: Наличие Договора | J14: Примечание | K14: Отметка об оплате | L14: Спец. Распоряжение
B15: Коммерческий отдел (ПОСТАВЩИКИ / ПОКУПАТЕЛИ)
A16: 1 | B16: Дынник | C16: ООО "Группа Компаний Демидов" | D16: СЧЕТ № ФИЛ26-428364 от 27.02.26 | E16: 35258 | F16: Труба профильная (2 сорт) (некондиция, упаковка) | G16: РТПЗ Волжский | H16: Бюджет ПЛАН | I16: Да | K16: оплачен
A17: 2 | B17: Дынник | C17: ООО "Группа Компаний Демидов" | D17: СЧЕТ № ФИЛ26-428102 от 27.02.26 | E17: 155154 | F17: Труба профильная (2 сорт) (некондиция, упаковка) | G17: РТПЗ Волжский | H17: Бюджет ПЛАН | I17: Да | K17: оплачен
A18: 3
A19: 4 | B19: Федоров А.А. | C19: Северсталь ПАО | D19: Договр № 643/1000-24100303 от 12.04.2024 | E19: .26000000 | F19: Металлопрокат | I19: Да
A20: 5 | B20: Крикса М.П. | C20: АЛЮМИНАРТ ООО | D20: Договор № 14 от 21.01.2026 г | E20: 3404096 | F20: возврат ошибочно перечисленных д.с | G20: РТПЗ Волжский | I20: Да | J20: Согласовано Солодовниковым А.Н. | K20: оплачен
A21: 6
A22: 7
A23: 8
A24: 9
A25: 10
A26: 11
A27: 12
A28: 13
A29: 14
A30: 15
A31: 16
A32: 17
... A35: 20
B36: Коммерческий отдел (ЛОГИСТИКА / Хранение / ПРР)
A37: 1 | B37: Голка | C37: АК№2 ООО | D37: Счет №1975 от 27.01 | E37: 115000 | F37: Транспорт | G37: РТПЗ Волжский | H37: Бюджет ПЛАН | I37: Да | K37: оплачен
A38: 2 | B38: Голка | C38: Дентро ООО | D38: Счет №2528 от 29.01 | E38: 58000 | F38: Транспорт | G38: РТПЗ Волжский | H38: Бюджет ПЛАН | I38: Нет | J38: скан | K38: оплачен
A39: 3 | B39: Голка | C39: РАУТ ООО | D39: Счет №4,6,7,10 от 26.01 | E39: =55000+80000+70000+47000 -> 252000 | F39: Транспорт | G39: РТПЗ Волжский | H39: Бюджет ПЛАН | I39: Да | K39: оплачен
A40: 4 | B40: Голка | C40: Стальстройпоставка ООО | D40: Счет №4,6,7,10 от 26.01 | E40: =96000+75000 -> 171000 | F40: Транспорт | G40: РТПЗ Волжский | H40: Бюджет ПЛАН | I40: Нет | J40: копия | K40: оплачен
A41: 5 | B41: Голка | C41: Кравцов С.А. ИП | D41: Счет №2 от 30.01 | E41: 20000 | F41: Транспорт | G41: РТПЗ Волжский | H41: Бюджет ПЛАН | I41: Нет | K41: оплачен
A42: 6 | B42: Голка | C42: НЕО ТРАНС ООО | D42: Счет №813 от 25.01 | E42: 85000 | F42: Транспорт | G42: РТПЗ Волжский | H42: Бюджет ПЛАН | I42: Да | K42: оплачен
A43: 7 | B43: Голка | C43: Черненко-Рус ООО | D43: Счет чр457-608п от 25.08 | E43: 95000 | F43: Транспорт | G43: РТПЗ Волжский | H43: Бюджет ПЛАН | I43: Да | K43: оплачен
A44: 8
A45: 9
A46: 10
A47: 11
A48: 12
A49: 13
A50: 14
A51: 15
A52: 16
A53: 17
A54: 18
A55: 19
A56: 20
B57: ПРОИЗВОДСТВЕННЫЙ комплекс / ТЕХ служба
A58: 1 | B58: Стадников | C58: ООО Волга-Бизнес | D58: счет №ВБ-94 от 25.02.2026 | E58: 32800 | F58: вывоз крупногабаритных отходов (пр коммун) | G58: РТПЗ Волжский | H58: Бюджет ПЛАН | I58: Нет | J58: на подписании | K58: оплачен
A59: 2 | B59: Дынник | C59: КАРБОН ИНВЕСТ ЗАО | D59: Счет-фактура №69 от 03.02.2026 | E59: 443173.9 | F59: Карбон, КМ (смазочные) | G59: РТПЗ Волжский | H59: Бюджет ПЛАН | I59: Нет | J59: копия | K59: оплачен
A60: 3 | B60: Дынник | C60: 2РС | D60: Счет на оплату № 9595 от 26 февраля 2026 г. | E60: 34100 | F60: Подшипники (РПМ) | G60: РТПЗ Волжский | H60: Бюджет ПЛАН | I60: Нет | J60: копия | K60: оплачен
A61: 4 | B61: Дынник | C61: ИП Вязовская Ирина Геннадьевна | D61: Счет-договор № 97 от 25 февраля 2026 г. | E61: 2300 | F61: Перекись водорода 60% (смазочные) | G61: РТПЗ Волжский | H61: Бюджет ПЛАН | I61: Нет | J61: скан | K61: оплачен
A62: 5 | B62: Дынник | C62: ООО "МИКРОБОР" | D62: Счет на оплату №408 от 26.02.2026 | E62: 67570.92 | F62: Пластина режущая «MICROBOR» (Инструмент) | G62: РТПЗ Волжский | H62: Бюджет ПЛАН | I62: Да
A63: 6 | B63: Дынник | C63: ПРЕМИУМ ЭЙР ООО | D63: Счёт-договор № 00825 от 26.02.26 | E63: 12700 | F63: Клапан термостатический VTFT (РПМ) | G63: РТПЗ Волжский | H63: Бюджет ПЛАН | I63: Нет | J63: скан | K63: оплачен
A64: 7 | B64: Дынник | C64: ООО «Флэйн-Сервис» | D64: Счет на оплату № 852 от 27 февраля 2026 г. | E64: 1000 | F64: Резиновое кольцо для РКТ (РПМ) | G64: РТПЗ Волжский | H64: Бюджет ПЛАН | I64: Да | K64: оплачен
A65: 8 | B65: Дынник | C65: ПМЦ2015 | D65: Счет на оплату № 10753/24 от 27 февраля 2026 г. | E65: 6061 | F65: Щетки, клей, замок (Хозрасходы) | G65: РТПЗ Волжский | H65: Бюджет ПЛАН | I65: Да | K65: оплачен
A66: 9 | B66: Дынник | C66: ООО "Поволжский Центр РТИ" | D66: Счет на оплату № 2265 от 26 февраля 2026 г. | E66: 9173.91 | F66: Ремень клиновой (РПМ) | G66: РТПЗ Волжский | H66: Бюджет ПЛАН | I66: Да | K66: оплачен
A67: 10 | B67: Дынник | C67: ООО "ЮЦТМ" | D67: Счет на оплату № УТ-267 от 27 февраля 2026 г. | E67: 23315.46 | F67: Пластина VCMT (РПМ) | G67: РТПЗ Волжский | H67: Бюджет ПЛАН | I67: Да
A68: 11 | B68: Дынник | C68: Интернет Решения, ООО | D68: Счет-Оферта № 0164150363-0048 от 27.02.2026 | E68: 4251 | F68: Припой,шайба,винты (Инструмент) | G68: РТПЗ Волжский | H68: Бюджет ПЛАН | J68: / припой на сумму 2315,00 в счет возвращенных д/с от поставщика | K68: оплачен
A69: 12 | B69: Дынник | C69: ВСЕИНСТРУМЕНТЫ.РУ ООО | D69: Счет-фактура №0302009527-ВЛЖ от 03.02.2026 | E69: 91887 | F69: Инструмент | G69: РТПЗ Волжский | H69: Бюджет ПЛАН | I69: Нет | J69: СКАН | K69: оплачен
A70: 13 | B70: Дынник | C70: ООО "Вектор-ПМ" | D70: Счет на оплату № 453 от 2 марта 2026 г. | E70: 37000 | F70: Весы крановые (Инутсрумент) | G70: РТПЗ Волжский | H70: Бюджет ПЛАН | I70: Да | K70: оплачен
A71: 13 | B71: Любимов Ю.В. | C71: ООО ОП Кристалл групп | D71: Счет № 9 от 14.01.2026 г. | E71: 320000 | F71: Услуги по охране согл договору №30/12/-1 от 30.12.2019 г. за Январь 2026г. | G71: РТПЗ Волжский | H71: Бюджет ПЛАН | I71: Да
A72: 14 | B72: Коваль В.А. | C72: УФК по Волгоградской области (Облкомимущество) | D72: Договор №14124 от 26 ноября 2021 г. | E72: 32722.06 | F72: НДС не облагается. Арендная плата по договору аренды.земельного участка №14124 от 26.11.2021 г. (Аренда зданий и помещений) | G72: РТПЗ Волжский | H72: Бюджет ПЛАН | I72: Да | K72: оплачен
A73: 15 | B73: Любимов Ю.В. | C73: ООО Волжскпромжелдортранс-Экспедитор | D73: счет № 22 от 24.02.2026 | E73: 12514.62 | F73: Транспортно-экспедиционные услуги за 2 декаду февраля 2026 года (жд) | G73: РТПЗ Волжский | H73: Бюджет ПЛАН | I73: Да | K73: оплачен
A74: 16
B75: РАСХОДЫ ПРОЧИЕ (Тех служба / Складской коммплекс / IT служба / Юр служба / Секретариат / Кадры / Маркетинг)
A76: 1 | B76: Гаркушенко | C76: ИП Максимова ВД | D76: ЦХБ-0425511 от 28.02 | E76: 1380 | F76: экспресс почта февраль | H76: Бюджет ПЛАН | I76: Да | K76: оплачен
A77: 2 | B77: Сухорутченко | C77: ООО КЕХ еКОММЕРЦ | D77: СЧ № 01-2031434506 от 02 марта 2026 г. | E77: 6000 | F77: Внесение аванса в личный кабинет 93403104 по счёту № 01-2031434506 от 02.03.2026 (обуч) | H77: Бюджет ПЛАН | I77: Да | K77: оплачен
A78: 3 | J78: общезаводская заявка
A79: 4 | B79: Приезжева | C79: Мистер Пэн | D79: счет 25 от 26.02.2026 | E79: 12818 | F79: моющие средства (хоз) | G79: РТПЗ Волжский | H79: Бюджет ПЛАН | I79: Да | J79: общезаводская заявка | K79: оплачен
A80: 5 | B80: Приезжева | C80: Мистер Пэн | D80: счет 23 от 26.02.2026 | E80: 5710 | F80: скотч (упаковка) | G80: РТПЗ Волжский | H80: Бюджет ПЛАН | I80: Да | J80: СУ | K80: оплачен
A81: 6
A82: 7
A83: 8
A84: 9
A85: 10
A86: 11
A87: 12
A88: 13
A89: 14
A90: 15
B91: Бухгалтерия (Налоги / ЗП / ЕСН / прочие платежи бух. службы)
A92: 1 | B92: Татаринова Н.А. | C92: ИФНС по ЕНП | D92: КБК 18201061201010000510 | E92: =28703+2685+174930/3 -> 89698 | F92: ЕНП (Прибыль аванс февраль) | H92: Бюджет ПЛАН | J92: прибыль аванс февраль Срок оплаты -02.03.26 | K92: оплачен
A93: 2 | B93: Татаринова Н.А. | C93: ООО АФ "СТАНДАРТ" | D93: Счет 46 от 18.11.25, Договор от 18.11.25 | E93: 55000 | F93: Аудит фин.отчетности за 2025г., без НДС (инф консуль) | H93: Бюджет ПЛАН | I93: Да | K93: оплачен
A94: 3
A95: 4
A96: 5
A97: 6
A98: 7
A99: 8
A100: 9
A101: 10
B102: ФЭО (Кредиты/ Лизинг / Проценты / прочие платежи)
A103: 1
A104: 2
A105: 3
...

Sheet 03
C2: ='02'!C2+1 -> 46084
A4: ООО ТД РТПЗ | E4: =SUM(E5:E12) -> 9256753.5 | F4: РЕЕСТР ЗАКРЫТ !!!
A5: Волжский счёт СБ 7503 | E5: 9081635.9
A6: Головной счёт СБ 13291 | E6: 19755.66
A8: счёт ЦМР Банк | E8: 15821.6
A9: счёт РОСБАНК 1115 | E9: 3366.84
A10: счёт Райффайзенбанк 38867 | E10: 120078.47
A11: счёт Промсвязьбанк 5439 | E11: 11193.59
A12: счёт Альфа-Банк 10329 | E12: 4901.43
A14: № п/п | B14: Инициатор платежа | C14: Контрагент - Получатель | D14: Договор/Счет | E14: Сумма к оплате | F14: Назначение платежа | G14: Подразделение - плательщик | H14: Бюджет/Статья | I14: Наличие Договора | J14: Примечание | K14: Отметка об оплате | L14: Спец. Распоряжение
B15: Коммерческий отдел (ПОСТАВЩИКИ / ПОКУПАТЕЛИ)
A16: 1
A17: 2 | B17: Федоров А.А. | C17: Северсталь ПАО | D17: Договр № 643/1000-24100303 от 12.04.2024 | E17: 26000000 | F17: Металлопрокат
A18: 3 | B18: Федоров А.А. | C18: НЛМК ПАО | D18: Договор В204709-24 от 24.10.2024 | E18: 4652500.6 | F18: Металлопрокат
A19: 4
A20: 5
A21: 6
A22: 7
A23: 8
A24: 9
A25: 10
A26: 11
A27: 12
A28: 13
A29: 14
A30: 15
... A35: 20
B36: Коммерческий отдел (ЛОГИСТИКА / Хранение / ПРР)
A37: 1
A38: 2
A39: 3
A40: 4
A41: 5
A42: 6
A43: 7
A44: 8
A45: 9
A46: 10
A47: 11
A48: 12
... A56: 20
B57: ПРОИЗВОДСТВЕННЫЙ комплекс / ТЕХ служба
A58: 1
A59: 2
A60: 3
A61: 4
A62: 5
A63: 6
A64: 7
A65: 8
A66: 9
A67: 10
A68: 11
A69: 12
... A72: 15
B73: РАСХОДЫ ПРОЧИЕ (Тех служба / Складской коммплекс / IT служба / Юр служба / Секретариат / Кадры / Маркетинг)
A74: 1 | B74: Гаркушенко | C74: Выросткова | E74: 28000 | F74: билеты Казань | G74: РТПЗ Ростов | H74: Бюджет ПЛАН | K74: оплачен
A75: 2
A76: 3
A77: 4
A78: 5
A79: 6
A80: 7
A81: 8
A82: 9
A83: 10
A84: 11
A85: 12
A86: 13
... A88: 15
B89: Бухгалтерия (Налоги / ЗП / ЕСН / прочие платежи бух. службы)
A90: 1 | B90: Лазарева Л.Ю | C90: Сбер Волжский | D90: реестр | E90: 11779.32 | F90: Расчет при увольнении за март 2026г | G90: РТПЗ Волжский | H90: Бюджет ПЛАН | K90: оплачен
A91: 2
A92: 3
A93: 4
A94: 5
A95: 6
A96: 7
A97: 8
A98: 9
A99: 10
B100: ФЭО (Кредиты/ Лизинг / Проценты / прочие платежи)
A101: 1
A102: 2
A103: 3
A104: 4
A105: 5
A106: ИТОГО ТД РТПЗ РАСХОДЫ ПО РЕЕСТРУ | E106: =SUM(E15:E105) -> 30692280
A107: ДЕФИЦИТ / ПРОФИЦИТ с Остатка на начало дня | E107: =E4-E106 -> -21435526
A109: ООО ЖИВАЯ СТАЛЬ | E109: =SUM(E110:E113) -> 3654.8
A110: счёт СБ 1125 | E110: 3654.8
A115: № п/п | B115: Инициатор платежа | C115: Контрагент - Получатель | D115: Договор/Счет | E115: Сумма к оплате | F115: Назначение платежа | G115: Подразделение - плательщик | H115: Бюджет/Статья | I115: Наличие Договора | J115: Примечание | K115: Отметка об оплате | L115: Спец. Распоряжение
B116: Коммерческий отдел (Закупка товара / Логистика / Снабжение/ ВЭД / Хранение / ПРР / Маркетинг)
A117: 1
A118: 2
A119: 3
A120: 4
A121: 5
A122: 6
A123: 7
...

Sheet 04
C2: ='03'!C2+1 -> 46085
A4: ООО ТД РТПЗ | E4: =SUM(E5:E12) -> 5862223.4 | F4: РЕЕСТР ЗАКРЫТ !!!
A5: Волжский счёт СБ 7503 | E5: 5656225.8 | F5: =E37+E38+E39+E40+E41+E42+E43+E44+E45++E46+E47+E48+E58+E59+E61+E62+E63+E67+E69+E70+E74+E76+E77+E78+E79+E80+E81+E82+E83+E89+E90+E91+E92+E93+E94+E95+E105 -> 3121479.9
A6: Головной счёт СБ 13291 | E6: 19755.66
A7: ИП Коваленко СБ 17500
A8: счёт ЦМР Банк | E8: 15821.6
A9: счёт РОСБАНК 1115 | E9: 3366.84
A10: счёт Райффайзенбанк 38867 | E10: 120078.47
A11: счёт Промсвязьбанк 5439 | E11: 42073.59
A12: счёт Альфа-Банк 10329 | E12: 4901.43
A14: № п/п | B14: Инициатор платежа | C14: Контрагент - Получатель | D14: Договор/Счет | E14: Сумма к оплате | F14: Назначение платежа | G14: Подразделение - плательщик | H14: Бюджет/Статья | I14: Наличие Договора | J14: Примечание | K14: Отметка об оплате | L14: Спец. Распоряжение
B15: Коммерческий отдел (ПОСТАВЩИКИ / ПОКУПАТЕЛИ)
A16: 1
A17: 2 | B17: Федоров А.А. | C17: Северсталь ПАО | D17: Договр № 643/1000-24100303 от 12.04.2024 | E17: 26000000 | F17: Металлопрокат | I17: Да
A18: 3 | B18: Федоров А.А. | C18: НЛМК ПАО | D18: Договор В204709-24 от 24.10.2024 | E18: 4652500.6 | F18: Металлопрокат | I18: Да
A19: 4
A20: 5
A21: 6
A22: 7
A23: 8
A24: 9
A25: 10
A26: 11
A27: 12
A28: 13
A29: 14
A30: 15
... A35: 20
B36: Коммерческий отдел (ЛОГИСТИКА / Хранение / ПРР)
A37: 1 | B37: Голка | C37: Ушаков ИП | D37: Счет № 55,50 от 02.02 | E37: =80000+80000 -> 160000 | F37: Транспорт | G37: РТПЗ Волжский | H37: Бюджет ПЛАН | I37: Нет | J37: скан | K37: оплачен
A38: 2 | B38: Голка | C38: Донцов ИП | D38: Счет №03 от 13.02 | E38: 58500 | F38: Транспорт | G38: РТПЗ Волжский | H38: Бюджет ПЛАН | I38: Нет | J38: копия | K38: оплачен
A39: 3 | B39: Голка | C39: Альфа ООО | D39: Счет №5 от 27.02 | E39: 105000 | F39: Транспорт | G39: РТПЗ Волжский | H39: Бюджет ПЛАН | I39: Да | K39: оплачен
A40: 4 | B40: Голка | C40: Воронков Ю.С. ИП | D40: Счет №7.26 от 15.01 | E40: 58000 | F40: Транспорт | G40: РТПЗ Волжский | H40: Бюджет ПЛАН | I40: Нет | J40: скан | K40: оплачен
A41: 5 | B41: Голка | C41: СКС ГРУПП ООО | D41: Счет №18,24,22 от 29.01 | E41: =42000+36000+36000 -> 114000 | F41: Транспорт | G41: РТПЗ Волжский | H41: Бюджет ПЛАН | I41: Да | K41: оплачен
A42: 6 | B42: Голка | C42: Черненко-Рус ООО | D42: Счет №1772 от 21.08 | E42: 90000 | F42: Транспорт | G42: РТПЗ Волжский | H42: Бюджет ПЛАН | I42: Да | K42: оплачен
A43: 7 | B43: Голка | C43: Долотказин ИП | D43: Счет №07 от 02.02 | E43: 55000 | F43: Транспорт | G43: РТПЗ Волжский | H43: Бюджет ПЛАН | I43: Да | K43: оплачен
A44: 8 | B44: Голка | C44: Вектор-Н ООО | D44: Счет №1183 от 26.12 | E44: 95000 | F44: Транспорт | G44: РТПЗ Волжский | H44: Бюджет ПЛАН | I44: Да | K44: оплачен
A45: 9 | B45: Голка | C45: Дентро ООО | D45: Счет №3627,3628 от 03.02 | E45: =95000+90000 -> 185000 | F45: Транспорт | G45: РТПЗ Волжский | H45: Бюджет ПЛАН | I45: Нет | J45: скан | K45: оплачен
A46: 10 | B46: Голка | C46: РАУТ ООО | D46: Счет №8,9 от 02.02 | E46: =70000+58000 -> 128000 | F46: Транспорт | G46: РТПЗ Волжский | H46: Бюджет ПЛАН | I46: Да | K46: оплачен
A47: 11 | B47: Голка | C47: Кузнеченков ИП | D47: Счет №14 от 19.02 | E47: 54999.9 | F47: Транспорт | G47: РТПЗ Волжский | H47: Бюджет ПЛАН | I47: Да | K47: оплачен
A48: 12 | B48: Голка | C48: Селезнёв ИП | D48: Счет №2163 от 24.02 | E48: 47000 | F48: Транспорт | G48: РТПЗ Волжский | H48: Бюджет ПЛАН | I48: Нет | J48: скан | K48: оплачен
A49: 13
A50: 14
A51: 15
A52: 16
A53: 17
A54: 18
A55: 19
A56: 20
B57: ПРОИЗВОДСТВЕННЫЙ комплекс / ТЕХ служба
A58: 1 | B58: Дынник | C58: СПЕЦОБЪЕДИНЕНИЕ ЮГО-ЗАПАД ООО | D58: Счет-фактура №1.12-0023 от 12.01.2026 | E58: 14036.1 | F58: Полуботинки (Спецодежда) | G58: РТПЗ Волжский | H58: Бюджет ПЛАН | I58: Да | K58: оплачен
A59: 2 | B59: Дынник | C59: Калабзаров Артем Олегович ИП | D59: Счет-фактуры №3081 от 22.01.2025, 3142 от 26.12.2025, 118 от 28.01.2026, 191 от 05.02.2026 | E59: 318383.39 | F59: СИЗы (Спецодежда) | G59: РТПЗ Волжский | H59: Бюджет ПЛАН | I59: Да | K59: оплачен
A60: 3 | B60: Любимов Ю.В. | C60: ООО ОП Кристалл групп | D60: Счет № 19 от 02.02.2026 г. | E60: 320000 | F60: Услуги по охране согл договору №30/12/-1 от 30.12.2019 г. за Февраль 2026г. (орг) | G60: РТПЗ Волжский | H60: Бюджет ПЛАН | I60: Да
A61: 4 | B61: Стадников | C61: ООО Техиндустрия | D61: Счет № 19 от 02.02.2026 г. | E61: 38800 | F61: валки (стан) | G61: РТПЗ Волжский | H61: Бюджет ПЛАН | I61: Да | J61: сумма к оплате по реестру | K61: оплачен
A62: 5 | B62: Стадников | C62: ООО Техиндустрия | D62: счет №20 от 02.02.2026 | E62: 126392 | F62: втулки (стан) | G62: РТПЗ Волжский | H62: Бюджет ПЛАН | I62: Да | J62: сумма к оплате по реестру | K62: оплачен
A63: 6 | B63: Стадников | C63: ИП Евдокимов С.М. | D63: счет №28 от 27.02.2026 | E63: 25200 | F63: закалка оси, шлифовка ножей (АПР) | G63: РТПЗ Волжский | H63: Бюджет ПЛАН | I63: Да | K63: оплачен
A64: 7 | B64: Стадников | C64: ООО Дезинфекционный Сервис | D64: счет №32 от 26.02.2026 | E64: 4200 | F64: дератизация, дезинсекция (пр коммун) | G64: РТПЗ Волжский | H64: Бюджет ПЛАН | I64: Нет
A65: 8 | B65: Стадников | C65: ООО Полином+ | D65: счет №313 от 13.02.2026 | E65: 8653.84 | F65: стирка спецодежды (усл пр-ва) | G65: РТПЗ Волжский | H65: Бюджет ПЛАН | I65: Да
A66: 9 | B66: Стадников | C66: ИП Дроздова Н.Н. | D66: счет №12 от 28.02.2026 | E66: 7000 | F66: услуги автовышки (ГПМ) | G66: РТПЗ Волжский | H66: Бюджет ПЛАН | I66: Да
A67: 10 | B67: Стадников | C67: ИП Швадченко А.В. | D67: счет №85611 от 03.03.2026 | E67: 70550 | F67: ремонт БМВ Х5 (Метком) | G67: РТПЗ Ростов | H67: Бюджет МЕТКОМ | I67: Да | K67: оплачен
A68: 11 | B68: Стадников | C68: ИП Шаповалов Г.В. | D68: счет №29 от 26.02.2026 | E68: 28690 | F68: ремонт каравелла (Метком) | G68: РТПЗ Ростов | H68: Бюджет МЕТКОМ | I68: Да
A69: 12 | B69: Дынник | C69: ООО "Восток-Агро" | D69: Счет-договор №369 от 26.02.2026 | E69: 2735 | F69: Насос НШ (Инструмент) | G69: РТПЗ Волжский | H69: Бюджет ПЛАН | I69: Нет | K69: оплачен
A70: 13 | B70: Любимов Ю.В. | C70: ООО Центрэнерго | D70: Договор №40ЭС-20 от 15.10.2020 г. | E70: 330000 | F70: реквизиты АБ Россия за потребление электроэнергии в марте 2026 г. | G70: РТПЗ Волжский | H70: Бюджет ПЛАН | I70: Да | K70: оплачен
A71: 14 | B71: Любимов Ю.В. | C71: ООО Центрэнерго | D71: Договор №40ЭС-20 от 15.10.2020 г. | E71: 12000 | F71: реквизиты АБ Россия за потребление электроэнергии в марте 2026 г. | G71: РТПЗ Волжский | H71: 79.02 КОД | I71: Да | J71: КОД
A72: 15 | B72: Любимов Ю.В. | C72: ООО Волжскпромжелдортранс-Экспедитор | D72: счет № 27 от 28.02.2026 | E72: 37543.91 | F72: Транспортно-экспедиционные услуги за 3 декаду февраля 2026 года (ЖД) | G72: РТПЗ Волжский | H72: Бюджет ПЛАН | I72: Да
A73: 16 | B73: Любимов Ю.В. | C73: ИП Якшин С В | D73: Счет № 47 от 27.02.2026 | E73: 288164 | F73: Услуги по перевозке пассажиров за Февраль 2026 г (Перевозка работников на производство) | G73: РТПЗ Волжский | H73: Бюджет ПЛАН | I73: Да
A74: 17 | B74: Дынник | C74: Праксайр Волгоград | D74: Счет №PXV-2617003921/50100532 от 28.02.2026 | E74: 6255.38 | F74: Аренда баллонов аргона, углекислота, кислород (сварка) | G74: РТПЗ Волжский | H74: Бюджет ПЛАН | I74: Да | K74: оплачен
A76: 19 | B76: Дынник | C76: Деловые Линии | D76: Счет 26-02981014878 от 16.02.2026 14:44:59 | E76: 960.08 | F76: Расходы на доставку (на производство/с производства) | G76: РТПЗ Волжский | H76: Бюджет ПЛАН | I76: Да | K76: оплачен
A77: 20 | B77: Дынник | C77: Деловые Линии | D77: Счет 26-00021044974 от 17.02.2026 18:38:12 | E77: 1307 | F77: Расходы на доставку (на производство/с производства) | G77: РТПЗ Волжский | H77: Бюджет ПЛАН | I77: Да | K77: оплачен
A78: 21 | B78: Дынник | C78: Деловые Линии | D78: Счет 26-02571015278 от 20.02.2026 2:04:33 | E78: 4197 | F78: Расходы на доставку (на производство/с производства) | G78: РТПЗ Волжский | H78: Бюджет ПЛАН | I78: Да | K78: оплачен
A79: 22 | B79: Дынник | C79: Деловые Линии | D79: Счет 26-02575008971 от 20.02.2026 8:21:46 | E79: 30 | F79: Расходы на доставку (на производство/с производства) | G79: РТПЗ Волжский | H79: Бюджет ПЛАН | I79: Да | K79: оплачен
A80: 23 | B80: Дынник | C80: Деловые Линии | D80: Счет 26-04031018621 от 26.02.2026 10:00:37 | E80: 839 | F80: Расходы на доставку (на производство/с производства) | G80: РТПЗ Волжский | H80: Бюджет ПЛАН | I80: Да | K80: оплачен
A81: 24 | B81: Дынник | C81: Компания Промметиз | D81: Счет на оплату № 8131 от 03 марта 2026 г. | E81: 8625 | F81: Круги, полотно (Инструмент) | G81: РТПЗ Волжский | H81: Бюджет ПЛАН | I81: Да | K81: оплачен
A82: 24 | B82: Дынник | C82: ООО "ТД "Подшипник Трейд" | D82: Счет на оплату № УТ-6881 от 26 февраля 2026 г. | E82: 19500 | F82: Подшипник (РПМ) | G82: РТПЗ Волжский | H82: Бюджет ПЛАН | I82: Да | J82: сумма к оплате по реестру | K82: оплачен
A83: 25.714286 | B83: Дынник | C83: ИП МОРОЗОВА ЕКАТЕРИНА АЛЕКСАНДРОВНА | D83: Счет на оплату № 43483 от 4 март 2026 г. | E83: 3907 | F83: Сальники армированные (РПМ) | G83: РТПЗ Волжский | H83: Бюджет ПЛАН | I83: Нет | K83: оплачен
A84: 26.685714
A85: 27.657143
A86: 28.628571
A87: 29.6
B88: РАСХОДЫ ПРОЧИЕ (Тех служба / Складской коммплекс / IT служба / Юр служба / Секретариат / Кадры / Маркетинг)
A89: 1 | B89: Жарков | C89: ООО «СМБ-Сервис» | D89: Счёт № ОПЛ-22381265557 ЛСС-5264829686-1 от 3 марта 2026 г. | E89: 50000 | F89: Контекстная реклама (рекл) | H89: Бюджет ПЛАН | I89: Да | K89: оплачен
A90: 2 | B90: Амитон Д.Д. | C90: ООО Компания Гэндальф | D90: счёт РГА03030027 от 03.03.2026 | E90: 18000 | F90: покупка термотрансферной ленты RESIN (расх IT) | H90: Бюджет ПЛАН | I90: Да | K90: оплачен
A91: 3 | B91: Приезжева | C91: Аква сервис | D91: счет 1413 от 03.03.2026 | E91: 16320 | F91: питьевая вода (орг) | G91: РТПЗ Волжский | H91: Бюджет ПЛАН | I91: Да | K91: оплачен
A92: 4 | B92: Приезжева | C92: МБИ Волгоград | D92: счет 19-31116 от 28.02.2026 | E92: 1182 | F92: экспресс почта | G92: РТПЗ Волжский | H92: Бюджет ПЛАН | I92: Да | K92: оплачен
A93: 5 | B93: Приезжева | C93: Мистер Пэн | D93: счет 21 от 26.02.2026 | E93: 19250 | F93: канцтовары (орг) | G93: РТПЗ Волжский | H93: Бюджет ПЛАН | I93: Да | J93: общезаводская заявка | K93: оплачен
A94: 6 | B94: Приезжева | C94: Мистер Пэн | D94: счет 24 от 26.02.2026 | E94: 4400 | F94: аптечки первой помощи (орг) | G94: РТПЗ Волжский | H94: Бюджет ПЛАН | I94: Да | J94: Охрана труда | K94: оплачен
A95: 7 | B95: Приезжева | C95: Мистер Пэн | D95: счет 22 от 26.02.2026 | E95: 3111 | F95: паста очищающая (хоз) | G95: РТПЗ Волжский | H95: Бюджет ПЛАН | I95: Да | J95: ТСЦ | K95: оплачен
A96: 8
A97: 9
A98: 10
A99: 11
A100: 12
A101: 13
A102: 14
A103: 15
B104: Бухгалтерия (Налоги / ЗП / ЕСН / прочие платежи бух. службы)
A105: 1 | B105: Лазарева Л.Ю | C105: ИФНС по ЕНП | D105: КБК 18201061201010000510 | E105: 887000 | F105: НДФЛ (период с 23.02-28.02.2026) | G105: РТПЗ Ростов | H105: Бюджет ПЛАН | J105: Крайний срок до 05.03.2026 | K105: оплачен
A106: 2
A107: 3
A108: 4
...

Sheet 05
C2: ='04'!C2+1 -> 46086
A4: ООО ТД РТПЗ | E4: =SUM(E5:E12) -> 195532.14 | F4: РЕЕСТР ЗАКРЫТ !!!
A5: Волжский счёт СБ 7503 | E5: 129274.05
A6: Головной счёт СБ 13291 | E6: 19755.66
A7: ИП Коваленко СБ 17500
A8: счёт ЦМР Банк | E8: 15821.6
A9: счёт РОСБАНК 1115 | E9: 3366.84
A10: счёт Райффайзенбанк 38867 | E10: 1395.47
A11: счёт Промсвязьбанк 5439 | E11: 21017.09
A12: счёт Альфа-Банк 10329 | E12: 4901.43
A14: № п/п | B14: Инициатор платежа | C14: Контрагент - Получатель | D14: Договор/Счет | E14: Сумма к оплате | F14: Назначение платежа | G14: Подразделение - плательщик | H14: Бюджет/Статья | I14: Наличие Договора | J14: Примечание | K14: Отметка об оплате | L14: Спец. Распоряжение
B15: Коммерческий отдел (ПОСТАВЩИКИ / ПОКУПАТЕЛИ)
A16: 1
A17: 2 | B17: Федоров А.А. | C17: Северсталь ПАО | D17: Договр № 643/1000-24100303 от 12.04.2024 | E17: 26000000 | F17: Металлопрокат
A18: 3 | B18: Федоров А.А. | C18: НЛМК ПАО | D18: Договор В204709-24 от 24.10.2024 | E18: 4652500.6 | F18: Металлопрокат | K18: оплачен
A19: 4
A20: 5
A21: 6
A22: 7
A23: 8
A24: 9
A25: 10
A26: 11
A27: 12
A28: 13
A29: 14
A30: 15
... A35: 20
B36: Коммерческий отдел (ЛОГИСТИКА / Хранение / ПРР)
A37: 1
A38: 2
A39: 3
A40: 4
A41: 5
A42: 6
A43: 7
A44: 8
A45: 9
A46: 10
A47: 11
A48: 12
... A56: 20
B57: ПРОИЗВОДСТВЕННЫЙ комплекс / ТЕХ служба
A58: 1
A59: 2
A60: 3
A61: 4
A62: 5
A63: 6
A64: 7
A65: 8
A66: 9
A67: 10
A68: 11
A69: 12
... A72: 15
B73: РАСХОДЫ ПРОЧИЕ (Тех служба / Складской коммплекс / IT служба / Юр служба / Секретариат / Кадры / Маркетинг)
A74: 1 | B74: Патлачева Н.В. | C74: Федеральная нотариальная палата | D74: по реквизитам | E74: 600 | F74: за регистрацию уведомления о залоге (госуслуги) | K74: оплачен
A75: 2
A76: 3
A77: 4
A78: 5
A79: 6
A80: 7
A81: 8
A82: 9
A83: 10
A84: 11
A85: 12
A86: 13
... A88: 15
B89: Бухгалтерия (Налоги / ЗП / ЕСН / прочие платежи бух. службы)
A90: 1 | B90: Лазарева Л.Ю | C90: Сбер Волжский | D90: реестр | E90: 121336.1 | F90: Отпускные за март 2026г | G90: РТПЗ Волжский | H90: Бюджет ПЛАН | K90: оплачен
A91: 2 | B91: Лазарева Л.Ю | C91: Тинькофф | D91: отдельным платежом | E91: 40684.6 | F91: Отпускные за март 2026г | G91: РТПЗ Волжский | H91: Бюджет ПЛАН | K91: оплачен
A92: 3 | B92: Лазарева Л.Ю | C92: Сбер Ростов | D92: реестр | E92: 42204.36 | F92: Отпускные за март 2026г | G92: РТПЗ Ростов | H92: Бюджет ПЛАН | K92: оплачен
A93: 4 | B93: Лазарева Л.Ю | C93: Сбер Волжский | D93: реестр | E93: 5000 | F93: Мат.помощь в связи со смертью матери | G93: РТПЗ Волжский | H93: Внебюджет | K93: оплачен
A94: 5
A95: 6
A96: 7
A97: 8
A98: 9
A99: 10
B100: ФЭО (Кредиты/ Лизинг / Проценты / прочие платежи)
A101: 1
A102: 2
A103: 3
A104: 4
A105: 5
A106: ИТОГО ТД РТПЗ РАСХОДЫ ПО РЕЕСТРУ | E106: =SUM(E15:E105) -> 30862326
A107: ДЕФИЦИТ / ПРОФИЦИТ с Остатка на начало дня | E107: =E4-E106 -> -30666794
A109: ООО ЖИВАЯ СТАЛЬ | E109: =SUM(E110:E113) -> 708640.62
A110: счёт СБ 1125 | E110: 708640.62
A115: № п/п | B115: Инициатор платежа | C115: Контрагент - Получатель | D115: Договор/Счет | E115: Сумма к оплате | F115: Назначение платежа | G115: Подразделение - плательщик | H115: Бюджет/Статья | I115: Наличие Договора | J115: Примечание | K115: Отметка об оплате | L115: Спец. Распоряжение
B116: Коммерческий отдел (Закупка товара / Логистика / Снабжение/ ВЭД / Хранение / ПРР / Маркетинг)
A117: 1
A118: 2
A119: 3
A120: 4
A121: 5
A122: 6
...

Sheet 06
C2: ='05'!C2+1 -> 46087
A4: ООО ТД РТПЗ | E4: =SUM(E5:E12) -> 9549260.8 | F4: РЕЕСТР ЗАКРЫТ !!!
A5: Волжский счёт СБ 7503 | E5: 9486369.6
A6: Головной счёт СБ 13291 | E6: 19755.66
A7: ИП Коваленко СБ 17500
A8: счёт ЦМР Банк | E8: 15821.6
A9: счёт РОСБАНК 1115 | E9: 0
A10: счёт Райффайзенбанк 38867 | E10: 1395.47
A11: счёт Промсвязьбанк 5439 | E11: 21017.09
A12: счёт Альфа-Банк 10329 | E12: 4901.43
A14: № п/п | B14: Инициатор платежа | C14: Контрагент - Получатель | D14: Договор/Счет | E14: Сумма к оплате | F14: Назначение платежа | G14: Подразделение - плательщик | H14: Бюджет/Статья | I14: Наличие Договора | J14: Примечание | K14: Отметка об оплате | L14: Спец. Распоряжение
B15: Коммерческий отдел (ПОСТАВЩИКИ / ПОКУПАТЕЛИ)
A16: 1
A17: 2 | B17: Федоров А.А. | C17: Северсталь ПАО | D17: Договр № 643/1000-24100303 от 12.04.2024 | E17: 26000000 | F17: Металлопрокат
A18: 3
A19: 4
A20: 5
A21: 6
A22: 7
A23: 8
A24: 9
A25: 10
A26: 11
A27: 12
A28: 13
A29: 14
... A35: 20
B36: Коммерческий отдел (ЛОГИСТИКА / Хранение / ПРР)
A37: 1
A38: 2
A39: 3
A40: 4
A41: 5
A42: 6
A43: 7
A44: 8
A45: 9
A46: 10
A47: 11
A48: 12
... A56: 20
B57: ПРОИЗВОДСТВЕННЫЙ комплекс / ТЕХ служба
A58: 1 | B58: Стадников | C58: ООО Лайт Моторс | D58: счет №TR-5983 от 06.03.2026 | E58: 46000 | F58: автошины БМВ Х5 (Метком) | G58: РТПЗ Ростов | H58: Бюджет МЕТКОМ | K58: оплачен
A59: 2
A60: 3
A61: 4
A62: 5
A63: 6
A64: 7
A65: 8
A66: 9
A67: 10
A68: 11
A69: 12
A70: 13
... A72: 15
B73: РАСХОДЫ ПРОЧИЕ (Тех служба / Складской коммплекс / IT служба / Юр служба / Секретариат / Кадры / Маркетинг)
A74: 1
A75: 2
A76: 3
A77: 4
A78: 5
A79: 6
A80: 7
A81: 8
A82: 9
A83: 10
A84: 11
A85: 12
... A88: 15
B89: Бухгалтерия (Налоги / ЗП / ЕСН / прочие платежи бух. службы)
A90: 1 | B90: Лазарева Л.Ю | C90: Сбер Волжский | D90: реестр | E90: 132000 | F90: Единовременная премия к 8 марта | G90: РТПЗ Волжский | H90: Бюджет ПЛАН | K90: оплачен
A91: 2 | B91: Лазарева Л.Ю | C91: на карту третьих лиц/Реквизиты на карту Миллер Светланы | D91: отдельным платежом | E91: 3000 | F91: Единовременная премия к 8 марта | G91: РТПЗ Волжский | H91: Бюджет ПЛАН | K91: оплачен
A92: 3 | B92: Лазарева Л.Ю | C92: на карту третьих лиц/Реквизиты на карту Книпенберг Марины | D92: отдельным платежом | E92: 3000 | F92: Единовременная премия к 8 марта | G92: РТПЗ Волжский | H92: Бюджет ПЛАН | K92: оплачен
A93: 4
A94: 5
A95: 6
A96: 7
A97: 8
A98: 9
A99: 10
B100: ФЭО (Кредиты/ Лизинг / Проценты / прочие платежи)
A101: 1
A102: 2
A103: 3
A104: 4
A105: 5
A106: ИТОГО ТД РТПЗ РАСХОДЫ ПО РЕЕСТРУ | E106: =SUM(E15:E105) -> 26184000
A107: ДЕФИЦИТ / ПРОФИЦИТ с Остатка на начало дня | E107: =E4-E106 -> -16634739
A109: ООО ЖИВАЯ СТАЛЬ | E109: =SUM(E110:E113) -> 708640.62
A110: счёт СБ 1125 | E110: 708640.62
A115: № п/п | B115: Инициатор платежа | C115: Контрагент - Получатель | D115: Договор/Счет | E115: Сумма к оплате | F115: Назначение платежа | G115: Подразделение - плательщик | H115: Бюджет/Статья | I115: Наличие Договора | J115: Примечание | K115: Отметка об оплате | L115: Спец. Распоряжение
B116: Коммерческий отдел (Закупка товара / Логистика / Снабжение/ ВЭД / Хранение / ПРР / Маркетинг)
A117: 1
A118: 2
A119: 3
A120: 4
A121: 5
A122: 6
A123: 7
...

Sheet 07
C2: ='06'!C2+1 -> 46088
A4: ООО ТД РТПЗ | E4: =SUM(E5:E12) -> 0
A5: Волжский счёт СБ 7503
A6: Головной счёт СБ 13291
A7: ИП Коваленко СБ 17500
A8: счёт ЦМР Банк
A9: счёт РОСБАНК 1115
A10: счёт Райффайзенбанк 38867
A11: счёт Промсвязьбанк 5439
A12: счёт Альфа-Банк 10329
A14: № п/п | B14: Инициатор платежа | C14: Контрагент - Получатель | D14: Договор/Счет | E14: Сумма к оплате | F14: Назначение платежа | G14: Подразделение - плательщик | H14: Бюджет/Статья | I14: Наличие Договора | J14: Примечание | K14: Отметка об оплате | L14: Спец. Распоряжение
B15: Коммерческий отдел (ПОСТАВЩИКИ / ПОКУПАТЕЛИ)
A16: 1
A17: 2
A18: 3
A19: 4
A20: 5
A21: 6
A22: 7
A23: 8
A24: 9
A25: 10
A26: 11
A27: 12
... A35: 20
B36: Коммерческий отдел (ЛОГИСТИКА / Хранение / ПРР)
A37: 1
A38: 2
A39: 3
A40: 4
A41: 5
A42: 6
A43: 7
A44: 8
A45: 9
A46: 10
A47: 11
A48: 12
... A56: 20
B57: ПРОИЗВОДСТВЕННЫЙ комплекс / ТЕХ служба
A58: 1
A59: 2
A60: 3
A61: 4
A62: 5
A63: 6
A64: 7
A65: 8
A66: 9
A67: 10
A68: 11
A69: 12
... A72: 15
B73: РАСХОДЫ ПРОЧИЕ (Тех служба / Складской коммплекс / IT служба / Юр служба / Секретариат / Кадры / Маркетинг)
A74: 1
A75: 2
A76: 3
A77: 4
A78: 5
A79: 6
A80: 7
A81: 8
A82: 9
A83: 10
A84: 11
A85: 12
... A88: 15
B89: Бухгалтерия (Налоги / ЗП / ЕСН / прочие платежи бух. службы)
A90: 1
A91: 2
A92: 3
A93: 4
A94: 5
A95: 6
A96: 7
A97: 8
A98: 9
A99: 10
B100: ФЭО (Кредиты/ Лизинг / Проценты / прочие платежи)
A101: 1
A102: 2
A103: 3
A104: 4
A105: 5
A106: ИТОГО ТД РТПЗ РАСХОДЫ ПО РЕЕСТРУ | E106: =SUM(E15:E105) -> 0
A107: ДЕФИЦИТ / ПРОФИЦИТ с Остатка на начало дня | E107: =E4-E106 -> 0
A109: ООО ЖИВАЯ СТАЛЬ | E109: =SUM(E110:E113) -> 0
A110: счёт СБ 1125
A115: № п/п | B115: Инициатор платежа | C115: Контрагент - Получатель | D115: Договор/Счет | E115: Сумма к оплате | F115: Назначение платежа | G115: Подразделение - плательщик | H115: Бюджет/Статья | I115: Наличие Договора | J115: Примечание | K115: Отметка об оплате | L115: Спец. Распоряжение
B116: Коммерческий отдел (Закупка товара / Логистика / Снабжение/ ВЭД / Хранение / ПРР / Маркетинг)
A117: 1
A118: 2
A119: 3
A120: 4
A121: 5
A122: 6
A123: 7
A124: 8
A125: 9
A126: 10
...

Sheet 08
C2: ='07'!C2+1 -> 46089
A4: ООО ТД РТПЗ | E4: =SUM(E5:E12) -> 0
A5: Волжский счёт СБ 7503
A6: Головной счёт СБ 13291
A7: ИП Коваленко СБ 17500
A8: счёт ЦМР Банк
A9: счёт РОСБАНК 1115
A10: счёт Райффайзенбанк 38867
A11: счёт Промсвязьбанк 5439
A12: счёт Альфа-Банк 10329
A14: № п/п | B14: Инициатор платежа | C14: Контрагент - Получатель | D14: Договор/Счет | E14: Сумма к оплате | F14: Назначение платежа | G14: Подразделение - плательщик | H14: Бюджет/Статья | I14: Наличие Договора | J14: Примечание | K14: Отметка об оплате | L14: Спец. Распоряжение
B15: Коммерческий отдел (ПОСТАВЩИКИ / ПОКУПАТЕЛИ)
A16: 1
A17: 2
A18: 3
A19: 4
A20: 5
A21: 6
A22: 7
A23: 8
A24: 9
A25: 10
A26: 11
A27: 12
... A35: 20
B36: Коммерческий отдел (ЛОГИСТИКА / Хранение / ПРР)
A37: 1
A38: 2
A39: 3
A40: 4
A41: 5
A42: 6
A43: 7
A44: 8
A45: 9
A46: 10
A47: 11
A48: 12
... A56: 20
B57: ПРОИЗВОДСТВЕННЫЙ комплекс / ТЕХ служба
A58: 1
A59: 2
A60: 3
A61: 4
A62: 5
A63: 6
A64: 7
A65: 8
A66: 9
A67: 10
A68: 11
A69: 12
... A72: 15
B73: РАСХОДЫ ПРОЧИЕ (Тех служба / Складской коммплекс / IT служба / Юр служба / Секретариат / Кадры / Маркетинг)
A74: 1
A75: 2
A76: 3
A77: 4
A78: 5
A79: 6
A80: 7
A81: 8
A82: 9
A83: 10
A84: 11
A85: 12
... A88: 15
B89: Бухгалтерия (Налоги / ЗП / ЕСН / прочие платежи бух. службы)
A90: 1
A91: 2
A92: 3
A93: 4
A94: 5
A95: 6
A96: 7
A97: 8
A98: 9
A99: 10
B100: ФЭО (Кредиты/ Лизинг / Проценты / прочие платежи)
A101: 1
A102: 2
A103: 3
A104: 4
A105: 5
A106: ИТОГО ТД РТПЗ РАСХОДЫ ПО РЕЕСТРУ | E106: =SUM(E15:E105) -> 0
A107: ДЕФИЦИТ / ПРОФИЦИТ с Остатка на начало дня | E107: =E4-E106 -> 0
A109: ООО ЖИВАЯ СТАЛЬ | E109: =SUM(E110:E113) -> 0
A110: счёт СБ 1125
A115: № п/п | B115: Инициатор платежа | C115: Контрагент - Получатель | D115: Договор/Счет | E115: Сумма к оплате | F115: Назначение платежа | G115: Подразделение - плательщик | H115: Бюджет/Статья | I115: Наличие Договора | J115: Примечание | K115: Отметка об оплате | L115: Спец. Распоряжение
B116: Коммерческий отдел (Закупка товара / Логистика / Снабжение/ ВЭД / Хранение / ПРР / Маркетинг)
A117: 1
A118: 2
A119: 3
A120: 4
A121: 5
A122: 6
A123: 7
A124: 8
A125: 9
A126: 10
...

Sheet 09
C2: ='08'!C2+1 -> 46090
A4: ООО ТД РТПЗ | E4: =SUM(E5:E12) -> 0
A5: Волжский счёт СБ 7503
A6: Головной счёт СБ 13291
A7: ИП Коваленко СБ 17500
A8: счёт ЦМР Банк
A9: счёт РОСБАНК 1115
A10: счёт Райффайзенбанк 38867
A11: счёт Промсвязьбанк 5439
A12: счёт Альфа-Банк 10329
A14: № п/п | B14: Инициатор платежа | C14: Контрагент - Получатель | D14: Договор/Счет | E14: Сумма к оплате | F14: Назначение платежа | G14: Подразделение - плательщик | H14: Бюджет/Статья | I14: Наличие Договора | J14: Примечание | K14: Отметка об оплате | L14: Спец. Распоряжение
B15: Коммерческий отдел (ПОСТАВЩИКИ / ПОКУПАТЕЛИ)
A16: 1
A17: 2
A18: 3
A19: 4
A20: 5
A21: 6
A22: 7
A23: 8
A24: 9
A25: 10
A26: 11
A27: 12
... A35: 20
B36: Коммерческий отдел (ЛОГИСТИКА / Хранение / ПРР)
A37: 1
A38: 2
A39: 3
A40: 4
A41: 5
A42: 6
A43: 7
A44: 8
A45: 9
A46: 10
A47: 11
A48: 12
... A56: 20
B57: ПРОИЗВОДСТВЕННЫЙ комплекс / ТЕХ служба
A58: 1
A59: 2
A60: 3
A61: 4
A62: 5
A63: 6
A64: 7
A65: 8
A66: 9
A67: 10
A68: 11
A69: 12
... A72: 15
B73: РАСХОДЫ ПРОЧИЕ (Тех служба / Складской коммплекс / IT служба / Юр служба / Секретариат / Кадры / Маркетинг)
A74: 1
A75: 2
A76: 3
A77: 4
A78: 5
A79: 6
A80: 7
A81: 8
A82: 9
A83: 10
A84: 11
A85: 12
... A88: 15
B89: Бухгалтерия (Налоги / ЗП / ЕСН / прочие платежи бух. службы)
A90: 1
A91: 2
A92: 3
A93: 4
A94: 5
A95: 6
A96: 7
A97: 8
A98: 9
A99: 10
B100: ФЭО (Кредиты/ Лизинг / Проценты / прочие платежи)
A101: 1
A102: 2
A103: 3
A104: 4
A105: 5
A106: ИТОГО ТД РТПЗ РАСХОДЫ ПО РЕЕСТРУ | E106: =SUM(E15:E105) -> 0
A107: ДЕФИЦИТ / ПРОФИЦИТ с Остатка на начало дня | E107: =E4-E106 -> 0
A109: ООО ЖИВАЯ СТАЛЬ | E109: =SUM(E110:E113) -> 0
A110: счёт СБ 1125
A115: № п/п | B115: Инициатор платежа | C115: Контрагент - Получатель | D115: Договор/Счет | E115: Сумма к оплате | F115: Назначение платежа | G115: Подразделение - плательщик | H115: Бюджет/Статья | I115: Наличие Договора | J115: Примечание | K115: Отметка об оплате | L115: Спец. Распоряжение
B116: Коммерческий отдел (Закупка товара / Логистика / Снабжение/ ВЭД / Хранение / ПРР / Маркетинг)
A117: 1
A118: 2
A119: 3
A120: 4
A121: 5
A122: 6
A123: 7
A124: 8
A125: 9
A126: 10
...

Sheet 10
C2: ='09'!C2+1 -> 46091
A4: ООО ТД РТПЗ | E4: =SUM(E5:E12) -> 980754.35 | F4: РЕЕСТР ЗАКРЫТ !!!
A5: Волжский счёт СБ 7503 | E5: 917863.1
A6: Головной счёт СБ 13291 | E6: 19755.66
A7: ИП Коваленко СБ 17500
A8: счёт ЦМР Банк | E8: 15821.6
A9: счёт РОСБАНК 1115 | E9: 0
A10: счёт Райффайзенбанк 38867 | E10: 1395.47
A11: счёт Промсвязьбанк 5439 | E11: 21017.09
A12: счёт Альфа-Банк 10329 | E12: 4901.43
A14: № п/п | B14: Инициатор платежа | C14: Контрагент - Получатель | D14: Договор/Счет | E14: Сумма к оплате | F14: Назначение платежа | G14: Подразделение - плательщик | H14: Бюджет/Статья | I14: Наличие Договора | J14: Примечание | K14: Отметка об оплате | L14: Спец. Распоряжение
B15: Коммерческий отдел (ПОСТАВЩИКИ / ПОКУПАТЕЛИ)
A16: 1 | I16: Да | J16: с райффайзена
A17: 2 | B17: Федоров А.А. | C17: Северсталь ПАО | D17: Договр № 643/1000-24100303 от 12.04.2024 | E17: .26000000 | F17: Металлопрокат
A18: 3
A19: 4
A20: 5
A21: 6
A22: 7
A23: 8
A24: 9
A25: 10
A26: 11
A27: 12
A28: 13
A29: 14
... A35: 20
B36: Коммерческий отдел (ЛОГИСТИКА / Хранение / ПРР)
A37: 1
A38: 2
A39: 3
A40: 4
A41: 5
A42: 6
A43: 7
A44: 8
A45: 9
A46: 10
A47: 11
A48: 12
... A56: 20
B57: ПРОИЗВОДСТВЕННЫЙ комплекс / ТЕХ служба
A58: 1
A59: 2
A60: 3
A61: 4
A62: 5
A63: 6
A64: 7
A65: 8
A66: 9
A67: 10
A68: 11
A69: 12
... A72: 15
B73: РАСХОДЫ ПРОЧИЕ (Тех служба / Складской коммплекс / IT служба / Юр служба / Секретариат / Кадры / Маркетинг)
A74: 1
A75: 2
A76: 3
A77: 4
A78: 5
A79: 6
A80: 7
A81: 8
A82: 9
A83: 10
A84: 11
A85: 12
... A88: 15
B89: Бухгалтерия (Налоги / ЗП / ЕСН / прочие платежи бух. службы)
A90: 1 | B90: Лазарева Л.Ю | C90: На карту третьих лиц /Реквизиты Миллер Светланы Александровны | D90: отдельным платежом | E90: 34804.92 | F90: Зар.плата за февраль 2026г | G90: РТПЗ Волжский | H90: Бюджет | K90: оплачен
A91: 2 | B91: Лазарева Л.Ю | C91: На карту третьих лиц /Реквизиты Марьиной Надежды Александровны | D91: отдельным платежом | E91: 20325.73 | F91: Зар.плата за февраль 2026г | G91: РТПЗ Волжский | H91: Бюджет | K91: оплачен
A92: 3 | B92: Лазарева Л.Ю | C92: На карту третьих лиц /Реквизиты Олейниковой Кристины Денисовны | D92: отдельным платежом | E92: 37788.21 | F92: Зар.плата за февраль 2026г | G92: РТПЗ Волжский | H92: Бюджет | K92: оплачен
A93: 4 | B93: Лазарева Л.Ю | C93: На карту третьих лиц /Реквизиты Книпенберг Марины Николаевны | D93: отдельным платежом | E93: 25545.77 | F93: Зар.плата за февраль 2026г | G93: РТПЗ Волжский | H93: Бюджет | K93: оплачен
A94: 5 | B94: Лазарева Л.Ю | C94: На карту третьих лиц /Реквизиты Новикова Валентина Ивановича | D94: отдельным платежом | E94: 9782.75 | F94: Зар.плата за февраль 2026г | G94: РТПЗ Волжский | H94: Бюджет | K94: оплачен
A95: 6 | B95: Лазарева Л.Ю | C95: ВТБ | D95: отдельным платежом | E95: 218022.04 | F95: Зар.плата за февраль 2026г | G95: РТПЗ Волжский | H95: Бюджет | K95: оплачен
A96: 7 | B96: Лазарева Л.Ю | C96: Альфа-Банк | D96: отдельным платежом | E96: 119937.86 | F96: Зар.плата за февраль 2026г | G96: РТПЗ Волжский | H96: Бюджет | K96: оплачен
A97: 8 | B97: Лазарева Л.Ю | C97: Россельхозбанк | D97: отдельным платежом | E97: 20737.03 | F97: Зар.плата за февраль 2026г | G97: РТПЗ Волжский | H97: Бюджет | K97: оплачен
A98: 9 | B98: Лазарева Л.Ю | C98: Озон Банк | D98: отдельным платежом | E98: 4484.78 | F98: Зар.плата за февраль 2026г | G98: РТПЗ Волжский | H98: Бюджет | K98: оплачен
A99: 10 | B99: Лазарева Л.Ю | C99: Тинькофф Банк | D99: отдельным платежом | E99: 208912.44 | F99: Зар.плата за февраль 2026г | G99: РТПЗ Волжский | H99: Бюджет | J99: В п/п у Жильцова НАЗНАЧЕНИЕ ПЛАТЕЖА: Код в назначении 1 //ВЗС//25135-46// | K99: оплачен
A100: 11 | B100: Лазарева Л.Ю | C100: Совкомбанк | D100: отдельным платежом | E100: 49043.36 | F100: Зар.плата за февраль 2026г | G100: РТПЗ Волжский | H100: Бюджет | J100: В п/п у Шибитова НАЗНАЧЕНИЕ ПЛАТЕЖА: Код в назначении 1 //ВЗС//78744-16// | K100: оплачен
A101: 12 | B101: Лазарева Л.Ю | C101: БАНК ПСБ | D101: отдельным платежом | E101: 11417.96 | F101: Зар.плата за февраль 2026г | G101: РТПЗ Волжский | H101: Бюджет | K101: оплачен
A102: 13 | B102: Лазарева Л.Ю | C102: Сбер Волжский | D102: реестр | E102: 6587484.4 | F102: Зар.плата за февраль 2026г | G102: РТПЗ Волжский | H102: Бюджет | K102: оплачен
A103: 14 | B103: Лазарева Л.Ю | C103: Банк Уралсиб | D103: отдельным платежом | E103: 19207.44 | F103: Зар.плата за февраль 2026г | G103: РТПЗ Волжский | H103: Бюджет | K103: оплачен
A104: 15 | B104: Лазарева Л.Ю | C104: Сбер Волжский/Болотин | D104: реестр | E104: 2610 | F104: Аренда транспорта с экипажем (пр тс) | G104: РТПЗ Волжский | H104: Бюджет | K104: оплачен
A105: 16 | B105: Лазарева Л.Ю | C105: ВТБ/ Машков Б.И | D105: отдельным платежом | E105: 435 | F105: Аренда транспорта без экипажа (пр тс) | G105: РТПЗ Волжский | H105: Бюджет | K105: оплачен
A106: 17 | B106: Лазарева Л.Ю | C106: Волжский ГОСП №2 УФССП России по Волгоградской области | D106: Испол.лист | E106: 72.5 | F106: Удержание из аренды транспорта Машкова Б. И (пр тс) | G106: РТПЗ Волжский | H106: Бюджет | K106: оплачен
A107: 18 | B107: Лазарева Л.Ю | C107: Волжский ГОСП №2 УФССП России по Волгоградской области | D107: Испол.лист | E107: 72.5 | F107: Удержание из аренды транспорта Машкова Б. И (пр тс) | G107: РТПЗ Волжский | H107: Бюджет | K107: оплачен
A108: 19 | B108: Лазарева Л.Ю | C108: ИФНС по г.Волжскому Волгоградской обл. | D108: Испол.лист | E108: 72.5 | F108: Удержание из аренды транспорта Машкова Б. И (пр тс) | G108: РТПЗ Волжский | H108: Бюджет | K108: оплачен
A109: 20 | B109: Лазарева Л.Ю | C109: ИФНС по г.Волжскому Волгоградской обл. | D109: Испол.лист | E109: 72.5 | F109: Удержание из аренды транспорта Машкова Б. И (пр тс) | G109: РТПЗ Волжский | H109: Бюджет | K109: оплачен
A110: 21 | B110: Лазарева Л.Ю | C110: Волжский ГОСП №2 УФССП России по Волгоградской области | D110: Испол.лист | E110: 72.5 | F110: Удержание из аренды транспорта Машкова Б. И (пр тс) | G110: РТПЗ Волжский | H110: Бюджет | K110: оплачен
A111: 22 | B111: Лазарева Л.Ю | C111: Волжский ГОСП №2 УФССП России по Волгоградской области | D111: Испол.лист | E111: 72.5 | F111: Удержание из аренды транспорта Машкова Б. И (пр тс) | G111: РТПЗ Волжский | H111: Бюджет | K111: оплачен
A112: 23 | B112: Лазарева Л.Ю | C112: Шибанова Татьяна Ильинична | D112: Испол.лист | E112: 24530.27 | F112: Удержание из з/платы Титова А.В | G112: РТПЗ Волжский | H112: Бюджет | K112: оплачен
... A143: 54 | B143: Лазарева Л.Ю | C143: Сбер Ростов | D143: реестр | E143: 1505505.8 | F143: Зар.плата за февраль 2026г | G143: РТПЗ Ростов | H143: Бюджет | K143: оплачен
A144: 56
A145: 57 | B145: Лазарева Л.Ю | C145: ИФНС по ЕНП | D145: КБК 18201061201010000510 | E145: 8130 | F145: Страх.взносы за февраль 2026г | G145: ПО РТПЗ | K145: оплачен 06.03
A146: 58
A147: 59
B148: ФЭО (Кредиты/ Лизинг / Проценты / прочие платежи)
A149: 1
...

Sheet 11
C2: ='10'!C2+1 -> 46092
A4: ООО ТД РТПЗ | E4: =SUM(E5:E12) -> 1090296.2 | F4: РЕЕСТР ЗАКРЫТ !!!
A5: Волжский счёт СБ 7503 | E5: 990305.48
A6: Головной счёт СБ 13291 | E6: 19755.66
A7: ИП Коваленко СБ 17500
A8: счёт ЦМР Банк | E8: 15821.6
A9: счёт РОСБАНК 1115 | E9: 0
A10: счёт Райффайзенбанк 38867 | E10: 1395.47
A11: счёт Промсвязьбанк 5439 | E11: 21017.09
A12: счёт Альфа-Банк 10329 | E12: 42000.93
A14: № п/п | B14: Инициатор платежа | C14: Контрагент - Получатель | D14: Договор/Счет | E14: Сумма к оплате | F14: Назначение платежа | G14: Подразделение - плательщик | H14: Бюджет/Статья | I14: Наличие Договора | J14: Примечание | K14: Отметка об оплате | L14: Спец. Распоряжение
B15: Коммерческий отдел (ПОСТАВЩИКИ / ПОКУПАТЕЛИ)
A16: 1 | B16: Дынник | C16: ООО "Группа Компаний Демидов" | D16: СЧЕТ № ФИЛ26-432101 от 10.03.26 | E16: 82628 | F16: Труба профильная (2 сорт) (некондиция. упаковка) | G16: РТПЗ Волжский | I16: Да | J16: В счете не указан договор - Договор поставки №15032021/2217 от 15.03.2021 | K16: оплачен
A17: 2 | B17: Федоров А.А. | C17: Северсталь ПАО | D17: Договр № 643/1000-24100303 от 12.04.2024 | E17: .26000000 | F17: Металлопрокат | I17: Да
A18: 3
A19: 4
A20: 5
A21: 6
A22: 7
A23: 8
A24: 9
A25: 10
A26: 11
A27: 12
A28: 13
A29: 14
... A35: 20
B36: Коммерческий отдел (ЛОГИСТИКА / Хранение / ПРР)
A37: 1 | B37: Голка | C37: ТЛК-Групп ООО | D37: Счет №5906,5262,5620,5370 от 26.01 | E37: =56000+57000+65000+90000 -> 268000 | F37: Транспорт | G37: РТПЗ Волжский | H37: Бюджет | I37: Да | K37: оплачен
A38: 2 | B38: Голка | C38: Качурин М.О. ИП | D38: Счет №112,124,207 от 22.01 | E38: =60000+50000+50000 -> 160000 | F38: Транспорт | G38: РТПЗ Волжский | H38: Бюджет | I38: Да | K38: оплачен
A39: 3 | B39: Голка | C39: Дентро ООО | D39: Счет №6132,3973,6774,8155 от 04.02 | E39: =75000+75000+55000+85000 -> 290000 | F39: Транспорт | G39: РТПЗ Волжский | H39: Бюджет | I39: Да | K39: оплачен
A40: 4 | B40: Голка | C40: Промснаб ООО | D40: Счет №14 от 06.02 | E40: 58000 | F40: Транспорт | G40: РТПЗ Волжский | H40: Бюджет | I40: Да | K40: оплачен
A41: 5 | B41: Голка | C41: Ушаков А.С. ИП | D41: Счет №66 от 09.02 | E41: 80000 | F41: Транспорт | G41: РТПЗ Волжский | H41: Бюджет | I41: Да | K41: оплачен
A42: 6 | B42: Голка | C42: Стальстройпоставка ООО | D42: Счет №50,67,82,41,68,69 от 09.02 | E42: =95000+40000+130000+26000+40000+88000 -> 419000 | F42: Транспорт | G42: РТПЗ Волжский | H42: Бюджет | I42: Да | K42: оплачен
A43: 7 | B43: Голка | C43: АК №2 ООО | D43: Счет №1980 от 05.02 | E43: 120000 | F43: Транспорт | G43: РТПЗ Волжский | H43: Бюджет | I43: Да | K43: оплачен
A44: 8 | B44: Голка | C44: НЕО ТРАНС ООО | D44: Счет №1867 от 04.02 | E44: 100000 | F44: Транспорт | G44: РТПЗ Волжский | H44: Бюджет | I44: Да | K44: оплачен
A45: 9 | B45: Голка | C45: СКС-Групп ООО | D45: Счет №23 от 03.02 | E45: 40000 | F45: Транспорт | G45: РТПЗ Волжский | H45: Бюджет | I45: Да | K45: оплачен
A46: 10 | B46: Голка | C46: Настина Т.В. ИП | D46: Счет №18 от 08.02 | E46: 56000 | F46: Транспорт | G46: РТПЗ Волжский | H46: Бюджет | I46: Да | K46: оплачен
A47: 11 | B47: Голка | C47: Вектор-Н ООО | D47: Счет №1,36 от 04.02 | E47: =90000+95000 -> 185000 | F47: Транспорт | G47: РТПЗ Волжский | H47: Бюджет | I47: Да | K47: оплачен
A48: 12 | B48: Голка | C48: РАУТ ООО | D48: Счет №11 от 30.01 | E48: 98000 | F48: Транспорт | G48: РТПЗ Волжский | H48: Бюджет | I48: Да | K48: оплачен
A49: 13 | B49: Голка | C49: Загребная Н.В. ИП | D49: Счет №18 от 26.02 | E49: 40000 | F49: Транспорт | G49: РТПЗ Волжский | H49: Бюджет | I49: Да | K49: оплачен
A50: 14 | B50: Голка | C50: Деловые Линии ООО | D50: Счет №26-02441188005 от 03.03 | E50: 6825 | F50: Транспорт | G50: РТПЗ Волжский | H50: Бюджет | I50: Да | J50: сч.44 сразу на расходы | K50: оплачен
A51: 15 | B51: Высокова | C51: ООО Металл-Инвест | D51: Счет № 13 от 30.01.2026 | E51: 32000 | F51: Транспорт | H51: Бюджет | I51: Да | K51: оплачен
A52: 16
A53: 17
A54: 18
A55: 19
A56: 20
B57: ПРОИЗВОДСТВЕННЫЙ комплекс / ТЕХ служба
A58: 1 | B58: Дынник | C58: Спекта Интерпак | D58: Счет на оплату № 1229 от 03 марта 2026 | E58: 60975.6 | F58: Бирки (упаковка) | G58: РТПЗ Волжский | H58: Бюджет | I58: Да | K58: оплачен
A59: 2 | B59: Стадников | C59: ООО НВЭК ПБ | D59: счет №43 от 03.03.2026 | E59: 61200 | F59: экспертиза промбезопасности мостовых кранов и диагностика кран-балок (ГПМ) | G59: РТПЗ Волжский | H59: Бюджет | I59: Да | K59: оплачен
A60: 3 | B60: Стадников | C60: ООО ВПЖТ | D60: счет №57 от 28.02.2026 | E60: 3009.48 | F60: предрейсовый медосмотр (пр тс) | G60: РТПЗ Волжский | H60: Бюджет | I60: Да | K60: оплачен
A61: 4 | B61: Стадников | C61: ООО ТК Петролиум | D61: счет №145 от 05.03.2026 | E61: 150000 | F61: ГСМ | G61: РТПЗ Волжский | H61: Бюджет | I61: Да | K61: оплачен
A62: 5 | B62: Стадников | C62: ООО НП Транспортники Волгоградской области | D62: счет №193 от 28.02.2026 | E62: 8250 | F62: предрейсовый медосмотр (пр тс) | G62: РТПЗ Волжский | H62: Бюджет | I62: Да | K62: оплачен
A63: 6 | B63: Стадников | C63: ООО Экоцентр | D63: счет №ЭВ-39334 от 28.02.2026 | E63: 3503.82 | F63: вывоз ТКО (пр коммун) | G63: РТПЗ Волжский | H63: Бюджет | I63: Да | K63: оплачен
A64: 7 | B64: Стадников | C64: ИП Клюев В.Г. | D64: счет №11 от 05.03.2026 | E64: 22500 | F64: химическая очистка теплообменника (АПР) | G64: РТПЗ Волжский | H64: Бюджет | I64: Да | K64: оплачен
A65: 8 | B65: Стадников | C65: ИП Черкас Н.А. | D65: счет №YGYG1257 от 05.03.2026 | E65: 16968 | F65: запчасти БМВ Х5 (Метком) | G65: РТПЗ Ростов | H65: Бюджет МЕТКОМ | I65: Да | K65: оплачен
A66: 9 | B66: Стадников | C66: ИП Швадченко А.В. | D66: счет №88145 от 10.03.2026 | E66: 2860 | F66: ремонт БМВ Х5 (Метком) | G66: РТПЗ Ростов | H66: Бюджет МЕТКОМ | I66: Да | K66: оплачен
A67: 10 | B67: Стадников | C67: ИП Шаповалов Г.В. | D67: счет №43 от 10.03.2026 | E67: 11432.12 | F67: запчасти каравелла (Метком) | G67: РТПЗ Ростов | H67: Бюджет МЕТКОМ | I67: Да | K67: оплачен
A68: 11 | B68: Стадников | C68: ИП Шаповалов Г.В. | D68: счет №29 от 26.02.2026 | E68: 28690 | F68: ремонт каравелла (Метком) | G68: РТПЗ Ростов | H68: Бюджет МЕТКОМ | I68: Да | K68: оплачен
A69: 12 | B69: Дынник | C69: ООО "ТД "Антей" | D69: Спецификация №8 от 27.02.2026 | E69: 79000 | F69: Аванс за пилы дисковые (АПР) | G69: РТПЗ Волжский | H69: Бюджет | I69: Да | J69: Сумма по реестру | K69: оплачен
A70: 13 | B70: Дынник | C70: ООО "Агрисовгаз" | D70: Спецификация №6 от 03.03.2026 | E70: 193625.6 | F70: Аванс за шайбы (АПР) | G70: РТПЗ Волжский | H70: Бюджет | I70: Да | J70: Сумма по реестру | K70: оплачен
A71: 14 | B71: Дынник | C71: ООО "ПРОМСТРОЙАВТОМАТИКА" | D71: Счет-фактура №161 от 20.02.2026 | E71: 41000 | F71: Замки (Упаковка) | G71: РТПЗ Волжский | H71: Бюджет | I71: Да | K71: оплачен
A72: 15 | B72: Дынник | C72: Интернет Решения | D72: Счет-Оферта № 0164150363-0049 от 11.03.2026 | E72: 2605 | F72: Костюм женский (Спецодежда) | G72: РТПЗ Волжский | H72: Бюджет | I72: Да | K72: оплачен
A73: 16 | B73: Любимов Ю.В. | C73: ООО ОП Кристалл групп | D73: Счет № 20 от 02.02.2026 г. | E73: 320000 | F73: Услуги по охране согл договору №30/12/-1 от 30.12.2019 г. за Февраль 2026г. (орг) | G73: РТПЗ Волжский | H73: Бюджет | I73: Да | K73: оплачен
A74: 17 | B74: Любимов Ю.В. | C74: ООО Центрэнерго | D74: Договор №40ЭС-20 от 15.10.2020 г. | E74: 12000 | F74: реквизиты АБ Россия за потребление электроэнергии в марте 2026 г. | G74: РТПЗ Волжский | H74: Бюджет | I74: Да | J74: КОД | K74: оплачен
A75: 18 | B75: Любимов Ю.В. | C75: ООО Волжскпромжелдортранс-Экспедитор | D75: счет № 27 от 28.02.2026 | E75: 37543.91 | F75: Транспортно-экспедиционные услуги за 3 декаду февраля 2026 года (ЖД) | G75: РТПЗ Волжский | H75: Бюджет | I75: Да | K75: оплачен
A76: 19
A77: 20
B78: РАСХОДЫ ПРОЧИЕ (Тех служба / Складской коммплекс / IT служба / Юр служба / Секретариат / Кадры / Маркетинг)
A79: 1 | B79: Гаркушенко | C79: Выростокова | E79: 40800 | F79: командировочные Казань | G79: РТПЗ Ростов | H79: Бюджет | K79: оплачен
A80: 2 | B80: Приезжева | C80: Мистер Пэн | D80: счет 26 от 26.02.2026 | E80: .126 | F80: чайники (орг) | G80: РТПЗ Волжский | H80: Бюджет | I80: Да | J80: ТСЦ, СУ
A81: 3 | B81: Амитон Д.Д. | C81: ПАО Мегафон | D81: счёт 72600253063/400 от 28.02.2026 | E81: 1525 | F81: оплата услуг связи (8-800) | G81: РТПЗ Ростов | H81: Бюджет | I81: Да | K81: оплачен
A82: 4 | B82: Амитон Д.Д. | C82: ПАО Мегафон | D82: счёт 420078146583 от 28.02.26 | E82: 17870.2 | F82: оплата услуг связи | G82: РТПЗ Ростов | H82: Бюджет | I82: Да | K82: оплачен
A83: 5 | B83: Амитон Д.Д. | C83: ООО Яндекс 360 для бизнеса | D83: счёт ЛС-5001351528-1 от 11 марта 2026 г. | E83: 23887 | F83: оплата доступа к сервису электронной почты (расх IT) | G83: РТПЗ Ростов | H83: Бюджет | I83: Да | K83: оплачен
A84: 6
A85: 7
A86: 8
A87: 9
A88: 10
A89: 11
A90: 12
A91: 13
A92: 14
A93: 15
B94: Бухгалтерия (Налоги / ЗП / ЕСН / прочие платежи бух. службы)
A95: 1 | B95: Ермолина Е.В | C95: Стадников А.Ю. | D95: авансовый отчет | E95: 2696 | F95: ТО автомобиля Каравелла | H95: Бюджет МЕТКОМ | K95: оплачен
A96: 2 | B96: Лазарева Л.Ю | C96: ОСФР ПО РОСТОВСКОЙ ОБЛАСТИ , Л/С 04584Ф58010) | D96: КБК 79710212000061000160 | E96: 263750 | F96: Страховые взносы по НС и ПЗ за февраль 2026г (налоги с фот) | G96: РТПЗ Ростов | H96: Бюджет | J96: Крайний срок 16.03.2026 | K96: оплачен
A97: 3
A98: 4
A99: 5
A100: 6
A101: 7
A102: 8
A103: 9
A104: 10
B105: ФЭО (Кредиты/ Лизинг / Проценты / прочие платежи)
A106: 1 | B106: Панфилова Е.О. | C106: СБЕР | D106: 7M-520KROD-XVL от 05.12.2025 | E106: 1293275 | F106: %% по оверу | H106: Бюджет
A107: 2
A108: 3
...

Sheet 12
C2: ='11'!C2+1 -> 46093
A4: ООО ТД РТПЗ | E4: =SUM(E5:E12) -> 23890461 | F4: РЕЕСТР ЗАКРЫТ !!!
A5: Волжский счёт СБ 7503 | E5: 15778008
A6: Головной счёт СБ 13291 | E6: 19755.66
A7: ИП Коваленко СБ 17500
A8: счёт ЦМР Банк | E8: 15821.6
A9: счёт РОСБАНК 1115 | E9: 0
A10: счёт Райффайзенбанк 38867 | E10: 4585965.3
A11: счёт Промсвязьбанк 5439 | E11: 3448909
A12: счёт Альфа-Банк 10329 | E12: 42000.93
A14: № п/п | B14: Инициатор платежа | C14: Контрагент - Получатель | D14: Договор/Счет | E14: Сумма к оплате | F14: Назначение платежа | G14: Подразделение - плательщик | H14: Бюджет/Статья | I14: Наличие Договора | J14: Примечание | K14: Отметка об оплате | L14: Спец. Распоряжение
B15: Коммерческий отдел (ПОСТАВЩИКИ / ПОКУПАТЕЛИ)
A16: 1 | B16: Татевосян | C16: Ереванский завод стальных труб Металл Стиль ЗАО | D16: Письмо от 27.02.2026 | E16: 157343.24 | F16: возврат по письму | I16: Да | K16: оплачен
A17: 2 | B17: Федоров А.А. | C17: Северсталь ПАО | D17: Договр № 643/1000-24100303 от 12.04.2024 | E17: .26000000 | F17: Металлопрокат | I17: Да
A18: 3 | B18: Федоров А.А. | C18: НЛМК ПАО | D18: Договор №204709-23 от 15.03.2023 | E18: 6000000 | F18: Металлопрокат | I18: Да | K18: оплачен
A19: 4
A20: 5
A21: 6
A22: 7
A23: 8
A24: 9
A25: 10
A26: 11
A27: 12
A28: 13
A29: 14
A30: 15
... A35: 20
B36: Коммерческий отдел (ЛОГИСТИКА / Хранение / ПРР)
A37: 1
A38: 2
A39: 3
A40: 4
A41: 5
A42: 6
A43: 7
A44: 8
A45: 9
A46: 10
A47: 11
A48: 12
... A56: 20
B57: ПРОИЗВОДСТВЕННЫЙ комплекс / ТЕХ служба
A58: 1
A59: 2
A60: 3
A61: 4
A62: 5
A63: 6
A64: 7
A65: 8
A66: 9
A67: 10
A68: 11
A69: 12
... A72: 15
B73: РАСХОДЫ ПРОЧИЕ (Тех служба / Складской коммплекс / IT служба / Юр служба / Секретариат / Кадры / Маркетинг)
A74: 1
A75: 2
A76: 3
A77: 4
A78: 5
A79: 6
A80: 7
A81: 8
A82: 9
A83: 10
A84: 11
A85: 12
... A88: 15
B89: Бухгалтерия (Налоги / ЗП / ЕСН / прочие платежи бух. службы)
A90: 1 | B90: Лазарева Л.Ю | C90: Сбер Волжский | D90: реестр | E90: 4270.8 | F90: Расчет при увольнении за март 2026г | G90: РТПЗ Волжский | H90: Бюджет | K90: оплачен
A91: 2 | B91: Лазарева Л.Ю | C91: Сбер Волжский | D91: реестр | E91: 176247.96 | F91: Отпускные за март 2026г | G91: РТПЗ Волжский | H91: Бюджет | K91: оплачен
A92: 3 | B92: Лазарева Л.Ю | C92: Сбер Ростов | D92: реестр | E92: 53761.58 | F92: Отпускные за март 2026г | G92: РТПЗ Ростов | H92: Бюджет | K92: оплачен
A93: 4
A94: 5
A95: 6
A96: 7
A97: 8
A98: 9
A99: 10
B100: ФЭО (Кредиты/ Лизинг / Проценты / прочие платежи)
A101: 1
A102: 2
A103: 3
A104: 4
A105: 5
A106: ИТОГО ТД РТПЗ РАСХОДЫ ПО РЕЕСТРУ | E106: =SUM(E15:E105) -> 6391623.6
A107: ДЕФИЦИТ / ПРОФИЦИТ с Остатка на начало дня | E107: =E4-E106 -> 17498837
A109: ООО ЖИВАЯ СТАЛЬ | E109: =SUM(E110:E113) -> 697262.62
A110: счёт СБ 1125 | E110: 697262.62
A115: № п/п | B115: Инициатор платежа | C115: Контрагент - Получатель | D115: Договор/Счет | E115: Сумма к оплате | F115: Назначение платежа | G115: Подразделение - плательщик | H115: Бюджет/Статья | I115: Наличие Договора | J115: Примечание | K115: Отметка об оплате | L115: Спец. Распоряжение
B116: Коммерческий отдел (Закупка товара / Логистика / Снабжение/ ВЭД / Хранение / ПРР / Маркетинг)
A117: 1
A118: 2
A119: 3
A120: 4
A121: 5
A122: 6
A123: 7
...

Sheet 13
C2: ='12'!C2+1 -> 46094
A4: ООО ТД РТПЗ | E4: =SUM(E5:E12) -> 3301667.9 | F4: РЕЕСТР ЗАКРЫТ !!!
A5: Волжский счёт СБ 7503 | E5: 3080006.4
A6: Головной счёт СБ 13291 | E6: 4429.92
A8: счёт ЦМР Банк | E8: 15821.6
A9: счёт РОСБАНК 1115 | E9: 49366.84
A10: счёт Райффайзенбанк 38867 | E10: 78553.1
A11: счёт Промсвязьбанк 5439 | E11: 31489.09
A12: счёт Альфа-Банк 10329 | E12: 42000.93
A14: № п/п | B14: Инициатор платежа | C14: Контрагент - Получатель | D14: Договор/Счет | E14: Сумма к оплате | F14: Назначение платежа | G14: Подразделение - плательщик | H14: Бюджет/Статья | I14: Наличие Договора | J14: Примечание | K14: Отметка об оплате | L14: Спец. Распоряжение
B15: Коммерческий отдел (ПОСТАВЩИКИ / ПОКУПАТЕЛИ)
A16: 1
A17: 2 | B17: Федоров А.А. | C17: Северсталь ПАО | D17: Договр № 643/1000-24100303 от 12.04.2024 | E17: .25 933 135,75 | F17: Металлопрокат
A18: 3
A19: 4
A20: 5
A21: 6
A22: 7
A23: 8
A24: 9
A25: 10
A26: 11
A27: 12
A28: 13
A29: 14
... A35: 20
B36: Коммерческий отдел (ЛОГИСТИКА / Хранение / ПРР)
A37: 1
A38: 2
A39: 3
A40: 4
A41: 5
A42: 6
A43: 7
A44: 8
A45: 9
A46: 10
A47: 11
A48: 12
... A56: 20
B57: ПРОИЗВОДСТВЕННЫЙ комплекс / ТЕХ служба
A58: 1
A59: 2
A60: 3
A61: 4
A62: 5
A63: 6
A64: 7
A65: 8
A66: 9
A67: 10
A68: 11
A69: 12
... A72: 15
B73: РАСХОДЫ ПРОЧИЕ (Тех служба / Складской коммплекс / IT служба / Юр служба / Секретариат / Кадры / Маркетинг)
A74: 1
A75: 2
A76: 3
A77: 4
A78: 5
A79: 6
A80: 7
A81: 8
A82: 9
A83: 10
A84: 11
A85: 12
... A88: 15
B89: Бухгалтерия (Налоги / ЗП / ЕСН / прочие платежи бух. службы)
A90: 1
A91: 2
A92: 3
A93: 4
A94: 5
A95: 6
A96: 7
A97: 8
A98: 9
A99: 10
B100: ФЭО (Кредиты/ Лизинг / Проценты / прочие платежи)
A101: 1
A102: 2
A103: 3
A104: 4
A105: 5
A106: ИТОГО ТД РТПЗ РАСХОДЫ ПО РЕЕСТРУ | E106: =SUM(E15:E105) -> 0
A107: ДЕФИЦИТ / ПРОФИЦИТ с Остатка на начало дня | E107: =E4-E106 -> 3301667.9
A109: ООО ЖИВАЯ СТАЛЬ | E109: =SUM(E110:E113) -> 697254.14
A110: счёт СБ 1125 | E110: 697254.14
A115: № п/п | B115: Инициатор платежа | C115: Контрагент - Получатель | D115: Договор/Счет | E115: Сумма к оплате | F115: Назначение платежа | G115: Подразделение - плательщик | H115: Бюджет/Статья | I115: Наличие Договора | J115: Примечание | K115: Отметка об оплате | L115: Спец. Распоряжение
B116: Коммерческий отдел (Закупка товара / Логистика / Снабжение/ ВЭД / Хранение / ПРР / Маркетинг)
A117: 1
A118: 2
A119: 3
A120: 4
A121: 5
A122: 6
A123: 7
A124: 8
A125: 9
...

Sheet 14
C2: ='13'!C2+1 -> 46095
A4: ООО ТД РТПЗ | E4: =SUM(E5:E12) -> 0
A5: Волжский счёт СБ 7503
A6: Головной счёт СБ 13291
A7: ИП Коваленко СБ 17500
A8: счёт ЦМР Банк
A9: счёт РОСБАНК 1115
A10: счёт Райффайзенбанк 38867
A11: счёт Промсвязьбанк 5439
A12: счёт Альфа-Банк 10329
A14: № п/п | B14: Инициатор платежа | C14: Контрагент - Получатель | D14: Договор/Счет | E14: Сумма к оплате | F14: Назначение платежа | G14: Подразделение - плательщик | H14: Бюджет/Статья | I14: Наличие Договора | J14: Примечание | K14: Отметка об оплате | L14: Спец. Распоряжение
B15: Коммерческий отдел (ПОСТАВЩИКИ / ПОКУПАТЕЛИ)
A16: 1
A17: 2
A18: 3
A19: 4
A20: 5
A21: 6
A22: 7
A23: 8
A24: 9
A25: 10
A26: 11
A27: 12
... A35: 20
B36: Коммерческий отдел (ЛОГИСТИКА / Хранение / ПРР)
A37: 1
A38: 2
A39: 3
A40: 4
A41: 5
A42: 6
A43: 7
A44: 8
A45: 9
A46: 10
A47: 11
A48: 12
... A56: 20
B57: ПРОИЗВОДСТВЕННЫЙ комплекс / ТЕХ служба
A58: 1
A59: 2
A60: 3
A61: 4
A62: 5
A63: 6
A64: 7
A65: 8
A66: 9
A67: 10
A68: 11
A69: 12
... A72: 15
B73: РАСХОДЫ ПРОЧИЕ (Тех служба / Складской коммплекс / IT служба / Юр служба / Секретариат / Кадры / Маркетинг)
A74: 1
A75: 2
A76: 3
A77: 4
A78: 5
A79: 6
A80: 7
A81: 8
A82: 9
A83: 10
A84: 11
A85: 12
... A88: 15
B89: Бухгалтерия (Налоги / ЗП / ЕСН / прочие платежи бух. службы)
A90: 1
A91: 2
A92: 3
A93: 4
A94: 5
A95: 6
A96: 7
A97: 8
A98: 9
A99: 10
B100: ФЭО (Кредиты/ Лизинг / Проценты / прочие платежи)
A101: 1
A102: 2
A103: 3
A104: 4
A105: 5
A106: ИТОГО ТД РТПЗ РАСХОДЫ ПО РЕЕСТРУ | E106: =SUM(E15:E105) -> 0
A107: ДЕФИЦИТ / ПРОФИЦИТ с Остатка на начало дня | E107: =E4-E106 -> 0
A109: ООО ЖИВАЯ СТАЛЬ | E109: =SUM(E110:E113) -> 0
A110: счёт СБ 1125
A115: № п/п | B115: Инициатор платежа | C115: Контрагент - Получатель | D115: Договор/Счет | E115: Сумма к оплате | F115: Назначение платежа | G115: Подразделение - плательщик | H115: Бюджет/Статья | I115: Наличие Договора | J115: Примечание | K115: Отметка об оплате | L115: Спец. Распоряжение
B116: Коммерческий отдел (Закупка товара / Логистика / Снабжение/ ВЭД / Хранение / ПРР / Маркетинг)
A117: 1
A118: 2
A119: 3
A120: 4
A121: 5
A122: 6
A123: 7
A124: 8
A125: 9
A126: 10
...

Sheet 15
C2: ='14'!C2+1 -> 46096
A4: ООО ТД РТПЗ | E4: =SUM(E5:E12) -> 0
A5: Волжский счёт СБ 7503
A6: Головной счёт СБ 13291
A7: ИП Коваленко СБ 17500
A8: счёт ЦМР Банк
A9: счёт РОСБАНК 1115
A10: счёт Райффайзенбанк 38867
A11: счёт Промсвязьбанк 5439
A12: счёт Альфа-Банк 10329
A14: № п/п | B14: Инициатор платежа | C14: Контрагент - Получатель | D14: Договор/Счет | E14: Сумма к оплате | F14: Назначение платежа | G14: Подразделение - плательщик | H14: Бюджет/Статья | I14: Наличие Договора | J14: Примечание | K14: Отметка об оплате | L14: Спец. Распоряжение
B15: Коммерческий отдел (ПОСТАВЩИКИ / ПОКУПАТЕЛИ)
A16: 1
A17: 2
A18: 3
A19: 4
A20: 5
A21: 6
A22: 7
A23: 8
A24: 9
A25: 10
A26: 11
A27: 12
... A35: 20
B36: Коммерческий отдел (ЛОГИСТИКА / Хранение / ПРР)
A37: 1
A38: 2
A39: 3
A40: 4
A41: 5
A42: 6
A43: 7
A44: 8
A45: 9
A46: 10
A47: 11
A48: 12
... A56: 20
B57: ПРОИЗВОДСТВЕННЫЙ комплекс / ТЕХ служба
A58: 1
A59: 2
A60: 3
A61: 4
A62: 5
A63: 6
A64: 7
A65: 8
A66: 9
A67: 10
A68: 11
A69: 12
... A72: 15
B73: РАСХОДЫ ПРОЧИЕ (Тех служба / Складской коммплекс / IT служба / Юр служба / Секретариат / Кадры / Маркетинг)
A74: 1
A75: 2
A76: 3
A77: 4
A78: 5
A79: 6
A80: 7
A81: 8
A82: 9
A83: 10
A84: 11
A85: 12
... A88: 15
B89: Бухгалтерия (Налоги / ЗП / ЕСН / прочие платежи бух. службы)
A90: 1
A91: 2
A92: 3
A93: 4
A94: 5
A95: 6
A96: 7
A97: 8
A98: 9
A99: 10
B100: ФЭО (Кредиты/ Лизинг / Проценты / прочие платежи)
A101: 1
A102: 2
A103: 3
A104: 4
A105: 5
A106: ИТОГО ТД РТПЗ РАСХОДЫ ПО РЕЕСТРУ | E106: =SUM(E15:E105) -> 0
A107: ДЕФИЦИТ / ПРОФИЦИТ с Остатка на начало дня | E107: =E4-E106 -> 0
A109: ООО ЖИВАЯ СТАЛЬ | E109: =SUM(E110:E113) -> 0
A110: счёт СБ 1125
A115: № п/п | B115: Инициатор платежа | C115: Контрагент - Получатель | D115: Договор/Счет | E115: Сумма к оплате | F115: Назначение платежа | G115: Подразделение - плательщик | H115: Бюджет/Статья | I115: Наличие Договора | J115: Примечание | K115: Отметка об оплате | L115: Спец. Распоряжение
B116: Коммерческий отдел (Закупка товара / Логистика / Снабжение/ ВЭД / Хранение / ПРР / Маркетинг)
A117: 1
A118: 2
A119: 3
A120: 4
A121: 5
A122: 6
A123: 7
A124: 8
A125: 9
A126: 10
...

Sheet 16
C2: ='15'!C2+1 -> 46097
A4: ООО ТД РТПЗ | E4: =SUM(E5:E12) -> 35745078 | F4: РЕЕСТР ЗАКРЫТ !!!
A5: Волжский счёт СБ 7503 | E5: 35026273 | F5: =E19+E20+E37+E39+E40+E41+E42+E43+E44+E45+E46+E47+E48+E49+E50+E58+E59+E60+E61+E62+E63+E64+E65+E66+E67+E68+E69+E70+E71+E72+E73+E74+E75+E76+E77+E78+E79+E87+E88+E89+E90+E91+E114 -> 2549995.9
A6: Головной счёт СБ 13291 | E6: 4429.92
A7: ИП Коваленко СБ 17500
A8: счёт ЦМР Банк | E8: 15821.6
A9: счёт РОСБАНК 1115 | E9: 49366.84
A10: счёт Райффайзенбанк 38867 | E10: 574893.1
A11: счёт Промсвязьбанк 5439 | E11: 31489.09
A12: счёт Альфа-Банк 10329 | E12: 42803.93
A14: № п/п | B14: Инициатор платежа | C14: Контрагент - Получатель | D14: Договор/Счет | E14: Сумма к оплате | F14: Назначение платежа | G14: Подразделение - плательщик | H14: Бюджет/Статья | I14: Наличие Договора | J14: Примечание | K14: Отметка об оплате | L14: Спец. Распоряжение
B15: Коммерческий отдел (ПОСТАВЩИКИ / ПОКУПАТЕЛИ)
A16: 1 | B16: пышный | C16: Кармет | E16: 3000000 | I16: Да | J16: с райфа | K16: оплачен
A17: 2 | B17: Федоров А.А. | C17: Северсталь ПАО | D17: Договр № 643/1000-24100303 от 12.04.2024 | E17: .25 933 135,75 | F17: Металлопрокат | I17: Да
A18: 3 | B18: Федоров А.А. | C18: НЛМК ПАО | D18: Договор №204709-23 от 15.03.2023 | E18: 3000000 | F18: Металлопрокат | I18: Да
A19: 4 | B19: Крикса М.П. | C19: АлСар ТОО | D19: Контракт № 19Э-2024 от 16.08.2024 | E19: 333474.3 | F19: Возврат денежных средств клиенту. | G19: РТПЗ Волжский | I19: Да | J19: Согласовано с Солодовниковым А.Н. | K19: оплачен
A20: 5 | B20: Дынник | C20: ООО "Группа Компаний Демидов" | D20: СЧЕТ № ФИЛ26-434576 от 13.03.26 | E20: 35592.6 | F20: Труба профильная 2 сорт (некондиция, упаковка) | G20: РТПЗ Волжский | I20: Да
A21: 6
A22: 7 | B22: Ченский М.В. | C22: СтройПартнёр ООО | D22: Договор №СП23-00689-КР от 12.07.2023 | E22: 671152.5 | F22: Металлопрокат | I22: Да
A23: 8 | B23: Ченский М.В. | C23: Мечел-Сервис ООО | D23: Договор №370019010049 от 01.04.2019 | E23: 263219.23 | F23: Металлопрокат
A24: 9
A25: 10
A26: 11
A27: 12
A28: 13
A29: 14
A30: 15
A31: 16
A32: 17
A33: 18
A34: 19
A35: 20
B36: Коммерческий отдел (ЛОГИСТИКА / Хранение / ПРР)
A37: 1 | B37: Голка | C37: НЕО ТРАНС ООО | D37: Счет №3730 от 13.02 | E37: 80000 | F37: Транспорт | G37: РТПЗ Волжский | H37: Бюджет | K37: оплачен
A38: 2
A39: 3 | B39: Голка | C39: Картавцев ИП | D39: Счет №1 от 13.02 | E39: 60000 | F39: Транспорт | G39: РТПЗ Волжский | H39: Бюджет | K39: оплачен
A40: 4 | B40: Голка | C40: Донцов ИП | D40: Счет №4 от 24.02 | E40: 8500 | F40: Транспорт | G40: РТПЗ Волжский | H40: Бюджет | K40: оплачен
A41: 5 | B41: Голка | C41: ДЕЛКО ООО | D41: Счет №14701 от 13.02 | E41: 55000 | F41: Транспорт | G41: РТПЗ Волжский | H41: Бюджет | K41: оплачен
A42: 6 | B42: Голка | C42: МЭТ ООО | D42: Счет №739/2026 от 12.02 | E42: 70000 | F42: Транспорт | G42: РТПЗ Волжский | H42: Бюджет | K42: оплачен
A43: 7 | B43: Голка | C43: АРКС ЛОГИСТИК ООО | D43: Счет №96 от 12.02 | E43: 45000 | F43: Транспорт | G43: РТПЗ Волжский | H43: Бюджет | K43: оплачен
A44: 8 | B44: Голка | C44: Землянский С.В. ИП | D44: Счет №43 от 14.02 | E44: 45000 | F44: Транспорт | G44: РТПЗ Волжский | H44: Бюджет | K44: оплачен
A45: 9 | B45: Голка | C45: СКС-Групп ООО | D45: Счет №29 от 04.02 | E45: 36000 | F45: Транспорт | G45: РТПЗ Волжский | H45: Бюджет | K45: оплачен
A46: 10 | B46: Голка | C46: Промснаб ООО | D46: Счет №29 от 16.02 | E46: 65000 | F46: Транспорт | G46: РТПЗ Волжский | H46: Бюджет | K46: оплачен
A47: 11 | B47: Голка | C47: Кушнарев ИП | D47: Счет №8 от 12.02 | E47: 85000 | F47: Транспорт | G47: РТПЗ Волжский | H47: Бюджет | K47: оплачен
A48: 12 | B48: Голка | C48: Ушаков ИП | D48: Счет №73 от 12.02 | E48: 80000 | F48: Транспорт | G48: РТПЗ Волжский | H48: Бюджет | K48: оплачен
A49: 13 | B49: Высокова | C49: ИП Мангов | D49: Счет № 82 от 17.02.2026 | E49: 8400 | F49: транспорт | H49: Бюджет | K49: оплачен
A50: 14 | B50: Высокова | C50: ИП Григорян Г.К. | D50: Счет № Р32603-10 от 10.03.2026 | E50: 16000 | F50: транспорт | H50: Бюджет | K50: оплачен
A51: 15
A52: 16
A53: 17
A54: 18
A55: 19
A56: 20
B57: ПРОИЗВОДСТВЕННЫЙ комплекс / ТЕХ служба
A58: 1 | B58: Любимов Ю.В. | C58: ИП Анохина Л. В. | D58: Договор №01052024 от 01.05.2024 г. | E58: 250000 | F58: НДС не облагается. Аренда движимого имущества по договору №01052024 от 01.05.2024 г. за февраль 2026 г. (прибыль соб-ку) | G58: РТПЗ Волжский | H58: Бюджет | I58: Да | K58: оплачен
A59: 2 | B59: Любимов Ю.В. | C59: ООО Волжская вода | D59: договор №17/82-В от 18.09.2018 | E59: 36812.89 | F59: Вода питьевая за февраль 2026 г.(води стоки) | G59: РТПЗ Волжский | H59: Бюджет | I59: Да | K59: оплачен
A60: 3 | B60: Любимов Ю.В. | C60: ООО Волжские стоки | D60: договор №17/82-С от 18.09.2018 | E60: 10578.62 | F60: Стоки хозфекальные за февраль 2026 г. (вод и стоки) | G60: РТПЗ Волжский | H60: Бюджет | I60: Да | K60: оплачен
A61: 4 | B61: Любимов Ю.В. | C61: ООО Грат | D61: Счет № 646 от 01.03.26 г. | E61: 6943 | F61: Техническая эксплуатация сети газораспределения и сети газопотребления объекта (газопровод среднего давления, ГРУ-400-У1), расположенного по адресу: Волгоградская обл., г. Волжский, ул. Александрова, 76 по дог. №ТЭ-35, от 6.06.2024 г. за Март 2025г. (отопление) | G61: РТПЗ Волжский | H61: Бюджет | I61: Да | K61: оплачен
A62: 5 | B62: Любимов Ю.В. | C62: ООО Грат | D62: Счет № 645 от 01.03.26 г. | E62: 10845 | F62: Техническое обслуживание, текущий ремонт и аварийно-диспетчерское обслуживание объекта (газопровод низкого давления (532,5 м), внутренний газопровод (32м) и газовое оборудование), расположенного по адресу: Волгоградская обл. г. Волжский, ул. Александрова, 76 по дог №ТО-88 от 6.05.2024г. за Март 2026 г. (отопление) | G62: РТПЗ Волжский | H62: Бюджет | I62: Да | K62: оплачен
A63: 6 | B63: Любимов Ю.В. | C63: ООО Волжскпромжелдортранс | D63: Счет № 68 от 28.02.2026 г. | E63: 28290.04 | F63: За услуги жд транспорта по договору № 49В/2016 от 26.04.2016 г. за 3 декаду февраля 2025 г (жд) | G63: РТПЗ Волжский | H63: Бюджет | I63: Да | K63: оплачен
A64: 7 | B64: Любимов Ю.В. | C64: ООО Волжскпромжелдортранс | D64: счет № 73 от 28.02.2026 | E64: 28987.2 | F64: За услуги по договору № 35-11/2021 от 18.02.2021 (пользов. жд краном) за 3 декаду февраля 2026 года (жд) | G64: РТПЗ Волжский | H64: Бюджет | I64: Да | K64: оплачен
A65: 8 | B65: Любимов Ю.В. | C65: ООО Волжскпромжелдортранс | D65: Счет № 69 от 28.02.2026 г. | E65: 1952 | F65: За услуги по договору № 38-48/2020 (пользов. Жд пути) за февраль 2026 г (жд) | G65: РТПЗ Волжский | H65: Бюджет | I65: Да | K65: оплачен
A66: 9 | B66: Любимов Ю.В. | C66: ООО Резерв | D66: Счет № 44 от 28.02.2026 | E66: 194040 | F66: перевозка пассажиров за ФЕВРАЛЬ 2026 г. (Перевозка работников на производство) | G66: РТПЗ Волжский | H66: Бюджет | I66: Нет | J66: Копия | K66: оплачен
A67: 10 | B67: Любимов Ю.В. | C67: ИП Якшин С В | D67: Счет № 47 от 27.02.2026 | E67: 288164 | F67: Услуги по перевозке пассажиров за Февраль 2026 г (Перевозка работников на производство) | G67: РТПЗ Волжский | H67: Бюджет | I67: Да | K67: оплачен
A68: 11 | B68: Стадников | C68: ООО НВЭК ПБ | D68: счет №42 от 03.03.2026 | E68: 85000 | F68: экспертиза промбезопасности цеха (усл сертиф) | G68: РТПЗ Волжский | H68: Бюджет | I68: Да | J68: Скан | K68: оплачен
A69: 12 | B69: Стадников | C69: ИП Дроздова Н.Н. | D69: счет №12 от 28.02.2026 | E69: 7000 | F69: услуги автовышки (ГПМ) | G69: РТПЗ Волжский | H69: Бюджет | I69: Да | K69: оплачен
A70: 13 | B70: Стадников | C70: ООО Дезинфекционный Сервис | D70: счет №32 от 26.02.2026 | E70: 4200 | F70: дератизация, дезинсекция (пр коммун) | G70: РТПЗ Волжский | H70: Бюджет | K70: оплачен
A71: 14 | B71: Стадников | C71: ООО Полином+ | D71: счет №313 от 13.02.2026 | E71: 8653.84 | F71: стирка спецодежды (усл пр-ва) | G71: РТПЗ Волжский | H71: Бюджет | I71: Да | K71: оплачен
A72: 15 | B72: Стадников | C72: ООО Профмед | D72: счет №189 от 28.02.2026 | E72: 11890 | F72: предварительный медосмотр (усл пр-ва) | G72: РТПЗ Волжский | H72: Бюджет | I72: Да | K72: оплачен
A73: 16 | B73: Стадников | C73: ИП Хорищенко | D73: счет №3 от 04.03.2026 | E73: 40000 | F73: ремонт кровли АБК (Содержание зданий и помещений) | G73: РТПЗ Волжский | H73: Внебюджет ПЛАТИМ | I73: Нет | J73: копия | K73: оплачен
A74: 17 | B74: Стадников | C74: ООО Фирма Волжский НТЦ | D74: счет №33 от 28.02.2026 | E74: 2226.91 | F74: тех.обслуживание системы учета газа (отопление) | G74: РТПЗ Волжский | H74: Бюджет | I74: Да | J74: Скан | K74: оплачен
A75: 18 | B75: Стадников | C75: ООО Кингойл | D75: счет №56725 от 11.03.2026 | E75: 16448.86 | F75: масла для авто, щетки (4150р-рем тс, 12 298,86 - ГСМ) | G75: РТПЗ Волжский | H75: Бюджет | I75: Нет | J75: Копия | K75: оплачен
A76: 19 | B76: Дынник | C76: Праксайр Волгоград | D76: Счет № 19167389/50000532 от 11.03.2026 | E76: 10610.34 | F76: Аргон, углекислота (сварка) | G76: РТПЗ Волжский | H76: Бюджет | I76: Да | K76: оплачен
A77: 20 | B77: Дынник | C77: ФИРСТ ООО ГК | D77: Счет-фактура №ФТ-144 от 28.01.2026 | E77: 6952 | F77: Спецодежда | G77: РТПЗ Волжский | H77: Бюджет | I77: Да | K77: оплачен
A78: 21 | B78: Дынник | C78: ВСЕИНСТРУМЕНТЫ.РУ ООО | D78: Счет-фактура №1802006142-ВЛЖ от 18.02.2026 | E78: 29585 | F78: Инструмент | G78: РТПЗ Волжский | H78: Бюджет | I78: Да | J78: Скан | K78: оплачен
A79: 22 | B79: Дынник | C79: ПРОМПРОЕКТ ООО | D79: Счет-фактура №70 от 09.02.2026 | E79: 100000 | F79: Импидоры, стержни, трубки, пластины (РПМ, Инструмент-46 тыс) | G79: РТПЗ Волжский | H79: Бюджет | I79: Да | J79: Сумма по реестру | K79: оплачен
A80: 23
A81: 24
A82: 25
A83: 26
A84: 27
A85: 28
B86: РАСХОДЫ ПРОЧИЕ (Тех служба / Складской коммплекс / IT служба / Юр служба / Секретариат / Кадры / Маркетинг)
A87: 1 | B87: Приезжева | C87: заявление под отчет | E87: 6000 | F87: офисные расходы (орг) | G87: РТПЗ Волжский | H87: Бюджет | J87: чай, кофе | K87: оплачен
A88: 2 | B88: Приезжева | C88: заявление под отчет | E88: 12000 | F88: почтовые расходы | G88: РТПЗ Волжский | H88: Бюджет | J88: отправка и получение корреспонденции | K88: оплачен
A89: 3 | B89: Приезжева | C89: заявление под отчет | E89: 22000 | F89: производственные расходы (РПМ) | G89: РТПЗ Волжский | H89: Бюджет | J89: аварийные ситуации на производстве | K89: оплачен
A90: 4 | B90: Амитон Д.Д. | C90: ООО Новофон-ОС | D90: счёт 0013230АВNF от 12 марта 2026 г. | E90: 1000 | F90: оплата услуг связи | H90: Бюджет | K90: оплачен
A91: 5
A92: 6
A93: 7
A94: 8
A95: 9
A96: 10
A97: 11
A98: 12
A99: 13
A100: 14
A101: 15
B102: Бухгалтерия (Налоги / ЗП / ЕСН / прочие платежи бух. службы)
A103: 1
...

Sheet 17
C2: ='16'!C2+1 -> 46098
A4: ООО ТД РТПЗ | E4: =SUM(E5:E12) -> 2760254.2 | F4: РЕЕСТР ЗАКРЫТ !!!
A5: Волжский счёт СБ 7503 | E5: 2481477.2
A6: Головной счёт СБ 13291 | E6: 4429.92
A7: ИП Коваленко СБ 17500
A8: счёт ЦМР Банк | E8: 15821.6
A9: счёт РОСБАНК 1115 | E9: 49366.84
A10: счёт Райффайзенбанк 38867 | E10: 134865.61
A11: счёт Промсвязьбанк 5439 | E11: 31489.09
A12: счёт Альфа-Банк 10329 | E12: 42803.93
A14: № п/п | B14: Инициатор платежа | C14: Контрагент - Получатель | D14: Договор/Счет | E14: Сумма к оплате | F14: Назначение платежа | G14: Подразделение - плательщик | H14: Бюджет/Статья | I14: Наличие Договора | J14: Примечание | K14: Отметка об оплате | L14: Спец. Распоряжение
B15: Коммерческий отдел (ПОСТАВЩИКИ / ПОКУПАТЕЛИ)
A16: 2 | B16: Федоров А.А. | C16: Северсталь ПАО | D16: Договр № 643/1000-24100303 от 12.04.2024 | E16: .25 933 135,75 | F16: Металлопрокат
A17: 3 | B17: Федоров А.А. | C17: НЛМК ПАО | D17: Договор №204709-23 от 15.03.2023 | E17: 2000000 | F17: Металлопрокат | K17: оплачен
A18: 6
A19: 7 | B19: Ченский М.В. | C19: СтройПартнёр ООО | D19: Договор №СП23-00689-КР от 12.07.2023 | E19: 671152.5 | F19: Металлопрокат | K19: оплачен
A20: 8 | B20: Ченский М.В. | C20: Мечел-Сервис ООО | D20: Договор №370019010049 от 01.04.2019 | E20: 263219.23 | F20: Металлопрокат | K20: оплачен
A21: 9
A22: 10
A23: 11
A24: 12
A25: 13
A26: 14
A27: 15
A28: 16
A29: 17
A30: 18
A31: 19
A32: 20
B33: Коммерческий отдел (ЛОГИСТИКА / Хранение / ПРР)
A34: 1
A35: 2
A36: 3
A37: 4
A38: 5
A39: 6
A40: 7
A41: 8
A42: 9
A43: 10
A44: 11
A45: 12
... A53: 20
B54: ПРОИЗВОДСТВЕННЫЙ комплекс / ТЕХ служба
A55: 1
A56: 2
A57: 3
A58: 4
A59: 5
A60: 6
A61: 7
A62: 8
A63: 9
A64: 10
A65: 11
A66: 12
... A69: 15
B70: РАСХОДЫ ПРОЧИЕ (Тех служба / Складской коммплекс / IT служба / Юр служба / Секретариат / Кадры / Маркетинг)
A71: 1 | B71: Николаев | C71: ПАО "МегаФон" | D71: Счёт на оплату № 560096635295 от 28.02.2026 | E71: 1000 | F71: Услуги связи (Договор № 5100811 от 21.09.2017) | G71: Волжский | H71: Бюджет | J71: Оплата 1000 (в счёте 474) | K71: оплачен
A72: 2
A73: 3
A74: 4
A75: 5
A76: 6
A77: 7
A78: 8
A79: 9
A80: 10
A81: 11
A82: 12
A83: 13
... A85: 15
B86: Бухгалтерия (Налоги / ЗП / ЕСН / прочие платежи бух. службы)
A87: 1
A88: 2
A89: 3
A90: 4
A91: 5
A92: 6
A93: 7
A94: 8
A95: 9
A96: 10
B97: ФЭО (Кредиты/ Лизинг / Проценты / прочие платежи)
A98: 1
A99: 2
A100: 3
A101: 4
A102: 5
A103: ИТОГО ТД РТПЗ РАСХОДЫ ПО РЕЕСТРУ | E103: =SUM(E15:E102) -> 2935371.7
A104: ДЕФИЦИТ / ПРОФИЦИТ с Остатка на начало дня | E104: =E4-E103 -> -175117.54
A106: ООО ЖИВАЯ СТАЛЬ | E106: =SUM(E107:E110) -> 697254.14
A107: счёт СБ 1125 | E107: 697254.14
A112: № п/п | B112: Инициатор платежа | C112: Контрагент - Получатель | D112: Договор/Счет | E112: Сумма к оплате | F112: Назначение платежа | G112: Подразделение - плательщик | H112: Бюджет/Статья | I112: Наличие Договора | J112: Примечание | K112: Отметка об оплате | L112: Спец. Распоряжение
B113: Коммерческий отдел (Закупка товара / Логистика / Снабжение/ ВЭД / Хранение / ПРР / Маркетинг)
A114: 1
A115: 2
A116: 3
A117: 4
A118: 5
...

Sheet 18
C2: ='17'!C2+1 -> 46099
A4: ООО ТД РТПЗ | E4: =SUM(E5:E12) -> 11353586 | F4: РЕЕСТР ЗАКРЫТ !!!
A5: Волжский счёт СБ 7503 | E5: 9061924.1
A6: Головной счёт СБ 13291 | E6: 27855.3
A7: ИП Коваленко СБ 17500
A8: счёт ЦМР Банк | E8: 15821.6
A9: счёт РОСБАНК 1115 | E9: 47366.84
A10: счёт Райффайзенбанк 38867 | E10: 126325.61
A11: счёт Промсвязьбанк 5439 | E11: 2031489.1
A12: счёт Альфа-Банк 10329 | E12: 42803.93
A14: № п/п | B14: Инициатор платежа | C14: Контрагент - Получатель | D14: Договор/Счет | E14: Сумма к оплате | F14: Назначение платежа | G14: Подразделение - плательщик | H14: Бюджет/Статья | I14: Наличие Договора | J14: Примечание | K14: Отметка об оплате | L14: Спец. Распоряжение
B15: Коммерческий отдел (ПОСТАВЩИКИ / ПОКУПАТЕЛИ)
A16: 1 | B16: Ченский М.В. | C16: СтройПартнёр ООО | D16: Договор №СП23-00689-КР от 12.07.2023 | E16: 725760 | F16: Металлопрокат | K16: оплачен
A17: 2
A18: 3 | B18: Федоров А.А. | C18: Северсталь ПАО | D18: Договр № 643/1000-24100303 от 12.04.2024 | E18: .25 933 135,75 | F18: Металлопрокат
A19: 4
A20: 5
A21: 6
A22: 7
A23: 8
A24: 9
A25: 10
A26: 11
A27: 12
A28: 13
A29: 14
A30: 15
... A35: 20
B36: Коммерческий отдел (ЛОГИСТИКА / Хранение / ПРР)
A37: 1 | B37: Голка | C37: Третьяков ИП | D37: Счет №260012601,26012801,26021101 от 11.02 | E37: =65000+78000+85000 -> 228000 | F37: Транспорт | G37: РТПЗ Волжский | H37: Бюджет | I37: Да | K37: оплачен
A38: 2 | B38: Голка | C38: Бабенко А.В. ИП | D38: Счет №54 от 27.02 | E38: 55000 | F38: Транспорт | G38: РТПЗ Волжский | H38: Бюджет | I38: Да | K38: оплачен
A39: 3 | B39: Голка | C39: Качурин М.О. ИП | D39: Счет №324 от 17.02 | E39: 52000 | F39: Транспорт | G39: РТПЗ Волжский | H39: Бюджет | I39: Да | K39: оплачен
A40: 4
A41: 5 | B41: Голка | C41: Ушаков А.С. ИП | D41: Счет №82 от 18.02 | E41: 80000 | F41: Транспорт | G41: РТПЗ Волжский | H41: Бюджет | I41: Да | J41: Копия | K41: оплачен
A42: 6 | B42: Голка | C42: ДЕЛКО ООО | D42: Счет №16152 от 18.02 | E42: 55000 | F42: Транспорт | G42: РТПЗ Волжский | H42: Бюджет | I42: Да | K42: оплачен
A43: 7 | B43: Голка | C43: Исаев М.Е. ИП | D43: Счет №13 от 11.03 | E43: 33000 | F43: Транспорт | G43: РТПЗ Волжский | H43: Бюджет | I43: Да | K43: оплачен
A44: 8 | B44: Голка | C44: СКС-Групп ООО | D44: Счет №36 от 13.02 | E44: 37000 | F44: Транспорт | G44: РТПЗ Волжский | H44: Бюджет | I44: Да | K44: оплачен
A45: 9 | B45: Голка | C45: РАУТ ООО | D45: Счет №12,14,17 от 16.02 | E45: =80000+62000+62000 -> 204000 | F45: Транспорт | G45: РТПЗ Волжский | H45: Бюджет | I45: Да | K45: оплачен
A46: 10 | B46: Голка | C46: Стальстройпоставка ООО | D46: Счет №106,105,108,125,140,131,352 от 18.02 | E46: =40000+70000+40000+85000+40000+48000+60000 -> 383000 | F46: Транспорт | G46: РТПЗ Волжский | H46: Бюджет | I46: Да | J46: Скан | K46: оплачен
A47: 11 | B47: Голка | C47: Ахметов А.С. ИП | D47: По Акту сверки от 17.02 | E47: 35000 | F47: Транспорт | G47: РТПЗ Волжский | H47: Бюджет | I47: Да | K47: оплачен
A48: 12 | B48: Голка | C48: ПАО ТРАНСКОНТЕЙНЕР | D48: Счет №3577771 от 16.03 | E48: 377415.54 | F48: Транспорт | G48: РТПЗ Волжский | H48: Бюджет | I48: Да | K48: оплачен
A49: 13 | B49: Голка | C49: Поволжье-Транс ООО | D49: Счет №ТЛПТ0006876 от 03.02 | E49: 95000 | F49: Транспорт | G49: РТПЗ Волжский | H49: Бюджет | I49: Да | K49: оплачен
A50: 14
A51: 15
A52: 16
A53: 17
A54: 18
A55: 19
A56: 20
B57: ПРОИЗВОДСТВЕННЫЙ комплекс / ТЕХ служба
A58: 1 | B58: Любимов Ю.В. | C58: ООО Волжскпромжелдортранс-Экспедитор | D58: счет № 34 от 11.03.2026 | E58: 37543.91 | F58: Транспортно-экспедиционные услуги за 1 декаду марта 2026 года (ЖД) | G58: РТПЗ Волжский | H58: Бюджет | I58: Да | K58: оплачен
A59: 2 | B59: Любимов Ю.В. | C59: ООО Волжскпромжелдортранс | D59: счет № 80 от 10.3.2026 | E59: 88393.55 | F59: За услуги жд транспорта по договору № 49В/2016 от 26.04.2016 г. за 1 декаду марта 2026 г (ЖД) | G59: РТПЗ Волжский | H59: Бюджет | I59: Да | K59: оплачен
A60: 3 | B60: Любимов Ю.В. | C60: ООО Волжскпромжелдортранс | D60: счет № 79 от 10.03.2026 | E60: 27740.4 | F60: За услуги по договору № 35-11/2021 от 18.02.2021 (пользов. жд краном) за 1 декаду марта 2026 года (ЖД) | G60: РТПЗ Волжский | H60: Бюджет | I60: Да | K60: оплачен
A61: 4 | B61: Стадников | C61: ООО Донской арсенал | D61: счет №260 от 12.03.2026 | E61: 30400 | F61: автошины черри 430 (Метком) | G61: РТПЗ Ростов | H61: Бюджет МЕТКОМ | I61: Нет | K61: оплачен
A62: 5 | B62: Стадников | C62: ООО Волжская противопожарная автоматика | D62: счет №62 от 03.03.2026 | E62: 5165.12 | F62: тех.обслуживание АУПС (усл -пр-ва) | G62: РТПЗ Волжский | H62: Бюджет | I62: Да | K62: оплачен
A63: 6 | B63: Любимов Ю.В. | C63: ООО Газпром межрегионгаз Волгоград | D63: договор № 09-5-68353/23К | E63: 232157.64 | F63: За потребление газа в феврале 2025 года по договору № 09-5-68353/23К (отопление) | G63: РТПЗ Волжский | H63: Бюджет | I63: Да | K63: оплачен
A64: 7 | B64: Любимов Ю.В. | C64: ООО Газпром межрегионгаз Волгоград | D64: договор № 09-5-68353/23Б | E64: 12063.52 | F64: За потребление и транспортировку газа в феврале 2025 года по договору № 09-5-68353/23Б (отопление) | G64: РТПЗ Волжский | H64: Бюджет | I64: Да | K64: оплачен
A65: 8 | B65: Стадников | C65: ИП Евдокимов С.М. | D65: счет №3 от 19.01.2026 | E65: 32667.6 | F65: валик, кронштейн, обод (АПР) | G65: РТПЗ Волжский | H65: Бюджет | I65: Да | J65: скан | K65: оплачен
A66: 9 | B66: Любимов Ю.В. | C66: ООО Центрэнерго | D66: Договор №40ЭС-20 от 15.10.2020 г. | E66: 440000 | F66: реквизиты АБ Россия за потребление электроэнергии в марте 2026 г. | G66: РТПЗ Волжский | H66: Бюджет | I66: Да | K66: оплачен
A67: 10 | B67: Любимов Ю.В. | C67: ООО Центрэнерго | D67: Договор №40ЭС-20 от 15.10.2020 г. | E67: 15000 | F67: реквизиты АБ Россия за потребление электроэнергии в марте 2026 г. | G67: РТПЗ Волжский | H67: 79.02 КОД | I67: Да | J67: КОД | K67: оплачен
A68: 11 | B68: Стадников | C68: ИП Кузнецова Е.В. | D68: счет №106 от 16.03.2026 | E68: 1074 | F68: тех.осмотр ларгус 188 (пр тс) | G68: РТПЗ Волжский | H68: Бюджет | I68: Да | K68: оплачен
A69: 12 | B69: Стадников | C69: МВД по городу Волжскому | D69: по реквизитам | E69: 500 | F69: гос.пошлина за тех.осмотр (пр тс) | G69: РТПЗ Волжский | H69: Бюджет | K69: оплачен
A70: 13 | B70: Стадников | C70: ИП Черкас Н.А. | D70: счет №YGYG1343 от 16.03.2026 | E70: 33209 | F70: зап.части БМВ Х5 (Метком) | G70: РТПЗ Ростов | H70: Бюджет МЕТКОМ | I70: Да | K70: оплачен
A71: 14 | B71: Стадников | C71: ИП Шевцова Е.Б. | D71: счет-оферта №ШЕ26-159 от 17.03.2026 | E71: 5320 | F71: шиномонтаж БМВ Х5 (Метком) | G71: РТПЗ Ростов | H71: Бюджет МЕТКОМ | I71: Да | J71: СКАН | K71: оплачен
A72: 15 | B72: Стадников | C72: ФБУ Волгоградский ЦСМ | D72: счет №7316 от 17.03.2026 | E72: 9414.86 | F72: поверка СИ (усл сертиф-я) | G72: РТПЗ Волжский | H72: Бюджет | I72: Да | K72: оплачен
A73: 16 | B73: Стадников | C73: ООО Траектория | D73: счет №4260 от 17.03.2026 | E73: 690 | F73: услуги Глонасс (пр тс) | G73: РТПЗ Волжский | H73: Бюджет | I73: Да | K73: оплачен
A74: 17 | B74: Дынник | C74: ООО "Галактика" | D74: Счет на оплату № 7607 от 17 марта 2026 г. | E74: 31200 | F74: Трубки медные (РПМ) | G74: РТПЗ Волжский | H74: Бюджет | I74: Да | K74: оплачен
A75: 18 | B75: Дынник | C75: Праксайр Волгоград | D75: Счет №19167807/50000532 от 17.03.2026 | E75: 8679.08 | F75: Углекислота (сварка) | G75: РТПЗ Волжский | H75: Бюджет | I75: Да | K75: оплачен
A76: 19 | B76: Дынник | C76: Деловые Линии | D76: Счет №26-02441155052 от 28.02.2026 | E76: 473.2 | F76: Расходы на доставку (на производство/с производства) | G76: РТПЗ Волжский | H76: Бюджет | I76: Да | J76: Сумма по реестру. База для расчета НДС: 473,2-90 (страховая сумма)=383,20 | K76: оплачен
A77: 20 | B77: Дынник | C77: Деловые Линии | D77: Счет 26-04031027088 от 05.03.2026 10:32:56 | E77: 1000 | F77: Расходы на доставку (на производство/с производства) | G77: РТПЗ Волжский | H77: Бюджет | I77: Да | K77: оплачен
A78: 21 | B78: Дынник | C78: Деловые Линии | D78: Счет 26-01691018333 от 05.03.2026 15:47:33 | E78: 1489 | F78: Расходы на доставку (на производство/с производства) | G78: РТПЗ Волжский | H78: Бюджет | I78: Да | K78: оплачен
A79: 22 | B79: Дынник | C79: Деловые Линии | D79: Счет 26-50190077149 от 06.03.2026 16:37:22 | E79: 1026 | F79: Расходы на доставку (на производство/с производства) | G79: РТПЗ Волжский | H79: Бюджет | I79: Да | K79: оплачен
A80: 23 | B80: Дынник | C80: Деловые Линии | D80: Счет 26-01301034942 от 07.03.2026 3:49:24 | E80: 1345 | F80: Расходы на доставку (на производство/с производства) | G80: РТПЗ Волжский | H80: Бюджет | I80: Да | K80: оплачен
A81: 24 | B81: Дынник | C81: Деловые Линии | D81: Счет 26-00721013042 от 07.03.2026 13:12:34 | E81: 1064 | F81: Расходы на доставку (на производство/с производства) | G81: РТПЗ Волжский | H81: Бюджет | I81: Да | K81: оплачен
A82: 25 | B82: Дынник | C82: Деловые Линии | D82: Счет 26-00261006699 от 06.03.2026 13:35:44 | E82: 1518 | F82: Расходы на доставку (на производство/с производства) | G82: РТПЗ Волжский | H82: Бюджет | I82: Да | K82: оплачен
A83: 26 | B83: Дынник | C83: Деловые Линии | D83: Счет 26-00661081932 от 13.03.2026 13:11:37 | E83: 1654 | F83: Расходы на доставку (на производство/с производства) | G83: РТПЗ Волжский | H83: Бюджет | I83: Да | K83: оплачен
A84: 27 | B84: Дынник | C84: Качурин Максим Олегович ИП | D84: Счет-фактура №М00106 от 16.02.2026 | E84: 79250 | F84: Брус профилированный (упаковка) | G84: РТПЗ Волжский | H84: Бюджет | I84: Да | K84: оплачен
A85: 28 | B85: Дынник | C85: Качурин Максим Олегович ИП | D85: Счет-фактура №М00145 от 03.03.2026 | E85: 79250 | F85: Брус профилированный (упаковка) | G85: РТПЗ Волжский | H85: Бюджет | I85: Да | K85: оплачен
A86: 29 | B86: Дынник | C86: ЭкоСтрой | D86: Счет-фактуры №30 от 26.01.2026, 57 от 13.02.2026, 61 от 16.02.2026 | E86: 210000 | F86: Брус профилированный (упаковка) | G86: РТПЗ Волжский | H86: Бюджет | I86: Да | J86: Копия/ Сумма по реестру | K86: оплачен
A87: 30 | B87: Стадников | C87: ИП Швадченко А.В. | D87: счет №89604 от 18.03.2026 | E87: 9200 | F87: ремонт БМВ Х5 (Метом) | G87: РТПЗ Ростов | H87: Бюджет МЕТКОМ
A88: 31
A89: 32
A90: 33
A91: 34
B92: РАСХОДЫ ПРОЧИЕ (Тех служба / Складской коммплекс / IT служба / Юр служба / Секретариат / Кадры / Маркетинг)
A93: 1 | B93: Гаркушенко | C93: ИП Данилов ВД | D93: сч 146 от 02.03.26 | E93: 171446.1 | F93: аренда офис март | G93: РТПЗ Ростов | H93: Бюджет | I93: Да | K93: оплачен
A94: 2
A95: 3
A96: 4
A97: 5
A98: 6
A99: 7
A100: 8
A101: 9
A102: 10
A103: 11
A104: 12
A105: 13
... A107: 15
B108: Бухгалтерия (Налоги / ЗП / ЕСН / прочие платежи бух. службы)
...

Sheet 19
C2: ='18'!C2+1 -> 46100
A4: ООО ТД РТПЗ | E4: =SUM(E5:E12) -> 9498017.4 | F4: РЕЕСТР ЗАКРЫТ !!!
A5: Волжский счёт СБ 7503 | E5: 6713089
A6: Головной счёт СБ 13291 | E6: 27855.3
A7: ИП Коваленко СБ 17500
A8: счёт ЦМР Банк | E8: 15821.6
A9: счёт РОСБАНК 1115 | E9: 47366.84
A10: счёт Райффайзенбанк 38867 | E10: 626325.61
A11: счёт Промсвязьбанк 5439 | E11: 2024755.1
A12: счёт Альфа-Банк 10329 | E12: 42803.93
A14: № п/п | B14: Инициатор платежа | C14: Контрагент - Получатель | D14: Договор/Счет | E14: Сумма к оплате | F14: Назначение платежа | G14: Подразделение - плательщик | H14: Бюджет/Статья | I14: Наличие Договора | J14: Примечание | K14: Отметка об оплате | L14: Спец. Распоряжение
B15: Коммерческий отдел (ПОСТАВЩИКИ / ПОКУПАТЕЛИ)
A16: 1 | B16: Федоров А.А. | C16: НЛМК ПАО | D16: Договор №204709-23 от 15.03.2023 | E16: 8000000 | F16: Металлопрокат | K16: оплачен
A17: 2
A18: 3
A19: 4
A20: 5
A21: 6
A22: 7
A23: 8
A24: 9
A25: 10
A26: 11
A27: 12
A28: 13
... A35: 20
B36: Коммерческий отдел (ЛОГИСТИКА / Хранение / ПРР)
A37: 1
A38: 2
A39: 3
A40: 4
A41: 5
A42: 6
A43: 7
A44: 8
A45: 9
A46: 10
A47: 11
A48: 12
... A56: 20
B57: ПРОИЗВОДСТВЕННЫЙ комплекс / ТЕХ служба
A58: 1
A59: 2
A60: 3
A61: 4
A62: 5
A63: 6
A64: 7
A65: 8
A66: 9
A67: 10
A68: 11
A69: 12
... A72: 15
B73: РАСХОДЫ ПРОЧИЕ (Тех служба / Складской коммплекс / IT служба / Юр служба / Секретариат / Кадры / Маркетинг)
A74: 1
A75: 2
A76: 3
A77: 4
A78: 5
A79: 6
A80: 7
A81: 8
A82: 9
A83: 10
A84: 11
A85: 12
... A88: 15
B89: Бухгалтерия (Налоги / ЗП / ЕСН / прочие платежи бух. службы)
A90: 1 | B90: Лазарева Л.Ю | C90: Сбер Волжский | D90: реестр | E90: 147745.54 | F90: Отпускные за март 2026г | G90: РТПЗ Волжский | H90: Бюджет | K90: оплачен
A91: 2 | B91: Лазарева Л.Ю | C91: Сбер Ростов | D91: реестр | E91: 65609.24 | F91: Отпускные за март 2026г | G91: РТПЗ Ростов | H91: Бюджет | K91: оплачен
A92: 3
A93: 4
A94: 5
A95: 6
A96: 7
A97: 8
A98: 9
A99: 10
B100: ФЭО (Кредиты/ Лизинг / Проценты / прочие платежи)
A101: 1
A102: 2
A103: 3
A104: 4
A105: 5
A106: ИТОГО ТД РТПЗ РАСХОДЫ ПО РЕЕСТРУ | E106: =SUM(E15:E105) -> 8213354.8
A107: ДЕФИЦИТ / ПРОФИЦИТ с Остатка на начало дня | E107: =E4-E106 -> 1284662.6
A109: ООО ЖИВАЯ СТАЛЬ | E109: =SUM(E110:E113) -> 697254.14
A110: счёт СБ 1125 | E110: 697254.14
A115: № п/п | B115: Инициатор платежа | C115: Контрагент - Получатель | D115: Договор/Счет | E115: Сумма к оплате | F115: Назначение платежа | G115: Подразделение - плательщик | H115: Бюджет/Статья | I115: Наличие Договора | J115: Примечание | K115: Отметка об оплате | L115: Спец. Распоряжение
B116: Коммерческий отдел (Закупка товара / Логистика / Снабжение/ ВЭД / Хранение / ПРР / Маркетинг)
A117: 1
A118: 2
A119: 3
A120: 4
A121: 5
A122: 6
A123: 7
A124: 8
A125: 9
...

Sheet 20
C2: ='19'!C2+1 -> 46101
A4: ООО ТД РТПЗ | E4: =SUM(E5:E12) -> 2833471.3 | F4: РЕЕСТР ЗАКРЫТ !!!
A5: Волжский счёт СБ 7503 | E5: 614473.9
A6: Головной счёт СБ 13291 | E6: 27855.3
A7: ИП Коваленко СБ 17500
A8: счёт ЦМР Банк | E8: 15821.6
A9: счёт РОСБАНК 1115 | E9: 47366.84
A10: счёт Райффайзенбанк 38867 | E10: 2060394.6
A11: счёт Промсвязьбанк 5439 | E11: 24755.09
A12: счёт Альфа-Банк 10329 | E12: 42803.93
A14: № п/п | B14: Инициатор платежа | C14: Контрагент - Получатель | D14: Договор/Счет | E14: Сумма к оплате | F14: Назначение платежа | G14: Подразделение - плательщик | H14: Бюджет/Статья | I14: Наличие Договора | J14: Примечание | K14: Отметка об оплате | L14: Спец. Распоряжение
B15: Коммерческий отдел (ПОСТАВЩИКИ / ПОКУПАТЕЛИ)
A16: 1 | B16: Ченский М.В. | C16: Сталепромышленная компания АО | D16: Договор поставки № 30/2019 от 02.04.2019 | E16: 486090 | F16: Металлопрокат | K16: оплачен
A17: 2 | C17: кармет | E17: 3000000 | J17: с райфа | K17: оплачен
A18: 3 | B18: Федоров А.А. | C18: Северсталь ПАО | D18: Договр № 643/1000-24100303 от 12.04.2024 | E18: .25 933 135,75 | F18: Металлопрокат
A19: 4 | B19: Федоров А.А. | C19: НЛМК ПАО | D19: Договор №204709-23 от 15.03.2023 | E19: 5000000 | F19: Металлопрокат | K19: оплачен
A20: 5
A21: 6
A22: 7
A23: 8
A24: 9
A25: 10
A26: 11
A27: 12
A28: 13
A29: 14
A30: 15
A31: 16
... A35: 20
B36: Коммерческий отдел (ЛОГИСТИКА / Хранение / ПРР)
A37: 1
A38: 2
A39: 3
A40: 4
A41: 5
A42: 6
A43: 7
A44: 8
A45: 9
A46: 10
A47: 11
A48: 12
... A56: 20
B57: ПРОИЗВОДСТВЕННЫЙ комплекс / ТЕХ служба
A58: 1
A59: 2
A60: 3
A61: 4
A62: 5
A63: 6
A64: 7
A65: 8
A66: 9
A67: 10
A68: 11
A69: 12
... A72: 15
B73: РАСХОДЫ ПРОЧИЕ (Тех служба / Складской коммплекс / IT служба / Юр служба / Секретариат / Кадры / Маркетинг)
A74: 1
A75: 2
A76: 3
A77: 4
A78: 5
A79: 6
A80: 7
A81: 8
A82: 9
A83: 10
A84: 11
A85: 12
... A88: 15
B89: Бухгалтерия (Налоги / ЗП / ЕСН / прочие платежи бух. службы)
A90: 1
A91: 2
A92: 3
A93: 4
A94: 5
A95: 6
A96: 7
A97: 8
A98: 9
A99: 10
B100: ФЭО (Кредиты/ Лизинг / Проценты / прочие платежи)
A101: 1 | B101: Панфилова Е.О. | C101: ПСБ | D101: 84-32315/0353 | E101: 1710684 | F101: %% по ВКЛ | G101: Бюджет | K101: оплачен
A102: 2
A103: 3
A104: 4
A105: 5
A106: ИТОГО ТД РТПЗ РАСХОДЫ ПО РЕЕСТРУ | E106: =SUM(E15:E105) -> 10196774
A107: ДЕФИЦИТ / ПРОФИЦИТ с Остатка на начало дня | E107: =E4-E106 -> -7363302.7
A109: ООО ЖИВАЯ СТАЛЬ | E109: =SUM(E110:E113) -> 697254.14
A110: счёт СБ 1125 | E110: 697254.14
A115: № п/п | B115: Инициатор платежа | C115: Контрагент - Получатель | D115: Договор/Счет | E115: Сумма к оплате | F115: Назначение платежа | G115: Подразделение - плательщик | H115: Бюджет/Статья | I115: Наличие Договора | J115: Примечание | K115: Отметка об оплате | L115: Спец. Распоряжение
B116: Коммерческий отдел (Закупка товара / Логистика / Снабжение/ ВЭД / Хранение / ПРР / Маркетинг)
A117: 1
A118: 2
A119: 3
A120: 4
A121: 5
A122: 6
...

Sheet 21
C2: ='20'!C2+1 -> 46102
A4: ООО ТД РТПЗ | E4: =SUM(E5:E12) -> 0
A5: Волжский счёт СБ 7503
A6: Головной счёт СБ 13291
A7: ИП Коваленко СБ 17500
A8: счёт ЦМР Банк
A9: счёт РОСБАНК 1115
A10: счёт Райффайзенбанк 38867
A11: счёт Промсвязьбанк 5439
A12: счёт Альфа-Банк 10329
A14: № п/п | B14: Инициатор платежа | C14: Контрагент - Получатель | D14: Договор/Счет | E14: Сумма к оплате | F14: Назначение платежа | G14: Подразделение - плательщик | H14: Бюджет/Статья | I14: Наличие Договора | J14: Примечание | K14: Отметка об оплате | L14: Спец. Распоряжение
B15: Коммерческий отдел (ПОСТАВЩИКИ / ПОКУПАТЕЛИ)
A16: 1
A17: 2
A18: 3
A19: 4
A20: 5
A21: 6
A22: 7
A23: 8
A24: 9
A25: 10
A26: 11
A27: 12
... A35: 20
B36: Коммерческий отдел (ЛОГИСТИКА / Хранение / ПРР)
A37: 1
A38: 2
A39: 3
A40: 4
A41: 5
A42: 6
A43: 7
A44: 8
A45: 9
A46: 10
A47: 11
A48: 12
... A56: 20
B57: ПРОИЗВОДСТВЕННЫЙ комплекс / ТЕХ служба
A58: 1
A59: 2
A60: 3
A61: 4
A62: 5
A63: 6
A64: 7
A65: 8
A66: 9
A67: 10
A68: 11
A69: 12
... A72: 15
B73: РАСХОДЫ ПРОЧИЕ (Тех служба / Складской коммплекс / IT служба / Юр служба / Секретариат / Кадры / Маркетинг)
A74: 1
A75: 2
A76: 3
A77: 4
A78: 5
A79: 6
A80: 7
A81: 8
A82: 9
A83: 10
A84: 11
A85: 12
... A88: 15
B89: Бухгалтерия (Налоги / ЗП / ЕСН / прочие платежи бух. службы)
A90: 1
A91: 2
A92: 3
A93: 4
A94: 5
A95: 6
A96: 7
A97: 8
A98: 9
A99: 10
B100: ФЭО (Кредиты/ Лизинг / Проценты / прочие платежи)
A101: 1
A102: 2
A103: 3
A104: 4
A105: 5
A106: ИТОГО ТД РТПЗ РАСХОДЫ ПО РЕЕСТРУ | E106: =SUM(E15:E105) -> 0
A107: ДЕФИЦИТ / ПРОФИЦИТ с Остатка на начало дня | E107: =E4-E106 -> 0
A109: ООО ЖИВАЯ СТАЛЬ | E109: =SUM(E110:E113) -> 0
A110: счёт СБ 1125
A115: № п/п | B115: Инициатор платежа | C115: Контрагент - Получатель | D115: Договор/Счет | E115: Сумма к оплате | F115: Назначение платежа | G115: Подразделение - плательщик | H115: Бюджет/Статья | I115: Наличие Договора | J115: Примечание | K115: Отметка об оплате | L115: Спец. Распоряжение
B116: Коммерческий отдел (Закупка товара / Логистика / Снабжение/ ВЭД / Хранение / ПРР / Маркетинг)
A117: 1
A118: 2
A119: 3
A120: 4
A121: 5
A122: 6
A123: 7
A124: 8
A125: 9
A126: 10
...

Sheet 22
C2: ='21'!C2+1 -> 46103
A4: ООО ТД РТПЗ | E4: =SUM(E5:E12) -> 0
A5: Волжский счёт СБ 7503
A6: Головной счёт СБ 13291
A7: ИП Коваленко СБ 17500
A8: счёт ЦМР Банк
A9: счёт РОСБАНК 1115
A10: счёт Райффайзенбанк 38867
A11: счёт Промсвязьбанк 5439
A12: счёт Альфа-Банк 10329
A14: № п/п | B14: Инициатор платежа | C14: Контрагент - Получатель | D14: Договор/Счет | E14: Сумма к оплате | F14: Назначение платежа | G14: Подразделение - плательщик | H14: Бюджет/Статья | I14: Наличие Договора | J14: Примечание | K14: Отметка об оплате | L14: Спец. Распоряжение
B15: Коммерческий отдел (ПОСТАВЩИКИ / ПОКУПАТЕЛИ)
A16: 1
A17: 2
A18: 3
A19: 4
A20: 5
A21: 6
A22: 7
A23: 8
A24: 9
A25: 10
A26: 11
A27: 12
... A35: 20
B36: Коммерческий отдел (ЛОГИСТИКА / Хранение / ПРР)
A37: 1
A38: 2
A39: 3
A40: 4
A41: 5
A42: 6
A43: 7
A44: 8
A45: 9
A46: 10
A47: 11
A48: 12
... A56: 20
B57: ПРОИЗВОДСТВЕННЫЙ комплекс / ТЕХ служба
A58: 1
A59: 2
A60: 3
A61: 4
A62: 5
A63: 6
A64: 7
A65: 8
A66: 9
A67: 10
A68: 11
A69: 12
... A72: 15
B73: РАСХОДЫ ПРОЧИЕ (Тех служба / Складской коммплекс / IT служба / Юр служба / Секретариат / Кадры / Маркетинг)
A74: 1
A75: 2
A76: 3
A77: 4
A78: 5
A79: 6
A80: 7
A81: 8
A82: 9
A83: 10
A84: 11
A85: 12
... A88: 15
B89: Бухгалтерия (Налоги / ЗП / ЕСН / прочие платежи бух. службы)
A90: 1
A91: 2
A92: 3
A93: 4
A94: 5
A95: 6
A96: 7
A97: 8
A98: 9
A99: 10
B100: ФЭО (Кредиты/ Лизинг / Проценты / прочие платежи)
A101: 1
A102: 2
A103: 3
A104: 4
A105: 5
A106: ИТОГО ТД РТПЗ РАСХОДЫ ПО РЕЕСТРУ | E106: =SUM(E15:E105) -> 0
A107: ДЕФИЦИТ / ПРОФИЦИТ с Остатка на начало дня | E107: =E4-E106 -> 0
A109: ООО ЖИВАЯ СТАЛЬ | E109: =SUM(E110:E113) -> 0
A110: счёт СБ 1125
A115: № п/п | B115: Инициатор платежа | C115: Контрагент - Получатель | D115: Договор/Счет | E115: Сумма к оплате | F115: Назначение платежа | G115: Подразделение - плательщик | H115: Бюджет/Статья | I115: Наличие Договора | J115: Примечание | K115: Отметка об оплате | L115: Спец. Распоряжение
B116: Коммерческий отдел (Закупка товара / Логистика / Снабжение/ ВЭД / Хранение / ПРР / Маркетинг)
A117: 1
A118: 2
A119: 3
A120: 4
A121: 5
A122: 6
A123: 7
A124: 8
A125: 9
A126: 10
...

Sheet 23
C2: ='22'!C2+1 -> 46104
A4: ООО ТД РТПЗ | E4: =SUM(E5:E12) -> 3963253.9 | F4: РЕЕСТР ЗАКРЫТ !!!
A5: Волжский счёт СБ 7503 | E5: 277491.7 | F5: =E35+E36+E37+E38+E39+E40+E41+E42+E43+E44+E45+E46+'25'!E37+'25'!E38+'25'!E39+'25'!E76+'25'!E41+'25'!E42+'25'!E43+'25'!E44+'25'!E45+'25'!E46+E99+E100 -> 5038141.5
A6: Головной счёт СБ 13291 | E6: 27855.3
A7: ИП Коваленко СБ 17500
A8: счёт ЦМР Банк | E8: 15821.6
A9: счёт РОСБАНК 1115 | E9: 47366.84
A10: счёт Райффайзенбанк 38867 | E10: 2537844.4
A11: счёт Промсвязьбанк 5439 | E11: 1014070.2
A12: счёт Альфа-Банк 10329 | E12: 42803.93
A14: № п/п | B14: Инициатор платежа | C14: Контрагент - Получатель | D14: Договор/Счет | E14: Сумма к оплате | F14: Назначение платежа | G14: Подразделение - плательщик | H14: Бюджет/Статья | I14: Наличие Договора | J14: Примечание | K14: Отметка об оплате | L14: Спец. Распоряжение
B15: Коммерческий отдел (ПОСТАВЩИКИ / ПОКУПАТЕЛИ)
A16: 1
A17: 2 | C17: кармет | E17: 2500000 | K17: оплачен
A18: 3
A19: 6 | B19: Федоров А.А. | C19: Северсталь ПАО | D19: Договр № 643/1000-24100303 от 12.04.2024 | E19: .25 933 135,75 | F19: Металлопрокат | I19: Да
A20: 7 | B20: Федоров А.А. | C20: НЛМК ПАО | D20: Договор №204709-23 от 15.03.2023 | F20: Металлопрокат | I20: Да
A21: 8
A22: 9
A23: 10
A24: 11
A25: 12
A26: 13
A27: 14
A28: 15
A29: 16
A30: 17
A31: 18
A32: 19
A33: 20
B34: Коммерческий отдел (ЛОГИСТИКА / Хранение / ПРР)
A35: 1 | B35: Высокова | C35: ИП Хачатрян | D35: Счет № 17 от 05.03.2026 | E35: 900 | F35: Транспорт | H35: Бюджет | I35: Да | K35: оплачен
A36: 2 | B36: Голка | C36: Воробьев А.Н. ИП | D36: Счет №31 от 17.02 | E36: 100000 | F36: Транспорт | G36: РТПЗ Волжский | H36: Бюджет | I36: Да | K36: оплачен
A37: 3 | B37: Голка | C37: Делко ООО | D37: Счет №17677 от 19.02 | E37: 120000 | F37: Транспорт | G37: РТПЗ Волжский | H37: Бюджет | I37: Да | K37: оплачен
A38: 4 | B38: Голка | C38: Третьяков В.И. | D38: Счет №25120501 от 05.12 | E38: 85000 | F38: Транспорт | G38: РТПЗ Волжский | H38: Бюджет | I38: Да | K38: оплачен
A39: 5 | B39: Голка | C39: АК№2 ООО | D39: Счет №1998,1995 от 18.02 | E39: =85000+85000 -> 170000 | F39: Транспорт | G39: РТПЗ Волжский | H39: Бюджет | I39: Да | K39: оплачен
A40: 6 | B40: Голка | C40: Качурин М.О. ИП | D40: Счет №350 от 20.02 | E40: 50000 | F40: Транспорт | G40: РТПЗ Волжский | H40: Бюджет | K40: оплачен
A41: 7 | B41: Голка | C41: ТК Никотранс ООО | D41: Счет №3526 от 20.02 | E41: 75000 | F41: Транспорт | G41: РТПЗ Волжский | H41: Бюджет | I41: Да | J41: КОПИЯ | K41: оплачен
A42: 8 | B42: Голка | C42: Долотказин Р.Р ИП | D42: Счет №13 от 20.02 | E42: 55000 | F42: Транспорт | G42: РТПЗ Волжский | H42: Бюджет | I42: Да | K42: оплачен
A43: 9 | B43: Голка | C43: Ес-Логистик ООО | D43: Счет №489 от 18.02 | E43: 72000 | F43: Транспорт | G43: РТПЗ Волжский | H43: Бюджет | I43: Да | J43: КОПИЯ | K43: оплачен
A44: 10 | B44: Голка | C44: Вектор-Н ООО | D44: Счет №37 от 09.02 | E44: 95000 | F44: Транспорт | G44: РТПЗ Волжский | H44: Бюджет | I44: Да | K44: оплачен
A45: 11 | B45: Голка | C45: РАУТ ООО | D45: Счет №26,18,20,19 от 24.02 | E45: =57000+80000+93000+88000 -> 318000 | F45: Транспорт | G45: РТПЗ Волжский | H45: Бюджет | I45: Да | K45: оплачен
A46: 12 | B46: Голка | C46: Стальстройпоставка ООО | D46: Счет №110,107,66,71,126,127,132,138,137 от 20.02 | E46: =40000+48000+75000+90000+40000+68000+69000+40000+70000 -> 540000 | F46: Транспорт | G46: РТПЗ Волжский | H46: Бюджет | I46: Да | J46: КОПИЯ | K46: оплачен
A47: 13
A48: 14
A49: 15
A50: 16
A51: 17
A52: 18
A53: 19
A54: 20
B55: ПРОИЗВОДСТВЕННЫЙ комплекс / ТЕХ служба
A56: 1
A57: 2
A58: 3
A59: 4
A60: 5
A61: 6
A62: 7
A63: 8
A64: 9
A65: 10
A66: 11
A67: 12
... A70: 15
B71: РАСХОДЫ ПРОЧИЕ (Тех служба / Складской коммплекс / IT служба / Юр служба / Секретариат / Кадры / Маркетинг)
A72: 1
A73: 2
A74: 3
A75: 4
A76: 5
A77: 6
A78: 7
A79: 8
A80: 9
A81: 10
A82: 11
A83: 12
... A86: 15
B87: Бухгалтерия (Налоги / ЗП / ЕСН / прочие платежи бух. службы)
A88: 1
A89: 2
A90: 3
A91: 4
A92: 5
A93: 6
A94: 7
A95: 8
A96: 9
A97: 10
B98: ФЭО (Кредиты/ Лизинг / Проценты / прочие платежи)
A99: 1 | B99: Панфилова Е.О. | C99: СБЕР | D99: 7M-520COP9-JD8 от 05.05.2025 | E99: 2159091.5 | F99: %% по ВКЛ | H99: Бюджет
A100: 2 | B100: Панфилова Е.О. | C100: СБЕР | D100: 7M-520COP9-JD8 от 05.05.2025 | E100: 606000 | F100: неттинг | H100: Бюджет
A101: 3
A102: 4
A103: 5
A104: ИТОГО ТД РТПЗ РАСХОДЫ ПО РЕЕСТРУ | E104: =SUM(E15:E103) -> 6945991.5
A105: ДЕФИЦИТ / ПРОФИЦИТ с Остатка на начало дня | E105: =E4-E104 -> -2982737.6
A107: ООО ЖИВАЯ СТАЛЬ | E107: =SUM(E108:E111) -> 697254.14
A108: счёт СБ 1125 | E108: 697254.14
...

Sheet 24
C2: ='23'!C2+1 -> 46105
A4: ООО ТД РТПЗ | E4: =SUM(E5:E12) -> 10200091 | F4: РЕЕСТР ЗАКРЫТ !!!
A5: Волжский счёт СБ 7503 | E5: 5053775.6
A6: Головной счёт СБ 13291 | E6: 26252.91
A7: ИП Коваленко СБ 17500
A8: счёт ЦМР Банк | E8: 15821.6
A9: счёт РОСБАНК 1115 | E9: 47366.84
A10: счёт Райффайзенбанк 38867 | E10: 30501.41
A11: счёт Промсвязьбанк 5439 | E11: 4014070.1
A12: счёт Альфа-Банк 10329 | E12: 1042803.9
A14: № п/п | B14: Инициатор платежа | C14: Контрагент - Получатель | D14: Договор/Счет | E14: Сумма к оплате | F14: Назначение платежа | G14: Подразделение - плательщик | H14: Бюджет/Статья | I14: Наличие Договора | J14: Примечание | K14: Отметка об оплате | L14: Спец. Распоряжение
B15: Коммерческий отдел (ПОСТАВЩИКИ / ПОКУПАТЕЛИ)
A16: 1
A17: 2
A18: 3 | B18: Федоров А.А. | C18: Северсталь ПАО | D18: Договр № 643/1000-24100303 от 12.04.2024 | E18: .25 933 135,75 | F18: Металлопрокат
A19: 4 | B19: Федоров А.А. | C19: НЛМК ПАО | D19: Договор №204709-23 от 15.03.2023 | E19: 5000000 | F19: Металлопрокат | K19: оплачен
A20: 5
A21: 6
A22: 7
A23: 8
A24: 9
A25: 10
A26: 11
A27: 12
A28: 13
A29: 14
A30: 15
A31: 16
... A35: 20
B36: Коммерческий отдел (ЛОГИСТИКА / Хранение / ПРР)
A37: 1
A38: 2
A39: 3
A40: 4
A41: 5
A42: 6
A43: 7
A44: 8
A45: 9
A46: 10
A47: 11
A48: 12
... A56: 20
B57: ПРОИЗВОДСТВЕННЫЙ комплекс / ТЕХ служба
A58: 1
A59: 2
A60: 3
A61: 4
A62: 5
A63: 6
A64: 7
A65: 8
A66: 9
A67: 10
A68: 11
A69: 12
... A72: 15
B73: РАСХОДЫ ПРОЧИЕ (Тех служба / Складской коммплекс / IT служба / Юр служба / Секретариат / Кадры / Маркетинг)
A74: 1
A75: 2
A76: 3
A77: 4
A78: 5
A79: 6
A80: 7
A81: 8
A82: 9
A83: 10
A84: 11
A85: 12
... A88: 15
B89: Бухгалтерия (Налоги / ЗП / ЕСН / прочие платежи бух. службы)
A90: 1 | B90: Лазарева Л.Ю | C90: На карту третьих лиц /Реквизиты Миллер Светланы Александровны | D90: отдельным платежом | E90: 22598.6 | F90: Зар.плата за 1 половину марта 2026г | G90: РТПЗ Волжский | H90: Бюджет | K90: оплачен
A91: 2 | B91: Лазарева Л.Ю | C91: На карту третьих лиц /Реквизиты Марьиной Надежды Александровны | D91: отдельным платежом | E91: 14767.19 | F91: Зар.плата за 1 половину марта 2026г | G91: РТПЗ Волжский | H91: Бюджет | K91: оплачен
A92: 3 | B92: Лазарева Л.Ю | C92: На карту третьих лиц /Реквизиты Олейниковой Кристины Денисовны | D92: отдельным платежом | E92: 30509.77 | F92: Зар.плата за 1 половину марта 2026г | G92: РТПЗ Волжский | H92: Бюджет | K92: оплачен
A93: 4 | B93: Лазарева Л.Ю | C93: На карту третьих лиц /Реквизиты Книпенберг Марины Николаевны | D93: отдельным платежом | E93: 9217.12 | F93: Зар.плата за 1 половину марта 2026г | G93: РТПЗ Волжский | H93: Бюджет | K93: оплачен
A94: 5 | B94: Лазарева Л.Ю | C94: На карту третьих лиц /Реквизиты Новикова Валентина Ивановича | D94: отдельным платежом | E94: 11581.8 | F94: Зар.плата за 1 половину марта 2026г | G94: РТПЗ Волжский | H94: Бюджет | K94: оплачен
A95: 6 | B95: Лазарева Л.Ю | C95: На карту третьих лиц /Реквизиты Гришиной Елизаветы Николаевны | D95: отдельным платежом | E95: 16078.63 | F95: Зар.плата за 1 половину марта 2026г | G95: РТПЗ Волжский | H95: Бюджет | K95: оплачен
A96: 7 | B96: Лазарева Л.Ю | C96: ВТБ | D96: отдельным платежом | E96: 166239.05 | F96: Зар.плата за 1 половину марта 2026г | G96: РТПЗ Волжский | H96: Бюджет | K96: оплачен
A97: 8 | B97: Лазарева Л.Ю | C97: Альфа-Банк | D97: отдельным платежом | E97: 73647.83 | F97: Зар.плата за 1 половину марта 2026г | G97: РТПЗ Волжский | H97: Бюджет | K97: оплачен
A98: 9 | B98: Лазарева Л.Ю | C98: Россельхозбанк | D98: отдельным платежом | E98: 15439.26 | F98: Зар.плата за 1 половину марта 2026г | G98: РТПЗ Волжский | H98: Бюджет | K98: оплачен
A99: 10 | B99: Лазарева Л.Ю | C99: Озон Банк | D99: отдельным платежом | E99: 29904.4 | F99: Зар.плата за 1 половину марта 2026г | G99: РТПЗ Волжский | H99: Бюджет | K99: оплачен
A100: 11 | B100: Лазарева Л.Ю | C100: Тинькофф Банк | D100: отдельным платежом | E100: 132604.01 | F100: Зар.плата за 1 половину марта 2026г | G100: РТПЗ Волжский | H100: Бюджет | K100: оплачен
A101: 12 | B101: Лазарева Л.Ю | C101: Совкомбанк | D101: отдельным платежом | E101: 24593 | F101: Зар.плата за 1 половину марта 2026г | G101: РТПЗ Волжский | H101: Бюджет | K101: оплачен
... A103: 14 | B103: Лазарева Л.Ю | C103: Сбер Волжский | D103: реестр | E103: 4103118.3 | F103: Зар.плата за 1 половину марта 2026г | G103: РТПЗ Волжский | H103: Бюджет | K103: оплачен
B109: ФЭО (Кредиты/ Лизинг / Проценты / прочие платежи)
A110: 1
A111: 2
A112: 3
A113: 4
A114: 5
A115: ИТОГО ТД РТПЗ РАСХОДЫ ПО РЕЕСТРУ | E115: =SUM(E15:E114) -> 9669474
A116: ДЕФИЦИТ / ПРОФИЦИТ с Остатка на начало дня | E116: =E4-E115 -> 530616.99
A118: ООО ЖИВАЯ СТАЛЬ | E118: =SUM(E119:E122) -> 40116.14
A119: счёт СБ 1125 | E119: 40116.14
A124: № п/п | B124: Инициатор платежа | C124: Контрагент - Получатель | D124: Договор/Счет | E124: Сумма к оплате | F124: Назначение платежа | G124: Подразделение - плательщик | H124: Бюджет/Статья | I124: Наличие Договора | J124: Примечание | K124: Отметка об оплате | L124: Спец. Распоряжение
B125: Коммерческий отдел (Закупка товара / Логистика / Снабжение/ ВЭД / Хранение / ПРР / Маркетинг)
A126: 1
A127: 2
A128: 3
...

Sheet 25
C2: ='24'!C2+1 -> 46106
A4: ООО ТД РТПЗ | E4: =SUM(E5:E12) -> 629398.13 | F4: РЕЕСТР ЗАКРЫТ !!!
A5: Волжский счёт СБ 7503 | E5: 483082.7
A6: Головной счёт СБ 13291 | E6: 26252.91
A7: ИП Коваленко СБ 17500
A8: счёт ЦМР Банк | E8: 15821.6
A9: счёт РОСБАНК 1115 | E9: 47366.84
A10: счёт Райффайзенбанк 38867 | E10: 30501.41
A11: счёт Промсвязьбанк 5439 | E11: 14070.15
A12: счёт Альфа-Банк 10329 | E12: 42803.93
A14: № п/п | B14: Инициатор платежа | C14: Контрагент - Получатель | D14: Договор/Счет | E14: Сумма к оплате | F14: Назначение платежа | G14: Подразделение - плательщик | H14: Бюджет/Статья | I14: Наличие Договора | J14: Примечание | K14: Отметка об оплате | L14: Спец. Распоряжение
B15: Коммерческий отдел (ПОСТАВЩИКИ / ПОКУПАТЕЛИ)
A16: 1
A17: 2 | B17: Федоров А.А. | C17: Северсталь ПАО | D17: Договр № 643/1000-24100303 от 12.04.2024 | E17: .25 933 135,75 | F17: Металлопрокат | I17: Да
A18: 3 | B18: Федоров А.А. | C18: НЛМК ПАО | D18: Договор №204709-23 от 15.03.2023 | F18: Металлопрокат | I18: Да
A19: 4
A20: 5
A21: 6
A22: 7
A23: 8
A24: 9
A25: 10
A26: 11
A27: 12
A28: 13
A29: 14
A30: 15
... A35: 20
B36: Коммерческий отдел (ЛОГИСТИКА / Хранение / ПРР)
A37: 1 | B37: Голка | C37: Кузнеченков И.А. ИП | D37: Счет №21 от 05.03 | E37: 45000 | F37: Транспорт | G37: РТПЗ Волжский | H37: Бюджет | K37: оплачен
A38: 2 | B38: Голка | C38: Настина Т.В. ИП | D38: Счет №56,50,58,59 от 14.03 | E38: =65000+62000+75000+74000 -> 276000 | F38: Транспорт | G38: РТПЗ Волжский | H38: Бюджет | K38: оплачен
A39: 3 | B39: Голка | C39: Третьяков ИП | D39: Счет №402,401 от 24.02 | E39: =65000+85000 -> 150000 | F39: Транспорт | G39: РТПЗ Волжский | H39: Бюджет | K39: оплачен
A40: 4 | B40: Голка | C40: Кушнарев Ю.Н. ИП | D40: Счет №9 от 16.02 | E40: 85000 | F40: Транспорт | G40: РТПЗ Волжский | H40: Бюджет | K40: оплачен
A41: 5 | B41: Голка | C41: Ушаков А.С. ИП | D41: Счет №89 от 24.02 | E41: 80000 | F41: Транспорт | G41: РТПЗ Волжский | H41: Бюджет | K41: оплачен
A42: 6 | B42: Голка | C42: Исаев ИП | D42: Счет №15 от 16.03 | E42: 34000 | F42: Транспорт | G42: РТПЗ Волжский | H42: Бюджет | K42: оплачен
A43: 7
A44: 8
A45: 9
A46: 10
A47: 11
A48: 12
A49: 13
A50: 14
A51: 15
A52: 16
A53: 17
A54: 18
... A56: 20
B57: ПРОИЗВОДСТВЕННЫЙ комплекс / ТЕХ служба
A58: 1 | B58: Любимов Ю.В. | C58: ИП Анохина Л. В. | D58: Договор №01052024 от 01.05.2024 г. | E58: 250000 | F58: НДС не облагается. Аренда движимого имущества по договору №01052024 от 01.05.2024 г. за февраль 2026 г. (прибыль соб-ку) | G58: РТПЗ Волжский | H58: Бюджет | I58: Да | K58: оплачен
A59: 2 | B59: Любимов Ю.В. | C59: ИП Анохина Л. В. | D59: Договор № 01/05/24/01 от 01.05.2024 г. | E59: 30000 | F59: НДС не облагается. Аренда движимого имущества по договору№ 01/05/24/01 от 01.05.2024 г. за февраль 2026 г. (прибыль соб-ку) | G59: РТПЗ Голова | H59: Бюджет | I59: Да | K59: оплачен
A60: 3 | B60: Любимов Ю.В. | C60: ИП Анохина Л. В. | D60: Договор № 01/05/24/02 от 01.05.2024 г. | E60: 10000 | F60: НДС не облагается. Аренда движимого имущества по договору № 01/05/24/02 от 01.05.2024 г. за февраль 2026 г. (прибыль соб-ку) | G60: РТПЗ Голова | H60: Бюджет | I60: Да | K60: оплачен
A61: 4
A62: 5 | B62: Стадников | C62: ООО Электросила | D62: счет №73 от 13.03.2026 | E62: 9330.56 | F62: ремонт электродвигателя (АПР) | G62: РТПЗ Волжский | H62: Бюджет | I62: Да | K62: оплачен
A63: 6 | B63: Стадников | C63: ИП Черкас Н.А. | D63: счет №YGYG1375 от 19.03.2026 | E63: 3416 | F63: запчасти БМВ Х5 (Метком) | G63: РТПЗ Ростов | H63: Бюджет МЕТКОМ | I63: Да | K63: оплачен
A64: 7 | B64: Дынник | C64: ТПК ООО | D64: Счет-фактура №220 от 18.03.2026 | E64: 15750 | F64: Проволока (сварка) | G64: РТПЗ Волжский | H64: Бюджет | I64: Да | J64: Копия | K64: оплачен
A65: 8 | B65: Дынник | C65: КИНГОЙЛ ООО | D65: Счет-фактура №47554 от 06.03.2026 | E65: 18332.82 | F65: Масло гидравл (смазочные) | G65: РТПЗ Волжский | H65: Бюджет | I65: Да | J65: КОПИЯ/Сумма по реестру | K65: оплачен
A66: 9 | B66: Дынник | C66: ЭНЕРГОКОМ ООО ﻿ | D66: Счет-фактура №063/2253 от 27.02.2026 | E66: 14135.05 | F66: Электроматериалы (РПМ) | G66: РТПЗ Волжский | H66: Бюджет | I66: Да | K66: оплачен
A67: 10 | B67: Дынник | C67: ПРОМПРОЕКТ ООО | D67: Счет-фактура №70 от 09.02.2026 | E67: 60000 | F67: Стержни, трубки (РПМ) | G67: РТПЗ Волжский | H67: Бюджет | I67: Да | J67: Сумма по реестру | K67: оплачен
A68: 11 | B68: Дынник | C68: Праксайр Волгоград | D68: Счет №19168306/50000532 от 24.03.2026 | E68: 7395.64 | F68: Аргон (сварка) | G68: РТПЗ Волжский | H68: Бюджет | I68: Да | K68: оплачен
A69: 12
A70: 13
A71: 14
A72: 15
B73: РАСХОДЫ ПРОЧИЕ (Тех служба / Складской коммплекс / IT служба / Юр служба / Секретариат / Кадры / Маркетинг)
A74: 1 | B74: Стадников | C74: ИП Дроздова Н.Н. | D74: счет №24 от 23.03.2026 | E74: 7000 | F74: услуги автовышки (ГПМ) | G74: РТПЗ Волжский | H74: Бюджет | I74: Нет | K74: оплачен
A75: 2 | B75: Приезжева | C75: Аква сервис | D75: счет 1927 от 23.03.2026 | E75: 10455 | F75: питьевая вода (орг) | G75: РТПЗ Волжский | H75: Бюджет | I75: Да | K75: оплачен
A76: 3 | B76: Стадников | C76: ИП Швадченко А.В. | D76: счет №89883 от 18.03.2026 | E76: 7150 | F76: ремонт БМВ Х5 (Метком) | G76: РТПЗ Ростов | H76: Бюджет МЕТКОМ | I76: Да | K76: оплачен
A77: 4 | B77: Гаркушенко | C77: Мирошников | E77: 43724 | F77: билеты Узбекистан | G77: РТПЗ Ростов | H77: Бюджет | K77: оплачен
A78: 5 | B78: Амитон Д.Д. | C78: ПАО Вымпелком | D78: счёт 101191736436 от 05.03.26 | E78: 15157.76 | F78: оплата услуг связи | G78: РТПЗ Волжский | H78: Бюджет | K78: оплачен
A79: 6 | B79: Амитон Д.Д. | C79: ПАО Вымпелком | D79: счёт 602-U00OL от 28.02.26 | E79: 8868.82 | F79: оплата услуг связи | G79: РТПЗ Волжский | H79: Бюджет | K79: оплачен
A80: 7 | B80: Амитон Д.Д. | C80: ООО ТД Мистер Пэн | D80: счёт 34 от 23.03.26 | E80: 9500 | F80: покупка риббона для термотрансферного принтера (расх IT) | G80: РТПЗ Волжский | H80: Бюджет | K80: оплачен
A81: 8 | B81: Амитон Д.Д. | C81: ООО ПАУЭРНЕТ | D81: счёт 991 от 28.02.26 | E81: 6700 | F81: оплата услуг связи | G81: РТПЗ Волжский | H81: Бюджет | K81: оплачен
A82: 9
A83: 10 | B83: Амитон Д.Д. | C83: ИП Николаевский А.В. | D83: счёт 7 от 31.01.26 | E83: 10000 | F83: Сервисной техническое обслуживание сети видеонаблюдения за январь 2026 (орг) | G83: РТПЗ Волжский | H83: Бюджет | K83: оплачен
A84: 11 | B84: Амитон Д.Д. | C84: ИП Николаевский А.В. | D84: счёт 32 от 31.10.25 | E84: 10000 | F84: Сервисной техническое обслуживание сети видеонаблюдения за октябрь 2025 (орг) | G84: РТПЗ Волжский | H84: Бюджет | K84: оплачен
A85: 12 | B85: Амитон Д.Д. | C85: ИП Николаевский А.В. | D85: счёт 36 от 28.11.25 | E85: 10000 | F85: Сервисной техническое обслуживание сети видеонаблюдения за ноябрь 2025 (орг) | G85: РТПЗ Волжский | H85: Бюджет | K85: оплачен
A86: 13 | B86: Амитон Д.Д. | C86: ИП Николаевский А.В. | D86: счёт 37 от 30.12.25 | E86: 10000 | F86: Сервисной техническое обслуживание сети видеонаблюдения за декабрь 2025 (орг) | G86: РТПЗ Волжский | H86: Бюджет | K86: оплачен
A87: 14 | B87: Гаркушенко | C87: Солодовников АН | E87: 7928 | F87: командировочные Воронеж | G87: РТПЗ Ростов | H87: Бюджет | K87: оплачен
A88: 15
B89: Бухгалтерия (Налоги / ЗП / ЕСН / прочие платежи бух. службы)
A90: 1 | B90: Лазарева Л.Ю | C90: Сбер Ростов | D90: реестр | E90: 557979.64 | F90: Зар.плата за 1 половину марта 2026г | G90: РТПЗ Ростов | H90: Бюджет | K90: оплачен
A91: 2 | B91: Лазарева Л.Ю | C91: Сбер Волжский/Швец | D91: реестр | E91: 7804 | F91: Оплата по договору ГПХ за март 2026г/Составление программ для токарного станка с ЧПУ (13 программ) (АПР) | G91: РТПЗ Волжский | H91: Бюджет | I91: Да | K91: оплачен
A92: 3 | B92: Лазарева Л.Ю | C92: ИФНС по ЕНП | D92: КБК 18201061201010000510 | E92: 1166 | F92: НДФЛ по договору ГПХ/Швец (период с 23.03 по 31.03.2025) (АПР) | G92: РТПЗ Ростов | H92: Бюджет | K92: оплачен
A93: 4 | B93: Лазарева Л.Ю | C93: Тинькофф Банк | D93: отдельным платежом | E93: 39698 | F93: Отпускные за март 2026г | G93: РТПЗ Волжский | H93: Бюджет | K93: оплачен
A94: 5 | B94: Лазарева Л.Ю | C94: Альфа-Банк | D94: отдельным платежом | E94: 41013.5 | F94: Отпускные за март 2026г | G94: РТПЗ Волжский | H94: Бюджет | K94: оплачен
A95: 6 | B95: Лазарева Л.Ю | C95: Сбер Волжский | D95: реестр | E95: 115458.62 | F95: Отпускные за март 2026г | G95: РТПЗ Волжский | H95: Бюджет | K95: оплачен
A96: 7 | B96: Лазарева Л.Ю | C96: Сбер Ростов | D96: реестр | E96: 22695.05 | F96: Отпускные за март 2026г | G96: РТПЗ Ростов | H96: Бюджет | K96: оплачен
A97: 8 | B97: Котельникова Т.В. | C97: ИФНС по ЕНП | D97: КБК 18201061201010000510 | E97: 294785 | F97: НДС 1/3 за 4 кв.2025 | H97: Бюджет | J97: срок оплаты до 28.03.2026 | K97: оплачен
A98: 9
A99: 10
B100: ФЭО (Кредиты/ Лизинг / Проценты / прочие платежи)
A101: 1
A102: 2
A103: 3 | C103: Метком | E103: 3100000 | K103: оплачен
A104: 4
A105: 5
A106: ИТОГО ТД РТПЗ РАСХОДЫ ПО РЕЕСТРУ | E106: =SUM(E15:E105) -> 5425443.5
A107: ДЕФИЦИТ / ПРОФИЦИТ с Остатка на начало дня | E107: =E4-E106 -> -4796045.3
A109: ООО ЖИВАЯ СТАЛЬ | E109: =SUM(E110:E113) -> 40116.14
...

Sheet 26
C2: ='25'!C2+1 -> 46107
A4: ООО ТД РТПЗ | E4: =SUM(E5:E12) -> 6253760.7 | F4: РЕЕСТР ЗАКРЫТ !!!
A5: Волжский счёт СБ 7503 | E5: 6077481.9
A6: Головной счёт СБ 13291 | E6: 26252.91
A7: ИП Коваленко СБ 17500
A8: счёт ЦМР Банк | E8: 15821.6
A9: счёт РОСБАНК 1115
A10: счёт Райффайзенбанк 38867 | E10: 24401.41
A11: счёт Промсвязьбанк 5439 | E11: 66998.95
A12: счёт Альфа-Банк 10329 | E12: 42803.93
A14: № п/п | B14: Инициатор платежа | C14: Контрагент - Получатель | D14: Договор/Счет | E14: Сумма к оплате | F14: Назначение платежа | G14: Подразделение - плательщик | H14: Бюджет/Статья | I14: Наличие Договора | J14: Примечание | K14: Отметка об оплате | L14: Спец. Распоряжение
B15: Коммерческий отдел (ПОСТАВЩИКИ / ПОКУПАТЕЛИ)
A16: 1
A17: 2 | B17: Федоров А.А. | C17: Северсталь ПАО | D17: Договр № 643/1000-24100303 от 12.04.2024 | E17: .25 933 135,75 | F17: Металлопрокат | I17: Да
A18: 3 | B18: Федоров А.А. | C18: НЛМК ПАО | D18: Договор №204709-23 от 15.03.2023 | F18: Металлопрокат | I18: Да
A19: 4
A20: 5
A21: 6
A22: 7
A23: 8
A24: 9
A25: 10
A26: 11
A27: 12
A28: 13
A29: 14
A30: 15
... A35: 20
B36: Коммерческий отдел (ЛОГИСТИКА / Хранение / ПРР)
A37: 1
A38: 2
A39: 3
A40: 4
A41: 5
A42: 6
A43: 7
A44: 8
A45: 9
A46: 10
A47: 11
A48: 12
... A56: 20
B57: ПРОИЗВОДСТВЕННЫЙ комплекс / ТЕХ служба
A58: 1
A59: 2
A60: 3
A61: 4
A62: 5
A63: 6
A64: 7
A65: 8
A66: 9
A67: 10
A68: 11
A69: 12
... A72: 15
B73: РАСХОДЫ ПРОЧИЕ (Тех служба / Складской коммплекс / IT служба / Юр служба / Секретариат / Кадры / Маркетинг)
A74: 1
A75: 2
A76: 3
A77: 4
A78: 5
A79: 6
A80: 7
A81: 8
A82: 9
A83: 10
A84: 11
A85: 12
... A88: 15
B89: Бухгалтерия (Налоги / ЗП / ЕСН / прочие платежи бух. службы)
A90: 1 | B90: Лазарева Л.Ю | C90: ИФНС по ЕНП | D90: КБК 18201061201010000510 | E90: 5600000 | F90: Страховые взносы за февраль 2026г(налоги с фот) | G90: РТПЗ Ростов | H90: Бюджет | J90: Крайний срок 30.03.2026 | K90: оплачен
A91: 2
A92: 3
A93: 4
A94: 5
A95: 6
A96: 7
A97: 8
A98: 9
A99: 10
B100: ФЭО (Кредиты/ Лизинг / Проценты / прочие платежи)
A101: 1
A102: 2
A103: 3
A104: 4
A105: 5
A106: ИТОГО ТД РТПЗ РАСХОДЫ ПО РЕЕСТРУ | E106: =SUM(E15:E105) -> 5600000
A107: ДЕФИЦИТ / ПРОФИЦИТ с Остатка на начало дня | E107: =E4-E106 -> 653760.69
A109: ООО ЖИВАЯ СТАЛЬ | E109: =SUM(E110:E113) -> 40116.14
A110: счёт СБ 1125 | E110: 40116.14
A115: № п/п | B115: Инициатор платежа | C115: Контрагент - Получатель | D115: Договор/Счет | E115: Сумма к оплате | F115: Назначение платежа | G115: Подразделение - плательщик | H115: Бюджет/Статья | I115: Наличие Договора | J115: Примечание | K115: Отметка об оплате | L115: Спец. Распоряжение
B116: Коммерческий отдел (Закупка товара / Логистика / Снабжение/ ВЭД / Хранение / ПРР / Маркетинг)
A117: 1
A118: 2
A119: 3
A120: 4
A121: 5
A122: 6
A123: 7
...

Sheet 27
C2: ='26'!C2+1 -> 46108
A4: ООО ТД РТПЗ | E4: =SUM(E5:E12) -> 3479181.5 | F4: РЕЕСТР ЗАКРЫТ !!!
A5: Волжский счёт СБ 7503 | E5: 3205641.6
A6: Головной счёт СБ 13291 | E6: 10252.91
A7: ИП Коваленко СБ 17500
A8: счёт ЦМР Банк | E8: 15821.6
A9: счёт РОСБАНК 1115 | E9: 43366.84
A10: счёт Райффайзенбанк 38867 | E10: 94295.62
A11: счёт Промсвязьбанк 5439 | E11: 66998.95
A12: счёт Альфа-Банк 10329 | E12: 42803.93
A14: № п/п | B14: Инициатор платежа | C14: Контрагент - Получатель | D14: Договор/Счет | E14: Сумма к оплате | F14: Назначение платежа | G14: Подразделение - плательщик | H14: Бюджет/Статья | I14: Наличие Договора | J14: Примечание | K14: Отметка об оплате | L14: Спец. Распоряжение
B15: Коммерческий отдел (ПОСТАВЩИКИ / ПОКУПАТЕЛИ)
A16: 1 | B16: Федоров А.А. | C16: Северсталь ПАО | D16: Договр № 643/1000-24100303 от 12.04.2024 | E16: .25 933 135,75 | F16: Металлопрокат
A17: 2 | B17: Федоров А.А. | C17: НЛМК ПАО | D17: Договор №204709-23 от 15.03.2023 | E17: 5000000 | F17: Металлопрокат | K17: оплачен
A18: 3
A19: 4
A20: 5
A21: 6
A22: 7
A23: 8
A24: 9
A25: 10
A26: 11
A27: 12
A28: 13
A29: 14
... A35: 20
B36: Коммерческий отдел (ЛОГИСТИКА / Хранение / ПРР)
A37: 1
A38: 2
A39: 3
A40: 4
A41: 5
A42: 6
A43: 7
A44: 8
A45: 9
A46: 10
A47: 11
A48: 12
... A56: 20
B57: ПРОИЗВОДСТВЕННЫЙ комплекс / ТЕХ служба
A58: 1
A59: 2
A60: 3
A61: 4
A62: 5
A63: 6
A64: 7
A65: 8
A66: 9
A67: 10
A68: 11
A69: 12
... A72: 15
B73: РАСХОДЫ ПРОЧИЕ (Тех служба / Складской коммплекс / IT служба / Юр служба / Секретариат / Кадры / Маркетинг)
A74: 1 | B74: Стадников | C74: ООО ТК Петролиум | D74: счет №94 от 26.03.2026 | E74: 50000 | F74: ГСМ | G74: РТПЗ Волжский | H74: Бюджет | K74: оплачен
A75: 2
A76: 3
A77: 4
A78: 5
A79: 6
A80: 7
A81: 8
A82: 9
A83: 10
A84: 11
A85: 12
A86: 13
... A88: 15
B89: Бухгалтерия (Налоги / ЗП / ЕСН / прочие платежи бух. службы)
A90: 1 | B90: Лазарева Л.Ю | C90: ИФНС по ЕНП | D90: КБК 18201061201010000510 | E90: 1425000 | F90: НДФЛ (период с 01.03-22.03.2026) (налоги с фот) | G90: РТПЗ Ростов | H90: Бюджет | J90: Крайний срок 30.03.2026 | K90: оплачен
A91: 2
A92: 3
A93: 4
A94: 5
A95: 6
A96: 7
A97: 8
A98: 9
A99: 10
B100: ФЭО (Кредиты/ Лизинг / Проценты / прочие платежи)
A101: 1
A102: 2
A103: 3
A104: 4
A105: 5
A106: ИТОГО ТД РТПЗ РАСХОДЫ ПО РЕЕСТРУ | E106: =SUM(E15:E105) -> 6475000
A107: ДЕФИЦИТ / ПРОФИЦИТ с Остатка на начало дня | E107: =E4-E106 -> -2995818.5
A109: ООО ЖИВАЯ СТАЛЬ | E109: =SUM(E110:E113) -> 40116.14
A110: счёт СБ 1125 | E110: 40116.14
A115: № п/п | B115: Инициатор платежа | C115: Контрагент - Получатель | D115: Договор/Счет | E115: Сумма к оплате | F115: Назначение платежа | G115: Подразделение - плательщик | H115: Бюджет/Статья | I115: Наличие Договора | J115: Примечание | K115: Отметка об оплате | L115: Спец. Распоряжение
B116: Коммерческий отдел (Закупка товара / Логистика / Снабжение/ ВЭД / Хранение / ПРР / Маркетинг)
A117: 1
A118: 2
A119: 3
A120: 4
A121: 5
A122: 6
A123: 7
...

Sheet 28
C2: ='27'!C2+1 -> 46109
A4: ООО ТД РТПЗ | E4: =SUM(E5:E12) -> 0
A5: Волжский счёт СБ 7503
A6: Головной счёт СБ 13291
A7: ИП Коваленко СБ 17500
A8: счёт ЦМР Банк
A9: счёт РОСБАНК 1115
A10: счёт Райффайзенбанк 38867
A11: счёт Промсвязьбанк 5439
A12: счёт Альфа-Банк 10329
A14: № п/п | B14: Инициатор платежа | C14: Контрагент - Получатель | D14: Договор/Счет | E14: Сумма к оплате | F14: Назначение платежа | G14: Подразделение - плательщик | H14: Бюджет/Статья | I14: Наличие Договора | J14: Примечание | K14: Отметка об оплате | L14: Спец. Распоряжение
B15: Коммерческий отдел (ПОСТАВЩИКИ / ПОКУПАТЕЛИ)
A16: 1
A17: 2
A18: 3
A19: 4
A20: 5
A21: 6
A22: 7
A23: 8
A24: 9
A25: 10
A26: 11
A27: 12
... A35: 20
B36: Коммерческий отдел (ЛОГИСТИКА / Хранение / ПРР)
A37: 1
A38: 2
A39: 3
A40: 4
A41: 5
A42: 6
A43: 7
A44: 8
A45: 9
A46: 10
A47: 11
A48: 12
... A56: 20
B57: ПРОИЗВОДСТВЕННЫЙ комплекс / ТЕХ служба
A58: 1
A59: 2
A60: 3
A61: 4
A62: 5
A63: 6
A64: 7
A65: 8
A66: 9
A67: 10
A68: 11
A69: 12
... A72: 15
B73: РАСХОДЫ ПРОЧИЕ (Тех служба / Складской коммплекс / IT служба / Юр служба / Секретариат / Кадры / Маркетинг)
A74: 1
A75: 2
A76: 3
A77: 4
A78: 5
A79: 6
A80: 7
A81: 8
A82: 9
A83: 10
A84: 11
A85: 12
... A88: 15
B89: Бухгалтерия (Налоги / ЗП / ЕСН / прочие платежи бух. службы)
A90: 1
A91: 2
A92: 3
A93: 4
A94: 5
A95: 6
A96: 7
A97: 8
A98: 9
A99: 10
B100: ФЭО (Кредиты/ Лизинг / Проценты / прочие платежи)
A101: 1
A102: 2
A103: 3
A104: 4
A105: 5
A106: ИТОГО ТД РТПЗ РАСХОДЫ ПО РЕЕСТРУ | E106: =SUM(E15:E105) -> 0
A107: ДЕФИЦИТ / ПРОФИЦИТ с Остатка на начало дня | E107: =E4-E106 -> 0
A109: ООО ЖИВАЯ СТАЛЬ | E109: =SUM(E110:E113) -> 0
A110: счёт СБ 1125
A115: № п/п | B115: Инициатор платежа | C115: Контрагент - Получатель | D115: Договор/Счет | E115: Сумма к оплате | F115: Назначение платежа | G115: Подразделение - плательщик | H115: Бюджет/Статья | I115: Наличие Договора | J115: Примечание | K115: Отметка об оплате | L115: Спец. Распоряжение
B116: Коммерческий отдел (Закупка товара / Логистика / Снабжение/ ВЭД / Хранение / ПРР / Маркетинг)
A117: 1
A118: 2
A119: 3
A120: 4
A121: 5
A122: 6
A123: 7
A124: 8
A125: 9
A126: 10
...

Sheet 29
C2: ='28'!C2+1 -> 46110
A4: ООО ТД РТПЗ | E4: =SUM(E5:E12) -> 0
A5: Волжский счёт СБ 7503
A6: Головной счёт СБ 13291
A7: ИП Коваленко СБ 17500
A8: счёт ЦМР Банк
A9: счёт РОСБАНК 1115
A10: счёт Райффайзенбанк 38867
A11: счёт Промсвязьбанк 5439
A12: счёт Альфа-Банк 10329
A14: № п/п | B14: Инициатор платежа | C14: Контрагент - Получатель | D14: Договор/Счет | E14: Сумма к оплате | F14: Назначение платежа | G14: Подразделение - плательщик | H14: Бюджет/Статья | I14: Наличие Договора | J14: Примечание | K14: Отметка об оплате | L14: Спец. Распоряжение
B15: Коммерческий отдел (ПОСТАВЩИКИ / ПОКУПАТЕЛИ)
A16: 1
A17: 2
A18: 3
A19: 4
A20: 5
A21: 6
A22: 7
A23: 8
A24: 9
A25: 10
A26: 11
A27: 12
... A35: 20
B36: Коммерческий отдел (ЛОГИСТИКА / Хранение / ПРР)
A37: 1
A38: 2
A39: 3
A40: 4
A41: 5
A42: 6
A43: 7
A44: 8
A45: 9
A46: 10
A47: 11
A48: 12
... A56: 20
B57: ПРОИЗВОДСТВЕННЫЙ комплекс / ТЕХ служба
A58: 1
A59: 2
A60: 3
A61: 4
A62: 5
A63: 6
A64: 7
A65: 8
A66: 9
A67: 10
A68: 11
A69: 12
... A72: 15
B73: РАСХОДЫ ПРОЧИЕ (Тех служба / Складской коммплекс / IT служба / Юр служба / Секретариат / Кадры / Маркетинг)
A74: 1
A75: 2
A76: 3
A77: 4
A78: 5
A79: 6
A80: 7
A81: 8
A82: 9
A83: 10
A84: 11
A85: 12
... A88: 15
B89: Бухгалтерия (Налоги / ЗП / ЕСН / прочие платежи бух. службы)
A90: 1
A91: 2
A92: 3
A93: 4
A94: 5
A95: 6
A96: 7
A97: 8
A98: 9
A99: 10
B100: ФЭО (Кредиты/ Лизинг / Проценты / прочие платежи)
A101: 1
A102: 2
A103: 3
A104: 4
A105: 5
A106: ИТОГО ТД РТПЗ РАСХОДЫ ПО РЕЕСТРУ | E106: =SUM(E15:E105) -> 0
A107: ДЕФИЦИТ / ПРОФИЦИТ с Остатка на начало дня | E107: =E4-E106 -> 0
A109: ООО ЖИВАЯ СТАЛЬ | E109: =SUM(E110:E113) -> 0
A110: счёт СБ 1125
A115: № п/п | B115: Инициатор платежа | C115: Контрагент - Получатель | D115: Договор/Счет | E115: Сумма к оплате | F115: Назначение платежа | G115: Подразделение - плательщик | H115: Бюджет/Статья | I115: Наличие Договора | J115: Примечание | K115: Отметка об оплате | L115: Спец. Распоряжение
B116: Коммерческий отдел (Закупка товара / Логистика / Снабжение/ ВЭД / Хранение / ПРР / Маркетинг)
A117: 1
A118: 2
A119: 3
A120: 4
A121: 5
A122: 6
A123: 7
A124: 8
A125: 9
A126: 10
...

Sheet 30
C2: ='29'!C2+1 -> 46111
A4: ООО ТД РТПЗ | E4: =SUM(E5:E12) -> 5923231.6 | F4: РЕЕСТР ЗАКРЫТ !!!
A5: Волжский счёт СБ 7503 | E5: 4649691.7
A6: Головной счёт СБ 13291 | E6: 10252.91
A7: ИП Коваленко СБ 17500
A8: счёт ЦМР Банк | E8: 15821.6
A9: счёт РОСБАНК 1115 | E9: 43366.84
A10: счёт Райффайзенбанк 38867 | E10: 94295.62
A11: счёт Промсвязьбанк 5439 | E11: 1066998.9
A12: счёт Альфа-Банк 10329 | E12: 42803.93
A14: № п/п | B14: Инициатор платежа | C14: Контрагент - Получатель | D14: Договор/Счет | E14: Сумма к оплате | F14: Назначение платежа | G14: Подразделение - плательщик | H14: Бюджет/Статья | I14: Наличие Договора | J14: Примечание | K14: Отметка об оплате | L14: Спец. Распоряжение
B15: Коммерческий отдел (ПОСТАВЩИКИ / ПОКУПАТЕЛИ)
A16: 1 | B16: Федоров А.А. | C16: Северсталь ПАО | D16: Договр № 643/1000-24100303 от 12.04.2024 | E16: .25 933 135,75 | F16: Металлопрокат | I16: Да
A17: 2 | B17: Федоров А.А. | C17: НЛМК ПАО | D17: Договор №204709-23 от 15.03.2023 | F17: Металлопрокат | I17: Да
A18: 3 | B18: Федоров А.А. | C18: Сталепромышленная компания АО | D18: Договор поставки № 30/2019 от 02.04.2019 | E18: .977032,5 | F18: Металлопрокат | I18: Да
A19: 4
A20: 5
A21: 6
A22: 7
A23: 8
A24: 9
A25: 10
A26: 11
A27: 12
A28: 13
A29: 14
A30: 15
... A35: 20
B36: Коммерческий отдел (ЛОГИСТИКА / Хранение / ПРР)
A37: 1
A38: 2
A39: 3
A40: 4
A41: 5
A42: 6
A43: 7
A44: 8
A45: 9
A46: 10
A47: 11
A48: 12
... A56: 20
B57: ПРОИЗВОДСТВЕННЫЙ комплекс / ТЕХ служба
A58: 1
A59: 2
A60: 3
A61: 4 | B61: Любимов Ю.В. | C61: ООО Центрэнерго | D61: Договор №40ЭС-20 от 15.10.2020 г. | E61: 950000 | F61: реквизиты АБ Россия за потребление электроэнергии в марте 2026 г. | G61: РТПЗ Волжский | H61: Внебюджет платим | I61: Да | K61: оплачен
A62: 5
A63: 6
A64: 7
A65: 8
A66: 9
A67: 10
A68: 11
A69: 12
A70: 13
A71: 14
A72: 15
B73: РАСХОДЫ ПРОЧИЕ (Тех служба / Складской коммплекс / IT служба / Юр служба / Секретариат / Кадры / Маркетинг)
A74: 1 | B74: Антоненко | C74: ИП ПОГУДИН ГРИГОРИЙ АНДРЕЕВИЧ | D74: Счет на оплату № 522 от 25 марта 2026 г. | E74: .4000 | F74: Брошюра ООО «РТПЗ», полимерный рулон, 4 страницы, А5 | H74: Внебюджет | I74: Да
A75: 2
A76: 3
A77: 4
A78: 5
A79: 6
A80: 7
A81: 8
A82: 9
A83: 10
A84: 11
A85: 12
A86: 13
... A88: 15
B89: Бухгалтерия (Налоги / ЗП / ЕСН / прочие платежи бух. службы)
A90: 1 | B90: Татаринова Н.А. | C90: ИФНС по ЕНП | D90: КБК 18201061201010000510 | E90: =11813+10216+14888+2685+28703+174923/3 -> 126612.67 | F90: Прибыль доплата год 2025 и аванс март 2026 | H90: Бюджет 10тыс | K90: оплачен
A91: 2
A92: 3
A93: 4
A94: 5
A95: 6
A96: 7
A97: 8
A98: 9
A99: 10
B100: ФЭО (Кредиты/ Лизинг / Проценты / прочие платежи)
A101: 1 | B101: Панфилова Е.О. | C101: ПСБ | D101: 84-32315/0353 | E101: .50000000 | F101: гасим тело долга | J101: НЕТ (Пышный)
A102: 2
A103: 3
A104: 4
A105: 5
A106: ИТОГО ТД РТПЗ РАСХОДЫ ПО РЕЕСТРУ | E106: =SUM(E15:E105) -> 1076612.7
A107: ДЕФИЦИТ / ПРОФИЦИТ с Остатка на начало дня | E107: =E4-E106 -> 4846618.9
A109: ООО ЖИВАЯ СТАЛЬ | E109: =SUM(E110:E113) -> 40116.14 | F109: РЕЕСТР ЗАКРЫТ !!!
A110: счёт СБ 1125 | E110: 40116.14
A115: № п/п | B115: Инициатор платежа | C115: Контрагент - Получатель | D115: Договор/Счет | E115: Сумма к оплате | F115: Назначение платежа | G115: Подразделение - плательщик | H115: Бюджет/Статья | I115: Наличие Договора | J115: Примечание | K115: Отметка об оплате | L115: Спец. Распоряжение
B116: Коммерческий отдел (Закупка товара / Логистика / Снабжение/ ВЭД / Хранение / ПРР / Маркетинг)
A117: 1
A118: 2
A119: 3
A120: 4
...

Sheet 31
C2: ='30'!C2+1 -> 46112
A4: ООО ТД РТПЗ | E4: =SUM(E5:E12) -> 1662698 | F4: РЕЕСТР ЗАКРЫТ !!!
A5: Волжский счёт СБ 7503 | E5: 1419968.1
A6: Головной счёт СБ 13291 | E6: 10252.91
A7: ИП Коваленко СБ 17500
A8: счёт ЦМР Банк | E8: 15821.6
A9: счёт РОСБАНК 1115 | E9: 43366.84
A10: счёт Райффайзенбанк 38867 | E10: 94272.62
A11: счёт Промсвязьбанк 5439 | E11: 66998.95
A12: счёт Альфа-Банк 10329 | E12: 12016.93
A14: № п/п | B14: Инициатор платежа | C14: Контрагент - Получатель | D14: Договор/Счет | E14: Сумма к оплате | F14: Назначение платежа | G14: Подразделение - плательщик | H14: Бюджет/Статья | I14: Наличие Договора | J14: Примечание | K14: Отметка об оплате | L14: Спец. Распоряжение
B15: Коммерческий отдел (ПОСТАВЩИКИ / ПОКУПАТЕЛИ)
A16: 1
A17: 2 | B17: Федоров А.А. | C17: Северсталь ПАО | D17: Договр № 643/1000-24100303 от 12.04.2024 | E17: .25 933 135,75 | F17: Металлопрокат | I17: Да
A18: 3 | B18: Федоров А.А. | C18: НЛМК ПАО | D18: Договор №204709-23 от 15.03.2023 | F18: Металлопрокат | I18: Да
A19: 4 | B19: Федоров А.А. | C19: Сталепромышленная компания АО | D19: Договор поставки № 30/2019 от 02.04.2019 | E19: .977032,5 | F19: Металлопрокат | I19: Да
A20: 5
A21: 6
A22: 7
A23: 8
A24: 9
A25: 10
A26: 11
A27: 12
A28: 13
A29: 14
A30: 15
A31: 16
... A35: 20
B36: Коммерческий отдел (ЛОГИСТИКА / Хранение / ПРР)
A37: 1
A38: 2
A39: 3
A40: 4
A41: 5
A42: 6
A43: 7
A44: 8
A45: 9
A46: 10
A47: 11
A48: 12
... A56: 20
B57: ПРОИЗВОДСТВЕННЫЙ комплекс / ТЕХ служба
A58: 1 | B58: Любимов Ю.В. | C58: ИП Анохина Л. В. | D58: Договор №01052024 от 01.05.2024 г. | E58: 170000 | F58: НДС не облагается. Аренда движимого имущества по договору №01052024 от 01.05.2024 г. за февраль 2026 г. | G58: РТПЗ Волжский | H58: Бюджет | I58: Да | K58: оплачен
A59: 2
A60: 3
A61: 4
A62: 5
A63: 6
A64: 7
A65: 8
A66: 9
A67: 10
A68: 11
A69: 12
A70: 13
... A72: 15
B73: РАСХОДЫ ПРОЧИЕ (Тех служба / Складской коммплекс / IT служба / Юр служба / Секретариат / Кадры / Маркетинг)
A74: 1
A75: 2
A76: 3
A77: 4
A78: 5
A79: 6
A80: 7
A81: 8
A82: 9
A83: 10
A84: 11
A85: 12
... A88: 15
B89: Бухгалтерия (Налоги / ЗП / ЕСН / прочие платежи бух. службы)
A90: 1 | B90: Ермолина | C90: Сидоров И В | D90: авансовый отчет | E90: 3500 | F90: шиномонтаж авто CHERY 430 | H90: Внебюджет МЕТКОМ | K90: оплачен
A91: 2
A92: 3
A93: 4
A94: 5
A95: 6
A96: 7
A97: 8
A98: 9
A99: 10
B100: ФЭО (Кредиты/ Лизинг / Проценты / прочие платежи)
A101: 1 | B101: Панфилова Е.О. | C101: ПСБ | D101: 84-32315/0353 | E101: 50000000 | F101: гасим тело долга | J101: посмотрим (пышный)
A102: 2 | B102: Панфилова Е.О. | C102: ПСБ | D102: 84-32315/0353 | E102: .50000000 | F102: гасим тело долга | J102: НЕТ (Пышный)
A103: 3
A104: 4
A105: 5
A106: ИТОГО ТД РТПЗ РАСХОДЫ ПО РЕЕСТРУ | E106: =SUM(E15:E105) -> 50173500
A107: ДЕФИЦИТ / ПРОФИЦИТ с Остатка на начало дня | E107: =E4-E106 -> -48510802
A109: ООО ЖИВАЯ СТАЛЬ | E109: =SUM(E110:E113) -> 28960.14
A110: счёт СБ 1125 | E110: 28960.14
A115: № п/п | B115: Инициатор платежа | C115: Контрагент - Получатель | D115: Договор/Счет | E115: Сумма к оплате | F115: Назначение платежа | G115: Подразделение - плательщик | H115: Бюджет/Статья | I115: Наличие Договора | J115: Примечание | K115: Отметка об оплате | L115: Спец. Распоряжение
B116: Коммерческий отдел (Закупка товара / Логистика / Снабжение/ ВЭД / Хранение / ПРР / Маркетинг)
A117: 1
A118: 2
A119: 3
A120: 4
A121: 5
...

Sheet Тех.Лист
A1: Да
A2: Нет
