Workbook
Name ДаНет: Тех.Лист!$A$1:$A$2

Sheet 01
E1: _____________________________ Согласовано
C2: 46082 | F2: Реестр разбит по Юр. лицам!!! КРУТИТЕ ВНИЗ
A4: ФАБРИКА ПРОЕКТОВ | E4: =SUM(E5:E6) -> 0
A5: Счет Альфа 1674
A6: счет СБЕР 6989
A8: № п/п | B8: Инициатор платежа | C8: Контрагент - Получатель | D8: Договор/Счет | E8: Сумма к оплате | F8: Назначение платежа | G8: Бюджет/Статья | H8: Наличие Договора | I8: Примечание | J8: Отметка об оплате | K8: Спец. Распоряжение / Приоритет
B9: Коммерческая деятельность (Закупка ТМЦ Снабжение / Логистика / Транзит)
A10: 1
A11: 2
A12: 3
A13: 4
A14: 5
A15: 6
A16: 7
A17: 8
A18: 9
A19: 10
A20: 11
A21: 12
... A59: 50
B60: АХР (Продажи / IT служба / Юр служба / ФЭО /Секретариат)
A61: 1
A62: 2
A63: 3
A64: 4
A65: 5
B66: Бухгалтерия (Налоги / ЗП / ЕСН / прочие платежи бух. службы)
A67: 1
A68: 2
A69: 3
A70: 4
A71: 5
A72: ИТОГО ФАБРИКА ПРОЕКТОВ РАСХОДЫ ПО РЕЕСТРУ | E72: =SUM(E9:E71) -> 0
A73: ДЕФИЦИТ / ПРОФИЦИТ с Остатка на начало дня | E73: =E4-E72 -> 0

Sheet 02
E1: _____________________________ Согласовано
C2: ='01'!C2+1 -> 46083 | F2: Реестр разбит по Юр. лицам!!! КРУТИТЕ ВНИЗ
A4: ФАБРИКА ПРОЕКТОВ | E4: =SUM(E5:E6) -> 87344.23 | F4: Реестр закрыт!!!
A5: Счет Альфа 1674 | E5: 85663.59
A6: счет СБЕР 6989 | E6: 1680.64
A8: № п/п | B8: Инициатор платежа | C8: Контрагент - Получатель | D8: Договор/Счет | E8: Сумма к оплате | F8: Назначение платежа | G8: Бюджет/Статья | H8: Наличие Договора | I8: Примечание | J8: Отметка об оплате | K8: Спец. Распоряжение / Приоритет
B9: Коммерческая деятельность (Закупка ТМЦ Снабжение / Логистика / Транзит)
A10: 1
A11: 2
A12: 3
A13: 4
A14: 5
A15: 6
A16: 7
A17: 8
A18: 9
A19: 10
A20: 11
A21: 12
... A59: 50
B60: АХР (Продажи / IT служба / Юр служба / ФЭО /Секретариат)
A61: 1
A62: 2
A63: 3
A64: 4
A65: 5
B66: Бухгалтерия (Налоги / ЗП / ЕСН / прочие платежи бух. службы)
A67: 1
A68: 2
A69: 3
A70: 4
A71: 5
A72: ИТОГО ФАБРИКА ПРОЕКТОВ РАСХОДЫ ПО РЕЕСТРУ | E72: =SUM(E9:E71) -> 0
A73: ДЕФИЦИТ / ПРОФИЦИТ с Остатка на начало дня | E73: =E4-E72 -> 87344.23

Sheet 03
E1: _____________________________ Согласовано
C2: ='02'!C2+1 -> 46084 | F2: Реестр разбит по Юр. лицам!!! КРУТИТЕ ВНИЗ
A4: ФАБРИКА ПРОЕКТОВ | E4: =SUM(E5:E6) -> 87344.23 | F4: Реестр закрыт!!!
A5: Счет Альфа 1674 | E5: 85663.59 | F5: 135 400 с РИК
A6: счет СБЕР 6989 | E6: 1680.64 | F6: 20 000 с УК
A8: № п/п | B8: Инициатор платежа | C8: Контрагент - Получатель | D8: Договор/Счет | E8: Сумма к оплате | F8: Назначение платежа | G8: Бюджет/Статья | H8: Наличие Договора | I8: Примечание | J8: Отметка об оплате | K8: Спец. Распоряжение / Приоритет
B9: Коммерческая деятельность (Закупка ТМЦ Снабжение / Логистика / Транзит)
A10: 1 | B10: Лещенко В.А. | C10: ООО ГЕРМЕС | D10: Счет № 493 от 24.10.2025 | E10: .218750 | F10: Закупка бетона | G10: Бюджет | H10: Да | I10: ГП 294 Забор. ИП Малый. Договор №ФП31072025 от 31.07.2025 Приложение №2
A11: =A10+1 -> 2 | B11: Лещенко В.А. | C11: ООО "Айрон" | D11: Счет №АИПП-2504 от 21.03.2025 | E11: .=16534 | F11: Закупка металла. | G11: Бюджет | H11: Да | I11: (Щепкино. СПА.стены)ИП Малый Договор подряда №ФП-03022025 от 03.02.2025 Пр. №2 от 03.02.2025 ИП Малый
A12: =A11+1 -> 3 | B12: Лещенко В.А. | C12: ООО "Айрон" | D12: Счет № АИПП-3664 от 25.04.2025 | E12: .126845 | F12: Закупка металла на объект | G12: Бюджет | H12: Да | I12: ГП 204 (Навес) Договор подряда №ФП-27032025 от 27.03.2025 Приложение № 2 от 27.03.2025
A13: =A12+1 -> 4 | B13: Лещенко В.А. | C13: ООО "Айрон" | D13: Счет № АИПП-3754 от 29.04.2025 | E13: .27325 | F13: Закупка металла. | G13: Бюджет | H13: Да | I13: ГП 204(навес) Договор подряда №ФП-27032025 от 27.03.2025 Приложение №2 от 27.03.2025
A14: =A13+1 -> 5 | B14: Лещенко В.А. | C14: ООО "Айрон" | D14: Счет № АИПП-5404 от 30.06.2025 | E14: .150100 | F14: Закупка металла на объект | G14: Бюджет | H14: Да | I14: ГП 294. ХБП ИП Малый Договор подряда №ФП-19062025 от 19.06.2025 Приложение №2 от 19.06.2025
A15: =A14+1 -> 6 | B15: Лещенко В.А. | C15: ООО "Айрон" | D15: Счет № АИПП-5407 от 30.06.2025 | E15: .17300 | F15: Закупка металла на объект | G15: Бюджет | H15: Да | I15: ГП 204. ИП Малый. Договор подряда №ФП-27032025 от 27.03.2025 Приложение №2 от 27.03.2025
A16: =A15+1 -> 7 | B16: Лещенко В.А. | C16: ООО "Айрон" | D16: Счет № АИПП-5408 от 30.06.2025 | E16: .35505 | F16: Закупка металла на объект | G16: Бюджет | H16: Да | I16: ГП 13. (ХБП) ИП Малый. Договор подряда №ФП-10660-72/01 от 12.02.2024 г. Приложение №1/8 от 14.03.2025
A17: =A16+1 -> 8 | B17: Лещенко В.А. | C17: ООО "Айрон" | D17: Счет № АИПП-6301 от 04.08.2025 | E17: .163370 | F17: Закупка металла на объект | G17: Бюджет | H17: Да | I17: ГП 326. Забор ИП Малый
A18: =A17+1 -> 9 | B18: Лещенко В.А. | C18: ООО "Айрон" | D18: Счет № АИПП-6303 от 04.08.2025 | E18: .115500 | F18: Закупка металла на объект | G18: Бюджет | H18: Да | I18: ГП 294. Бассеин ИП Малый
A19: =A18+1 -> 10 | B19: Лещенко В.А. | C19: ООО "Айрон" | D19: Счет № АИПП-6304 от 04.08.2025 | E19: .51000 | F19: Закупка металла на объект | G19: Бюджет | H19: Да | I19: ГП 294. Забор ИП Малый
A20: =A19+1 -> 11 | B20: Лещенко В.А. | C20: ИП Полежаев А.А. | D20: Счет № 42 от 26.09.2025 | E20: .363298 | F20: Устройство фасада с молдингами на ХБП по дог.№ФП-10660-29 от 16.09.2022, пр.№ 1/19 | G20: Бюджет | H20: Да | I20: Окончательный ГП 326
A21: =A20+1 -> 12 | B21: Лещенко В.А. | C21: ИП Полежаев А.А. | D21: Счет № 44 от 30.09.2025 | E21: .313500 | F21: Устройство фасада с молдингами на ХБП. Договор подряда №ФП-10660-29 от 16.09.2022 Приложение № 1/25 | G21: Бюджет | H21: Да | I21: Аванс ГП 294,295
A22: =A21+1 -> 13 | B22: Малый П.А. | C22: ИП Полежаев А.А. | D22: Счёт №50 от 26.11.2025 | E22: .538264 | F22: Устройство фасада с молдингами | G22: Бюджет | H22: Да | I22: Окончательный ГП-243
A23: =A22+1 -> 14 | B23: Малый П.А. | C23: ИП Полежаев А.А. | D23: Счёт№51 от 02.12.2025 | E23: .54956 | F23: Устройство калон террасы | G23: Бюджет | I23: Окончательный. ГП-294.295 Договор подряда№ФП-10660-29 ОТ 16.09.2022
A24: =A23+1 -> 15 | B24: Малый П.А. | C24: ИП Полежаев А.А. | D24: Счёт№53 от 20.01.2025 | E24: .842553 | F24: Фасад | I24: ГП-148 Дог№-ФП-25112024-01от 25.11.2024 ПР№2 от 25.11.2024
A25: =A24+1 -> 16 | B25: Малый П.А. | C25: ИП Чередниченко | D25: Счёт № 17 от 05.12.2025. | E25: .112952 | F25: Монтаж натяжных потолков | G25: Бюджет | H25: да | I25: ГП-138 Дог-10660-84/01от01.10.2024
A26: =A25+1 -> 17 | B26: Лещенко В.А. | C26: ИП Любомирский В.Г. | D26: Счет № 20 от 28.07.2025 | E26: .558077 | F26: Электромонтажные работы | G26: Бюджет | H26: Да | I26: Вн. рынок. Щепкин СПА
A27: =A26+1 -> 18 | B27: Салпагаров Р.А. | C27: ИП Любомирский В.Г. | D27: Счет № 25 от 23.09.2025 | E27: .210906 | F27: Оплата работ по пр.1/12 от 22.09.25 к дог.№ФП-10660-10/01 от 19.03.2024г | G27: Бюджет | H27: Да | I27: ГП 13. Электрика. 4й этап
A28: =A27+1 -> 19 | B28: Малый П.А. | C28: ИП Кравченко К.Н. | D28: Счёт№542 от 24.10.2025 | E28: .32621,5 | F28: Пиломатериалы | G28: Бюджет | H28: Да | I28: Вн.Рынок. Щепкино, кровля
A29: =A28+1 -> 20 | B29: Малый П.А. | C29: ИП Кравченко К.Н. | D29: Счёт №548 от 28.10.2025 | E29: .38400 | F29: Пиломатериалы | G29: Бюджет | H29: Да | I29: Вн.Рынок. Щепкино,кровля
A30: =A29+1 -> 21 | B30: Малый П.А. | C30: ИП Кравченко К.Н. | D30: Счёт №566 от 19.11.2025 | E30: .38400 | F30: Пиломатериалы | G30: Бюджет | H30: Да | I30: Навес ГП 262
A31: =A30+1 -> 22 | B31: Малый П.А. | C31: ИП Кравченко К.Н. | D31: Счёт № 609 от 22.12.2025 | E31: .128725,35 | F31: Пиломатериалы | G31: Бюджет | I31: Навес ГП 262
A32: =A31+1 -> 23 | B32: Синицына В.В. | C32: ИП Храмова Э.Э. | D32: Счет №2042 от 17.11.2025 | E32: .42000 | F32: Услуги по благоустройству территории с 10.11.2025 по 13.11.2025 | G32: Бюджет | H32: Да
A33: =A32+1 -> 24 | B33: Малый П.А. | C33: ИП Храмова Э.Э | D33: Счёт№2177от 08.12.2025 | E33: .16800 | F33: Благоустройство территории | G33: Бюджет | I33: ГП-103 Дог№ФП-10660-36 Планирование грунта
A34: =A33+1 -> 25 | B34: Малый П.А. | C34: ИП Храмова Э.Э. | D34: Счёт№2233 от 15.12.2025 | E34: .8400 | F34: Благоустройство территории | G34: Бюджет | I34: ГП-218,231,213,214,216,221,188 Дог№10660-36 от 15.032023 чистка преддомовых территорий
A35: =A34+1 -> 26 | B35: Синицына В.В. | C35: ИП Храмова Э.Э. | D35: Счет №2252 от 22.12.2025 | E35: .42000 | F35: Услуги по благоустройству территории | G35: Бюджет
A36: =A35+1 -> 27 | B36: Синицына В.В. | C36: ИП Храмова Э.Э. | D36: Счет №2301 от 25.12.2025г. | E36: .25200 | F36: Услуги по благоустройству территории | G36: Бюджет
A37: =A36+1 -> 28 | B37: Салпагаров Р.А. | C37: ИП Сердечная О.Ю. | D37: Счет № 291 от 17.09.2025 | E37: .59500 | F37: Договор №3 от 30.03.2022 г. Транспортные услуги по перевозке опалубки, 05.09.2025 г.,16.09.2025 г. | G37: Бюджет | H37: Да | I37: ГП 294. Бассейн.ИП Малый
A38: =A37+1 -> 29 | B38: Салпагаров Р.А. | C38: ИП Козлова Н.В. | D38: Счет № 27 от 19.11.2024 | E38: .=30500 | F38: Ус-во фасада по дог.№ФП-10660-93 от 01.10.2024 от 19.11.2024 | G38: Бюджет | H38: Да | I38: Окончательный.ГП-211
A39: =A38+1 -> 30 | B39: Салпагаров Р.А. | C39: ООО "АЛЮМИНИУМ" | D39: Счет № 385 от 03.09.2025 | E39: .386200 | F39: Оплата за алюмииевые конструкции по дог.№ФП-28052024 от 28.05.2025 | G39: Бюджет | H39: Да | I39: ГП 291. Витражи.
A40: =A39+1 -> 31 | B40: Синицына В.В. | C40: ИП Никулов А.В. | D40: Счет №113 от 21.11.2025 | E40: .=146016/2 | F40: Аванс по Приложению 1/14 к Договору №ФП-10660-98 от 04.04.2025 | G40: Бюджет | I40: Монтаж системы полива на придомовой ГП 273, 280
A41: =A40+1 -> 32 | B41: Лещенко В.А. | C41: ИП Стрельцов В.А. | D41: Счет № 23 от 07.11.2025 | E41: .600050 | F41: Устройство приточно-вытяжной вентиляции согласно Приложения №1/13 от 11.06.2025г. к Договору подряда №ФП-10660-53/01 от 08.10.2024 г. | G41: Бюджет | H41: Да | I41: ГП 291. Вентиляция
A42: =A41+1 -> 33 | B42: Малый П.А. | C42: ИП Алты-Садых С.Ю | D42: Счёт№18/2 от 15.12.2025 | E42: .109250 | F42: Окончательный платеж за работы, изготовление,монтаж,шлифовку пропитку и окраску деревянных элементов террасы | G42: Бюджет | H42: да | I42: ГП-148 Дог№-ФП-10660-31 ОТ 14.11.2022
A43: =A42+1 -> 34 | B43: Салпагаров Р.А. | C43: ИП Чеботарев А.В. | D43: Счет № 1369 от 11.09.2025 | E43: .107000 | F43: Разработка дизайн проекта. Пр.№ 1/2 к дог.№ФП-10660-101 от 21.08.2025 | G43: Бюджет | H43: Да | I43: ГП 146
A44: =A43+1 -> 35 | B44: Малый П.А. | C44: ИП Глазунов Е.А. | D44: Счёт№15 от 22.01.2026 | E44: .18400 | F44: Уборка помещений | H44: Да
A45: =A44+1 -> 36 | B45: Лещенко В.А. | C45: сз Шкрябина | D45: Счет №24365802 от 04.12.2025г. | E45: .=414800-114800-130000 | F45: Монтаж фасонных изделий | G45: Бюджет | H45: Да | I45: ГП 291-292
A46: =A45+1 -> 37 | B46: Малый П.А. | C46: ИП Чеботарёв | D46: Счёт№281 от 24.02.2026 | E46: .30000 | F46: Авторский надзор | I46: ГП 291 Дог об авторском надзоре№2 от 24.02.2026
A47: =A46+1 -> 38 | B47: Малый П.А. | C47: ИП Доброхотова Н.А. | D47: Счёт№1 от 15.01.2026 | E47: .20000 | F47: ЛДУ | I47: Вн. рынок Ореховая роща Дог№ФП-10660 ОТ 21.02.2024
A48: =A47+1 -> 39 | B48: Малый П.А. | C48: ООО"Офисмаг" | D48: Счёт№Сч-КОР-326943от 18.02.2026 | E48: 3450.82 | F48: Канцтовары | G48: Бюджет | H48: Да | J48: оплачен
A49: =A48+1 -> 40
A50: =A49+1 -> 41
A51: =A50+1 -> 42
A52: =A51+1 -> 43
A53: =A52+1 -> 44
A54: =A53+1 -> 45
A55: =A54+1 -> 46
A56: =A55+1 -> 47
A57: =A56+1 -> 48
A58: =A57+1 -> 49
B59: АХР (Продажи / IT служба / Юр служба / ФЭО /Секретариат)
A60: 1
A61: 2
A62: 3
A63: 4
A64: 5
B65: Бухгалтерия (Налоги / ЗП / ЕСН / прочие платежи бух. службы)
A66: 1 | B66: Дмитриева О. В. | C66: ИФНС по ЕНП | D66: КБК 182 01 06 12 01 01 0000 510 | E66: .42000 | F66: НДФЛ (период с 23.02-28.02.2026) | I66: срок оплаты до 05.03.26
A67: 3 | B67: Дмитриева О. В. | C67: ИФНС по ЕНП | D67: КБК 182 01 06 12 01 01 0000 510 | E67: .73000 | F67: НДФЛ (период с 01.02-22.02.2026) | I67: срок оплаты до 02.03.26
A68: 4 | B68: Дмитриева О. В. | C68: ИФНС по ЕНП | D68: КБК 18201061201010000510 | E68: 235000 | F68: Страховые взносы за январь 2026 г (налоги с фот) | I68: срок оплаты до 02.03.26 | J68: оплачен
A69: 5
A70: ИТОГО ФАБРИКА ПРОЕКТОВ РАСХОДЫ ПО РЕЕСТРУ | E70: =SUM(E9:E69) -> 238450.82
A71: ДЕФИЦИТ / ПРОФИЦИТ с Остатка на начало дня | E71: =E4-E70 -> -151106.59

Sheet 04
E1: _____________________________ Согласовано
C2: ='03'!C2+1 -> 46085 | F2: Реестр разбит по Юр. лицам!!! КРУТИТЕ ВНИЗ
A4: ФАБРИКА ПРОЕКТОВ | E4: =SUM(E5:E6) -> 4253.41 | F4: Реестр закрыт!!!
A5: Счет Альфа 1674 | E5: 2572.77
A6: счет СБЕР 6989 | E6: 1680.64
A8: № п/п | B8: Инициатор платежа | C8: Контрагент - Получатель | D8: Договор/Счет | E8: Сумма к оплате | F8: Назначение платежа | G8: Бюджет/Статья | H8: Наличие Договора | I8: Примечание | J8: Отметка об оплате | K8: Спец. Распоряжение / Приоритет
B9: Коммерческая деятельность (Закупка ТМЦ Снабжение / Логистика / Транзит)
A10: 1
A11: 2
A12: 3
A13: 4
A14: 5
A15: 6
A16: 7
A17: 8
A18: 9
A19: 10
A20: 11
A21: 12
... A59: 50
B60: АХР (Продажи / IT служба / Юр служба / ФЭО /Секретариат)
A61: 1
A62: 2
A63: 3
A64: 4
A65: 5
B66: Бухгалтерия (Налоги / ЗП / ЕСН / прочие платежи бух. службы)
A67: 1
A68: 2
A69: 3
A70: 4
A71: 5
A72: ИТОГО ФАБРИКА ПРОЕКТОВ РАСХОДЫ ПО РЕЕСТРУ | E72: =SUM(E9:E71) -> 0
A73: ДЕФИЦИТ / ПРОФИЦИТ с Остатка на начало дня | E73: =E4-E72 -> 4253.41

Sheet 05
E1: _____________________________ Согласовано
C2: ='04'!C2+1 -> 46086 | F2: Реестр разбит по Юр. лицам!!! КРУТИТЕ ВНИЗ
A4: ФАБРИКА ПРОЕКТОВ | E4: =SUM(E5:E6) -> 166889.41 | F4: Реестр закрыт!!!
A5: Счет Альфа 1674 | E5: 165208.77
A6: счет СБЕР 6989 | E6: 1680.64
A8: № п/п | B8: Инициатор платежа | C8: Контрагент - Получатель | D8: Договор/Счет | E8: Сумма к оплате | F8: Назначение платежа | G8: Бюджет/Статья | H8: Наличие Договора | I8: Примечание | J8: Отметка об оплате | K8: Спец. Распоряжение / Приоритет
B9: Коммерческая деятельность (Закупка ТМЦ Снабжение / Логистика / Транзит)
A10: 1 | B10: Лещенко В.А. | C10: ООО ГЕРМЕС | D10: Счет № 493 от 24.10.2025 | E10: .218750 | F10: Закупка бетона | G10: Бюджет | H10: Да | I10: ГП 294 Забор. ИП Малый. Договор №ФП31072025 от 31.07.2025 Приложение №2
A11: =A10+1 -> 2 | B11: Лещенко В.А. | C11: ООО "Айрон" | D11: Счет №АИПП-2504 от 21.03.2025 | E11: .=16534 | F11: Закупка металла. | G11: Бюджет | H11: Да | I11: (Щепкино. СПА.стены)ИП Малый Договор подряда №ФП-03022025 от 03.02.2025 Пр. №2 от 03.02.2025 ИП Малый
A12: =A11+1 -> 3 | B12: Лещенко В.А. | C12: ООО "Айрон" | D12: Счет № АИПП-3664 от 25.04.2025 | E12: .126845 | F12: Закупка металла на объект | G12: Бюджет | H12: Да | I12: ГП 204 (Навес) Договор подряда №ФП-27032025 от 27.03.2025 Приложение № 2 от 27.03.2025
A13: =A12+1 -> 4 | B13: Лещенко В.А. | C13: ООО "Айрон" | D13: Счет № АИПП-3754 от 29.04.2025 | E13: .27325 | F13: Закупка металла. | G13: Бюджет | H13: Да | I13: ГП 204(навес) Договор подряда №ФП-27032025 от 27.03.2025 Приложение №2 от 27.03.2025
A14: =A13+1 -> 5 | B14: Лещенко В.А. | C14: ООО "Айрон" | D14: Счет № АИПП-5404 от 30.06.2025 | E14: .150100 | F14: Закупка металла на объект | G14: Бюджет | H14: Да | I14: ГП 294. ХБП ИП Малый Договор подряда №ФП-19062025 от 19.06.2025 Приложение №2 от 19.06.2025
A15: =A14+1 -> 6 | B15: Лещенко В.А. | C15: ООО "Айрон" | D15: Счет № АИПП-5407 от 30.06.2025 | E15: .17300 | F15: Закупка металла на объект | G15: Бюджет | H15: Да | I15: ГП 204. ИП Малый. Договор подряда №ФП-27032025 от 27.03.2025 Приложение №2 от 27.03.2025
A16: =A15+1 -> 7 | B16: Лещенко В.А. | C16: ООО "Айрон" | D16: Счет № АИПП-5408 от 30.06.2025 | E16: .35505 | F16: Закупка металла на объект | G16: Бюджет | H16: Да | I16: ГП 13. (ХБП) ИП Малый. Договор подряда №ФП-10660-72/01 от 12.02.2024 г. Приложение №1/8 от 14.03.2025
A17: =A16+1 -> 8 | B17: Лещенко В.А. | C17: ООО "Айрон" | D17: Счет № АИПП-6301 от 04.08.2025 | E17: .163370 | F17: Закупка металла на объект | G17: Бюджет | H17: Да | I17: ГП 326. Забор ИП Малый
A18: =A17+1 -> 9 | B18: Лещенко В.А. | C18: ООО "Айрон" | D18: Счет № АИПП-6303 от 04.08.2025 | E18: .115500 | F18: Закупка металла на объект | G18: Бюджет | H18: Да | I18: ГП 294. Бассеин ИП Малый
A19: =A18+1 -> 10 | B19: Лещенко В.А. | C19: ООО "Айрон" | D19: Счет № АИПП-6304 от 04.08.2025 | E19: .51000 | F19: Закупка металла на объект | G19: Бюджет | H19: Да | I19: ГП 294. Забор ИП Малый
A20: =A19+1 -> 11 | B20: Лещенко В.А. | C20: ИП Полежаев А.А. | D20: Счет № 42 от 26.09.2025 | E20: .363298 | F20: Устройство фасада с молдингами на ХБП по дог.№ФП-10660-29 от 16.09.2022, пр.№ 1/19 | G20: Бюджет | H20: Да | I20: Окончательный ГП 326
A21: =A20+1 -> 12 | B21: Лещенко В.А. | C21: ИП Полежаев А.А. | D21: Счет № 44 от 30.09.2025 | E21: .313500 | F21: Устройство фасада с молдингами на ХБП. Договор подряда №ФП-10660-29 от 16.09.2022 Приложение № 1/25 | G21: Бюджет | H21: Да | I21: Аванс ГП 294,295
A22: =A21+1 -> 13 | B22: Малый П.А. | C22: ИП Полежаев А.А. | D22: Счёт №50 от 26.11.2025 | E22: .538264 | F22: Устройство фасада с молдингами | G22: Бюджет | H22: Да | I22: Окончательный ГП-243
A23: =A22+1 -> 14 | B23: Малый П.А. | C23: ИП Полежаев А.А. | D23: Счёт№51 от 02.12.2025 | E23: .54956 | F23: Устройство калон террасы | G23: Бюджет | I23: Окончательный. ГП-294.295 Договор подряда№ФП-10660-29 ОТ 16.09.2022
A24: =A23+1 -> 15 | B24: Малый П.А. | C24: ИП Полежаев А.А. | D24: Счёт№53 от 20.01.2025 | E24: .842553 | F24: Фасад | I24: ГП-148 Дог№-ФП-25112024-01от 25.11.2024 ПР№2 от 25.11.2024
A25: =A24+1 -> 16 | B25: Малый П.А. | C25: ИП Чередниченко | D25: Счёт № 17 от 05.12.2025. | E25: .112952 | F25: Монтаж натяжных потолков | G25: Бюджет | H25: да | I25: ГП-138 Дог-10660-84/01от01.10.2024
A26: =A25+1 -> 17 | B26: Лещенко В.А. | C26: ИП Любомирский В.Г. | D26: Счет № 20 от 28.07.2025 | E26: .558077 | F26: Электромонтажные работы | G26: Бюджет | H26: Да | I26: Вн. рынок. Щепкин СПА
A27: =A26+1 -> 18 | B27: Салпагаров Р.А. | C27: ИП Любомирский В.Г. | D27: Счет № 25 от 23.09.2025 | E27: .210906 | F27: Оплата работ по пр.1/12 от 22.09.25 к дог.№ФП-10660-10/01 от 19.03.2024г | G27: Бюджет | H27: Да | I27: ГП 13. Электрика. 4й этап
A28: =A27+1 -> 19 | B28: Малый П.А. | C28: ИП Кравченко К.Н. | D28: Счёт№542 от 24.10.2025 | E28: .32621,5 | F28: Пиломатериалы | G28: Бюджет | H28: Да | I28: Вн.Рынок. Щепкино, кровля
A29: =A28+1 -> 20 | B29: Малый П.А. | C29: ИП Кравченко К.Н. | D29: Счёт №548 от 28.10.2025 | E29: .38400 | F29: Пиломатериалы | G29: Бюджет | H29: Да | I29: Вн.Рынок. Щепкино,кровля
A30: =A29+1 -> 21 | B30: Малый П.А. | C30: ИП Кравченко К.Н. | D30: Счёт №566 от 19.11.2025 | E30: .38400 | F30: Пиломатериалы | G30: Бюджет | H30: Да | I30: Навес ГП 262
A31: =A30+1 -> 22 | B31: Малый П.А. | C31: ИП Кравченко К.Н. | D31: Счёт № 609 от 22.12.2025 | E31: .128725,35 | F31: Пиломатериалы | G31: Бюджет | I31: Навес ГП 262
A32: =A31+1 -> 23 | B32: Синицына В.В. | C32: ИП Храмова Э.Э. | D32: Счет №2042 от 17.11.2025 | E32: .42000 | F32: Услуги по благоустройству территории с 10.11.2025 по 13.11.2025 | G32: Бюджет | H32: Да
A33: =A32+1 -> 24 | B33: Малый П.А. | C33: ИП Храмова Э.Э | D33: Счёт№2177от 08.12.2025 | E33: .16800 | F33: Благоустройство территории | G33: Бюджет | I33: ГП-103 Дог№ФП-10660-36 Планирование грунта
A34: =A33+1 -> 25 | B34: Малый П.А. | C34: ИП Храмова Э.Э. | D34: Счёт№2233 от 15.12.2025 | E34: .8400 | F34: Благоустройство территории | G34: Бюджет | I34: ГП-218,231,213,214,216,221,188 Дог№10660-36 от 15.032023 чистка преддомовых территорий
A35: =A34+1 -> 26 | B35: Синицына В.В. | C35: ИП Храмова Э.Э. | D35: Счет №2252 от 22.12.2025 | E35: .42000 | F35: Услуги по благоустройству территории | G35: Бюджет
A36: =A35+1 -> 27 | B36: Синицына В.В. | C36: ИП Храмова Э.Э. | D36: Счет №2301 от 25.12.2025г. | E36: .25200 | F36: Услуги по благоустройству территории | G36: Бюджет
A37: =A36+1 -> 28 | B37: Салпагаров Р.А. | C37: ИП Сердечная О.Ю. | D37: Счет № 291 от 17.09.2025 | E37: .59500 | F37: Договор №3 от 30.03.2022 г. Транспортные услуги по перевозке опалубки, 05.09.2025 г.,16.09.2025 г. | G37: Бюджет | H37: Да | I37: ГП 294. Бассейн.ИП Малый
A38: =A37+1 -> 29 | B38: Салпагаров Р.А. | C38: ИП Козлова Н.В. | D38: Счет № 27 от 19.11.2024 | E38: .=30500 | F38: Ус-во фасада по дог.№ФП-10660-93 от 01.10.2024 от 19.11.2024 | G38: Бюджет | H38: Да | I38: Окончательный.ГП-211
A39: =A38+1 -> 30 | B39: Салпагаров Р.А. | C39: ООО "АЛЮМИНИУМ" | D39: Счет № 385 от 03.09.2025 | E39: .386200 | F39: Оплата за алюмииевые конструкции по дог.№ФП-28052024 от 28.05.2025 | G39: Бюджет | H39: Да | I39: ГП 291. Витражи.
A40: =A39+1 -> 31 | B40: Синицына В.В. | C40: ИП Никулов А.В. | D40: Счет №113 от 21.11.2025 | E40: .=146016/2 | F40: Аванс по Приложению 1/14 к Договору №ФП-10660-98 от 04.04.2025 | G40: Бюджет | I40: Монтаж системы полива на придомовой ГП 273, 280
A41: =A40+1 -> 32 | B41: Лещенко В.А. | C41: ИП Стрельцов В.А. | D41: Счет № 23 от 07.11.2025 | E41: .600050 | F41: Устройство приточно-вытяжной вентиляции согласно Приложения №1/13 от 11.06.2025г. к Договору подряда №ФП-10660-53/01 от 08.10.2024 г. | G41: Бюджет | H41: Да | I41: ГП 291. Вентиляция
A42: =A41+1 -> 33 | B42: Малый П.А. | C42: ИП Алты-Садых С.Ю | D42: Счёт№18/2 от 15.12.2025 | E42: .109250 | F42: Окончательный платеж за работы, изготовление,монтаж,шлифовку пропитку и окраску деревянных элементов террасы | G42: Бюджет | H42: да | I42: ГП-148 Дог№-ФП-10660-31 ОТ 14.11.2022
A43: =A42+1 -> 34 | B43: Салпагаров Р.А. | C43: ИП Чеботарев А.В. | D43: Счет № 1369 от 11.09.2025 | E43: .107000 | F43: Разработка дизайн проекта. Пр.№ 1/2 к дог.№ФП-10660-101 от 21.08.2025 | G43: Бюджет | H43: Да | I43: ГП 146
A44: =A43+1 -> 35 | B44: Малый П.А. | C44: ИП Глазунов Е.А. | D44: Счёт№15 от 22.01.2026 | E44: .18400 | F44: Уборка помещений | H44: Да
A45: =A44+1 -> 36 | B45: Лещенко В.А. | C45: сз Шкрябина | D45: Счет №24365802 от 04.12.2025г. | E45: .=414800-114800-130000 | F45: Монтаж фасонных изделий | G45: Бюджет | H45: Да | I45: ГП 291-292
A46: =A45+1 -> 37 | B46: Малый П.А. | C46: ИП Чеботарёв | D46: Счёт№281 от 24.02.2026 | E46: .30000 | F46: Авторский надзор | I46: ГП 291 Дог об авторском надзоре№2 от 24.02.2026
A47: =A46+1 -> 38 | B47: Малый П.А. | C47: ИП Доброхотова Н.А. | D47: Счёт№1 от 15.01.2026 | E47: .20000 | F47: ЛДУ | I47: Вн. рынок Ореховая роща Дог№ФП-10660 ОТ 21.02.2024
A48: 39 | B48: Малый П.А. | C48: ООО"Ростехплан" | D48: Счёт№06/03 от06.03.2026 | E48: .12000 | F48: Техплан | I48: ГП-326 Дог№04707 от 11.02.2026
A49: 40
A50: 41
A51: 42
A52: 43
A53: 44
A54: 45
A55: 46
A56: 47
A57: 48
A58: 49
A59: 50
B60: АХР (Продажи / IT служба / Юр служба / ФЭО /Секретариат)
A61: 1 | B61: Дмитриева О. В. | C61: ИФНС по ЕНП | D61: КБК 182 01 06 12 01 01 0000 510 | E61: .42000 | F61: НДФЛ (период с 23.02-28.02.2026) | I61: срок оплаты до 05.03.26
A62: 3 | B62: Дмитриева О. В. | C62: ИФНС по ЕНП | D62: КБК 182 01 06 12 01 01 0000 510 | E62: .73000 | F62: НДФЛ (период с 01.02-22.02.2026) | I62: срок оплаты до 02.03.26
A63: 3 | B63: Антоненко | C63: ООО «КЕХ еКоммерц» | D63: Счет № 01-2033820861 от 05 марта 2026 г. | E63: 10000 | F63: Внесение аванса в личный кабинет 353814823 по счёту № 01-2033820861 от 05.03.2026 в сумме 10 000,00 руб., в т. ч. НДС 1 803,28 руб. | J63: оплачен
A64: 4 | B64: Антоненко | C64: ИП Медовник Андрей Сергеевич | D64: Счет на оплату № 125 от 16 февраля 2026 г. Поставщик | E64: 5000 | F64: Адаптация/модификация программ для ЭВМ и баз данных на платформе Prologue-UNI (Тариф: "Визитка", Проект: "abfabrika.ru", Период: "Март 2026 г.") | J64: оплачен
A65: 5
B66: Бухгалтерия (Налоги / ЗП / ЕСН / прочие платежи бух. службы)
A67: 1
A68: 2
A69: 3
A70: 4
A71: 5
A72: ИТОГО ФАБРИКА ПРОЕКТОВ РАСХОДЫ ПО РЕЕСТРУ | E72: =SUM(E9:E71) -> 15000
A73: ДЕФИЦИТ / ПРОФИЦИТ с Остатка на начало дня | E73: =E4-E72 -> 151889.41

Sheet 06
E1: _____________________________ Согласовано
C2: ='05'!C2+1 -> 46087 | F2: Реестр разбит по Юр. лицам!!! КРУТИТЕ ВНИЗ
A4: ФАБРИКА ПРОЕКТОВ | E4: =SUM(E5:E6) -> 351809.41 | F4: Реестр закрыт!!!
A5: Счет Альфа 1674 | E5: 350128.77
A6: счет СБЕР 6989 | E6: 1680.64
A8: № п/п | B8: Инициатор платежа | C8: Контрагент - Получатель | D8: Договор/Счет | E8: Сумма к оплате | F8: Назначение платежа | G8: Бюджет/Статья | H8: Наличие Договора | I8: Примечание | J8: Отметка об оплате | K8: Спец. Распоряжение / Приоритет
B9: Коммерческая деятельность (Закупка ТМЦ Снабжение / Логистика / Транзит)
A10: 1
A11: 2
A12: 3
A13: 4
A14: 5
A15: 6
A16: 7
A17: 8
A18: 9
A19: 10
A20: 11
A21: 12
... A59: 50
B60: АХР (Продажи / IT служба / Юр служба / ФЭО /Секретариат)
A61: 1
A62: 2
A63: 3
A64: 4
A65: 5
B66: Бухгалтерия (Налоги / ЗП / ЕСН / прочие платежи бух. службы)
A67: 1
A68: 2
A69: 3
A70: 4
A71: 5
A72: ИТОГО ФАБРИКА ПРОЕКТОВ РАСХОДЫ ПО РЕЕСТРУ | E72: =SUM(E9:E71) -> 0
A73: ДЕФИЦИТ / ПРОФИЦИТ с Остатка на начало дня | E73: =E4-E72 -> 351809.41

Sheet 07
E1: _____________________________ Согласовано
C2: ='06'!C2+1 -> 46088 | F2: Реестр разбит по Юр. лицам!!! КРУТИТЕ ВНИЗ
A4: ФАБРИКА ПРОЕКТОВ | E4: =SUM(E5:E6) -> 0
A5: Счет Альфа 1674
A6: счет СБЕР 6989
A8: № п/п | B8: Инициатор платежа | C8: Контрагент - Получатель | D8: Договор/Счет | E8: Сумма к оплате | F8: Назначение платежа | G8: Бюджет/Статья | H8: Наличие Договора | I8: Примечание | J8: Отметка об оплате | K8: Спец. Распоряжение / Приоритет
B9: Коммерческая деятельность (Закупка ТМЦ Снабжение / Логистика / Транзит)
A10: 1
A11: 2
A12: 3
A13: 4
A14: 5
A15: 6
A16: 7
A17: 8
A18: 9
A19: 10
A20: 11
A21: 12
... A59: 50
B60: АХР (Продажи / IT служба / Юр служба / ФЭО /Секретариат)
A61: 1
A62: 2
A63: 3
A64: 4
A65: 5
B66: Бухгалтерия (Налоги / ЗП / ЕСН / прочие платежи бух. службы)
A67: 1
A68: 2
A69: 3
A70: 4
A71: 5
A72: ИТОГО ФАБРИКА ПРОЕКТОВ РАСХОДЫ ПО РЕЕСТРУ | E72: =SUM(E9:E71) -> 0
A73: ДЕФИЦИТ / ПРОФИЦИТ с Остатка на начало дня | E73: =E4-E72 -> 0

Sheet 08
E1: _____________________________ Согласовано
C2: ='07'!C2+1 -> 46089 | F2: Реестр разбит по Юр. лицам!!! КРУТИТЕ ВНИЗ
A4: ФАБРИКА ПРОЕКТОВ | E4: =SUM(E5:E6) -> 0
A5: Счет Альфа 1674
A6: счет СБЕР 6989
A8: № п/п | B8: Инициатор платежа | C8: Контрагент - Получатель | D8: Договор/Счет | E8: Сумма к оплате | F8: Назначение платежа | G8: Бюджет/Статья | H8: Наличие Договора | I8: Примечание | J8: Отметка об оплате | K8: Спец. Распоряжение / Приоритет
B9: Коммерческая деятельность (Закупка ТМЦ Снабжение / Логистика / Транзит)
A10: 1
A11: 2
A12: 3
A13: 4
A14: 5
A15: 6
A16: 7
A17: 8
A18: 9
A19: 10
A20: 11
A21: 12
... A59: 50
B60: АХР (Продажи / IT служба / Юр служба / ФЭО /Секретариат)
A61: 1
A62: 2
A63: 3
A64: 4
A65: 5
B66: Бухгалтерия (Налоги / ЗП / ЕСН / прочие платежи бух. службы)
A67: 1
A68: 2
A69: 3
A70: 4
A71: 5
A72: ИТОГО ФАБРИКА ПРОЕКТОВ РАСХОДЫ ПО РЕЕСТРУ | E72: =SUM(E9:E71) -> 0
A73: ДЕФИЦИТ / ПРОФИЦИТ с Остатка на начало дня | E73: =E4-E72 -> 0

Sheet 09
E1: _____________________________ Согласовано
C2: ='08'!C2+1 -> 46090 | F2: Реестр разбит по Юр. лицам!!! КРУТИТЕ ВНИЗ
A4: ФАБРИКА ПРОЕКТОВ | E4: =SUM(E5:E6) -> 0
A5: Счет Альфа 1674
A6: счет СБЕР 6989
A8: № п/п | B8: Инициатор платежа | C8: Контрагент - Получатель | D8: Договор/Счет | E8: Сумма к оплате | F8: Назначение платежа | G8: Бюджет/Статья | H8: Наличие Договора | I8: Примечание | J8: Отметка об оплате | K8: Спец. Распоряжение / Приоритет
B9: Коммерческая деятельность (Закупка ТМЦ Снабжение / Логистика / Транзит)
A10: 1
A11: 2
A12: 3
A13: 4
A14: 5
A15: 6
A16: 7
A17: 8
A18: 9
A19: 10
A20: 11
A21: 12
... A59: 50
B60: АХР (Продажи / IT служба / Юр служба / ФЭО /Секретариат)
A61: 1
A62: 2
A63: 3
A64: 4
A65: 5
B66: Бухгалтерия (Налоги / ЗП / ЕСН / прочие платежи бух. службы)
A67: 1
A68: 2
A69: 3
A70: 4
A71: 5
A72: ИТОГО ФАБРИКА ПРОЕКТОВ РАСХОДЫ ПО РЕЕСТРУ | E72: =SUM(E9:E71) -> 0
A73: ДЕФИЦИТ / ПРОФИЦИТ с Остатка на начало дня | E73: =E4-E72 -> 0

Sheet 10
E1: _____________________________ Согласовано
C2: ='09'!C2+1 -> 46091 | F2: Реестр разбит по Юр. лицам!!! КРУТИТЕ ВНИЗ
A4: ФАБРИКА ПРОЕКТОВ | E4: =SUM(E5:E6) -> 350128.77 | F4: Реестр закрыт!!!
A5: Счет Альфа 1674 | E5: 350128.77 | F5: 7 000 с ЯП
A6: счет СБЕР 6989 | E6: .1680,64
A8: № п/п | B8: Инициатор платежа | C8: Контрагент - Получатель | D8: Договор/Счет | E8: Сумма к оплате | F8: Назначение платежа | G8: Бюджет/Статья | H8: Наличие Договора | I8: Примечание | J8: Отметка об оплате | K8: Спец. Распоряжение / Приоритет
B9: Коммерческая деятельность (Закупка ТМЦ Снабжение / Логистика / Транзит)
A10: 1
A11: 2
A12: 3
A13: 4
A14: 5
A15: 6
A16: 7
A17: 8
A18: 9
A19: 10
A20: 11
A21: 12
... A59: 50
B60: АХР (Продажи / IT служба / Юр служба / ФЭО /Секретариат)
A61: 1 | B61: Амитон Д.Д. | C61: ПАО Вымпелком | D61: счёт 101189501178 от 28.02.26 | E61: .6019,15 | F61: оплата услуг связи
A62: 2
A63: 3
A64: 4
A65: 5
B66: Бухгалтерия (Налоги / ЗП / ЕСН / прочие платежи бух. службы)
A67: 1 | B67: Дмитриева О. В. | C67: Альфа-Банк | D67: реестр | E67: 354888.1 | F67: зарплата за февраль 2026 г. | J67: на обработке
A68: 2 | B68: Дмитриева О. В. | C68: ИФНС по ЕНП | D68: КБК 18201061201010000510 | E68: .225000 | F68: Страховые взносы за февраль 2026 г (налоги с фот)
A69: 3 | B69: Дмитриева О. В. | C69: ИФНС по ЕНП | D69: КБК 182 01 06 12 01 01 0000 510 | E69: .42000 | F69: НДФЛ (период с 23.02-28.02.2026) | I69: срок оплаты до 05.03.26
A70: 4 | B70: Дмитриева О. В. | C70: ИФНС по ЕНП | D70: КБК 182 01 06 12 01 01 0000 510 | E70: .73000 | F70: НДФЛ (период с 01.02-22.02.2026) | I70: срок оплаты до 02.03.26
A71: ИТОГО ФАБРИКА ПРОЕКТОВ РАСХОДЫ ПО РЕЕСТРУ | E71: =SUM(E9:E70) -> 354888.1
A72: ДЕФИЦИТ / ПРОФИЦИТ с Остатка на начало дня | E72: =E4-E71 -> -4759.33

Sheet 11
E1: _____________________________ Согласовано
C2: ='10'!C2+1 -> 46092 | F2: Реестр разбит по Юр. лицам!!! КРУТИТЕ ВНИЗ
A4: ФАБРИКА ПРОЕКТОВ | E4: =SUM(E5:E6) -> 3921.31 | F4: Реестр закрыт!!!
A5: Счет Альфа 1674 | E5: 2240.67
A6: счет СБЕР 6989 | E6: 1680.64
A8: № п/п | B8: Инициатор платежа | C8: Контрагент - Получатель | D8: Договор/Счет | E8: Сумма к оплате | F8: Назначение платежа | G8: Бюджет/Статья | H8: Наличие Договора | I8: Примечание | J8: Отметка об оплате | K8: Спец. Распоряжение / Приоритет
B9: Коммерческая деятельность (Закупка ТМЦ Снабжение / Логистика / Транзит)
A10: 1
A11: 2
A12: 3
A13: 4
A14: 5
A15: 6
A16: 7
A17: 8
A18: 9
A19: 10
A20: 11
A21: 12
... A59: 50
B60: АХР (Продажи / IT служба / Юр служба / ФЭО /Секретариат)
A61: 1
A62: 2
A63: 3
A64: 4
A65: 5
B66: Бухгалтерия (Налоги / ЗП / ЕСН / прочие платежи бух. службы)
A67: 1
A68: 2
A69: 3
A70: 4
A71: 5
A72: ИТОГО ФАБРИКА ПРОЕКТОВ РАСХОДЫ ПО РЕЕСТРУ | E72: =SUM(E9:E71) -> 0
A73: ДЕФИЦИТ / ПРОФИЦИТ с Остатка на начало дня | E73: =E4-E72 -> 3921.31

Sheet 12
E1: _____________________________ Согласовано
C2: ='11'!C2+1 -> 46093 | F2: Реестр разбит по Юр. лицам!!! КРУТИТЕ ВНИЗ
A4: ФАБРИКА ПРОЕКТОВ | E4: =SUM(E5:E6) -> 3921.31 | F4: Реестр закрыт!!!
A5: Счет Альфа 1674 | E5: 2240.67
A6: счет СБЕР 6989 | E6: 1680.64
A8: № п/п | B8: Инициатор платежа | C8: Контрагент - Получатель | D8: Договор/Счет | E8: Сумма к оплате | F8: Назначение платежа | G8: Бюджет/Статья | H8: Наличие Договора | I8: Примечание | J8: Отметка об оплате | K8: Спец. Распоряжение / Приоритет
B9: Коммерческая деятельность (Закупка ТМЦ Снабжение / Логистика / Транзит)
A10: 1 | B10: Малый П.А. | C10: ИП Храмова Э.Э. | D10: Счёт№389 от 10.03.2026 | E10: .12600 | F10: Услуги по благоустройству територии | H10: Да | I10: Дог №ФП-10660 от 15.03.2023
A11: 2 | B11: Малый П.А. | C11: ИП Кривошлыкова | D11: Счёт№42 от 11.03.2026 | E11: .27200 | F11: Транспортные услуги | H11: Да | I11: ГП 385 Фундамент
A12: 3
A13: 4
A14: 5
A15: 6
A16: 7
A17: 8
A18: 9
A19: 10
A20: 11
A21: 12
A22: 13
A23: 14
... A59: 50
B60: АХР (Продажи / IT служба / Юр служба / ФЭО /Секретариат)
A61: 1 | B61: Амитон Д.Д. | C61: ООО Яндекс 360 для бизнеса | D61: счёт ЛС-5001476685-1 от 11 марта 2026 г. | E61: .3326 | F61: оплата доступа к сервису электронной почты | H61: Да
A62: 2
A63: 3
A64: 4
A65: 5
B66: Бухгалтерия (Налоги / ЗП / ЕСН / прочие платежи бух. службы)
A67: 1
A68: 2
A69: 3
A70: 4
A71: 5
A72: ИТОГО ФАБРИКА ПРОЕКТОВ РАСХОДЫ ПО РЕЕСТРУ | E72: =SUM(E9:E71) -> 0
A73: ДЕФИЦИТ / ПРОФИЦИТ с Остатка на начало дня | E73: =E4-E72 -> 3921.31

Sheet 13
E1: _____________________________ Согласовано
C2: ='12'!C2+1 -> 46094 | F2: Реестр разбит по Юр. лицам!!! КРУТИТЕ ВНИЗ
A4: ФАБРИКА ПРОЕКТОВ | E4: =SUM(E5:E6) -> 3921.31 | F4: Реестр закрыт!!!
A5: Счет Альфа 1674 | E5: 2240.67
A6: счет СБЕР 6989 | E6: 1680.64
A8: № п/п | B8: Инициатор платежа | C8: Контрагент - Получатель | D8: Договор/Счет | E8: Сумма к оплате | F8: Назначение платежа | G8: Бюджет/Статья | H8: Наличие Договора | I8: Примечание | J8: Отметка об оплате | K8: Спец. Распоряжение / Приоритет
B9: Коммерческая деятельность (Закупка ТМЦ Снабжение / Логистика / Транзит)
A10: 1
A11: 2
A12: 3
A13: 4
A14: 5
A15: 6
A16: 7
A17: 8
A18: 9
A19: 10
A20: 11
A21: 12
... A59: 50
B60: АХР (Продажи / IT служба / Юр служба / ФЭО /Секретариат)
A61: 1
A62: 2
A63: 3
A64: 4
A65: 5
B66: Бухгалтерия (Налоги / ЗП / ЕСН / прочие платежи бух. службы)
A67: 1
A68: 2
A69: 3
A70: 4
A71: 5
A72: ИТОГО ФАБРИКА ПРОЕКТОВ РАСХОДЫ ПО РЕЕСТРУ | E72: =SUM(E9:E71) -> 0
A73: ДЕФИЦИТ / ПРОФИЦИТ с Остатка на начало дня | E73: =E4-E72 -> 3921.31

Sheet 14
E1: _____________________________ Согласовано
C2: ='13'!C2+1 -> 46095 | F2: Реестр разбит по Юр. лицам!!! КРУТИТЕ ВНИЗ
A4: ФАБРИКА ПРОЕКТОВ | E4: =SUM(E5:E6) -> 0
A5: Счет Альфа 1674
A6: счет СБЕР 6989
A8: № п/п | B8: Инициатор платежа | C8: Контрагент - Получатель | D8: Договор/Счет | E8: Сумма к оплате | F8: Назначение платежа | G8: Бюджет/Статья | H8: Наличие Договора | I8: Примечание | J8: Отметка об оплате | K8: Спец. Распоряжение / Приоритет
B9: Коммерческая деятельность (Закупка ТМЦ Снабжение / Логистика / Транзит)
A10: 1
A11: 2
A12: 3
A13: 4
A14: 5
A15: 6
A16: 7
A17: 8
A18: 9
A19: 10
A20: 11
A21: 12
... A59: 50
B60: АХР (Продажи / IT служба / Юр служба / ФЭО /Секретариат)
A61: 1
A62: 2
A63: 3
A64: 4
A65: 5
B66: Бухгалтерия (Налоги / ЗП / ЕСН / прочие платежи бух. службы)
A67: 1
A68: 2
A69: 3
A70: 4
A71: 5
A72: ИТОГО ФАБРИКА ПРОЕКТОВ РАСХОДЫ ПО РЕЕСТРУ | E72: =SUM(E9:E71) -> 0
A73: ДЕФИЦИТ / ПРОФИЦИТ с Остатка на начало дня | E73: =E4-E72 -> 0

Sheet 15
E1: _____________________________ Согласовано
C2: ='14'!C2+1 -> 46096 | F2: Реестр разбит по Юр. лицам!!! КРУТИТЕ ВНИЗ
A4: ФАБРИКА ПРОЕКТОВ | E4: =SUM(E5:E6) -> 0
A5: Счет Альфа 1674
A6: счет СБЕР 6989
A8: № п/п | B8: Инициатор платежа | C8: Контрагент - Получатель | D8: Договор/Счет | E8: Сумма к оплате | F8: Назначение платежа | G8: Бюджет/Статья | H8: Наличие Договора | I8: Примечание | J8: Отметка об оплате | K8: Спец. Распоряжение / Приоритет
B9: Коммерческая деятельность (Закупка ТМЦ Снабжение / Логистика / Транзит)
A10: 1
A11: 2
A12: 3
A13: 4
A14: 5
A15: 6
A16: 7
A17: 8
A18: 9
A19: 10
A20: 11
A21: 12
... A59: 50
B60: АХР (Продажи / IT служба / Юр служба / ФЭО /Секретариат)
A61: 1
A62: 2
A63: 3
A64: 4
A65: 5
B66: Бухгалтерия (Налоги / ЗП / ЕСН / прочие платежи бух. службы)
A67: 1
A68: 2
A69: 3
A70: 4
A71: 5
A72: ИТОГО ФАБРИКА ПРОЕКТОВ РАСХОДЫ ПО РЕЕСТРУ | E72: =SUM(E9:E71) -> 0
A73: ДЕФИЦИТ / ПРОФИЦИТ с Остатка на начало дня | E73: =E4-E72 -> 0

Sheet 16
E1: _____________________________ Согласовано
C2: ='15'!C2+1 -> 46097 | F2: Реестр разбит по Юр. лицам!!! КРУТИТЕ ВНИЗ
A4: ФАБРИКА ПРОЕКТОВ | E4: =SUM(E5:E6) -> 161921.31 | F4: Реестр закрыт!!!
A5: Счет Альфа 1674 | E5: 160240.67
A6: счет СБЕР 6989 | E6: 1680.64
A8: № п/п | B8: Инициатор платежа | C8: Контрагент - Получатель | D8: Договор/Счет | E8: Сумма к оплате | F8: Назначение платежа | G8: Бюджет/Статья | H8: Наличие Договора | I8: Примечание | J8: Отметка об оплате | K8: Спец. Распоряжение / Приоритет
B9: Коммерческая деятельность (Закупка ТМЦ Снабжение / Логистика / Транзит)
A10: 1
A11: 2
A12: 3
A13: 4
A14: 5
A15: 6
A16: 7
A17: 8
A18: 9
A19: 10
A20: 11
A21: 12
... A59: 50
B60: АХР (Продажи / IT служба / Юр служба / ФЭО /Секретариат)
A61: 1
A62: 2
A63: 3
A64: 4
A65: 5
B66: Бухгалтерия (Налоги / ЗП / ЕСН / прочие платежи бух. службы)
A67: 1
A68: 2
A69: 3
A70: 4
A71: 5
A72: ИТОГО ФАБРИКА ПРОЕКТОВ РАСХОДЫ ПО РЕЕСТРУ | E72: =SUM(E9:E71) -> 0
A73: ДЕФИЦИТ / ПРОФИЦИТ с Остатка на начало дня | E73: =E4-E72 -> 161921.31

Sheet 17
E1: _____________________________ Согласовано
C2: ='16'!C2+1 -> 46098 | F2: Реестр разбит по Юр. лицам!!! КРУТИТЕ ВНИЗ
A4: ФАБРИКА ПРОЕКТОВ | E4: =SUM(E5:E6) -> 161921.31 | F4: Реестр закрыт!!!
A5: Счет Альфа 1674 | E5: 160240.67
A6: счет СБЕР 6989 | E6: 1680.64
A8: № п/п | B8: Инициатор платежа | C8: Контрагент - Получатель | D8: Договор/Счет | E8: Сумма к оплате | F8: Назначение платежа | G8: Бюджет/Статья | H8: Наличие Договора | I8: Примечание | J8: Отметка об оплате | K8: Спец. Распоряжение / Приоритет
B9: Коммерческая деятельность (Закупка ТМЦ Снабжение / Логистика / Транзит)
A10: 1 | B10: Лещенко В.А. | C10: ООО ГЕРМЕС | D10: Счет № 493 от 24.10.2025 | E10: .218750 | F10: Закупка бетона | G10: Бюджет | H10: Да | I10: ГП 294 Забор. ИП Малый. Договор №ФП31072025 от 31.07.2025 Приложение №2
A11: =A10+1 -> 2 | B11: Лещенко В.А. | C11: ООО "Айрон" | D11: Счет №АИПП-2504 от 21.03.2025 | E11: .=16534 | F11: Закупка металла. | G11: Бюджет | H11: Да | I11: (Щепкино. СПА.стены)ИП Малый Договор подряда №ФП-03022025 от 03.02.2025 Пр. №2 от 03.02.2025 ИП Малый
A12: =A11+1 -> 3 | B12: Лещенко В.А. | C12: ООО "Айрон" | D12: Счет № АИПП-3664 от 25.04.2025 | E12: .126845 | F12: Закупка металла на объект | G12: Бюджет | H12: Да | I12: ГП 204 (Навес) Договор подряда №ФП-27032025 от 27.03.2025 Приложение № 2 от 27.03.2025
A13: =A12+1 -> 4 | B13: Лещенко В.А. | C13: ООО "Айрон" | D13: Счет № АИПП-3754 от 29.04.2025 | E13: .27325 | F13: Закупка металла. | G13: Бюджет | H13: Да | I13: ГП 204(навес) Договор подряда №ФП-27032025 от 27.03.2025 Приложение №2 от 27.03.2025
A14: =A13+1 -> 5 | B14: Лещенко В.А. | C14: ООО "Айрон" | D14: Счет № АИПП-5404 от 30.06.2025 | E14: .150100 | F14: Закупка металла на объект | G14: Бюджет | H14: Да | I14: ГП 294. ХБП ИП Малый Договор подряда №ФП-19062025 от 19.06.2025 Приложение №2 от 19.06.2025
A15: =A14+1 -> 6 | B15: Лещенко В.А. | C15: ООО "Айрон" | D15: Счет № АИПП-5407 от 30.06.2025 | E15: .17300 | F15: Закупка металла на объект | G15: Бюджет | H15: Да | I15: ГП 204. ИП Малый. Договор подряда №ФП-27032025 от 27.03.2025 Приложение №2 от 27.03.2025
A16: =A15+1 -> 7 | B16: Лещенко В.А. | C16: ООО "Айрон" | D16: Счет № АИПП-5408 от 30.06.2025 | E16: .35505 | F16: Закупка металла на объект | G16: Бюджет | H16: Да | I16: ГП 13. (ХБП) ИП Малый. Договор подряда №ФП-10660-72/01 от 12.02.2024 г. Приложение №1/8 от 14.03.2025
A17: =A16+1 -> 8 | B17: Лещенко В.А. | C17: ООО "Айрон" | D17: Счет № АИПП-6301 от 04.08.2025 | E17: .163370 | F17: Закупка металла на объект | G17: Бюджет | H17: Да | I17: ГП 326. Забор ИП Малый
A18: =A17+1 -> 9 | B18: Лещенко В.А. | C18: ООО "Айрон" | D18: Счет № АИПП-6303 от 04.08.2025 | E18: .115500 | F18: Закупка металла на объект | G18: Бюджет | H18: Да | I18: ГП 294. Бассеин ИП Малый
A19: =A18+1 -> 10 | B19: Лещенко В.А. | C19: ООО "Айрон" | D19: Счет № АИПП-6304 от 04.08.2025 | E19: .51000 | F19: Закупка металла на объект | G19: Бюджет | H19: Да | I19: ГП 294. Забор ИП Малый
A20: =A19+1 -> 11 | B20: Лещенко В.А. | C20: ИП Полежаев А.А. | D20: Счет № 42 от 26.09.2025 | E20: .363298 | F20: Устройство фасада с молдингами на ХБП по дог.№ФП-10660-29 от 16.09.2022, пр.№ 1/19 | G20: Бюджет | H20: Да | I20: Окончательный ГП 326
A21: =A20+1 -> 12 | B21: Лещенко В.А. | C21: ИП Полежаев А.А. | D21: Счет № 44 от 30.09.2025 | E21: .313500 | F21: Устройство фасада с молдингами на ХБП. Договор подряда №ФП-10660-29 от 16.09.2022 Приложение № 1/25 | G21: Бюджет | H21: Да | I21: Аванс ГП 294,295
A22: =A21+1 -> 13 | B22: Малый П.А. | C22: ИП Полежаев А.А. | D22: Счёт №50 от 26.11.2025 | E22: .538264 | F22: Устройство фасада с молдингами | G22: Бюджет | H22: Да | I22: Окончательный ГП-243
A23: =A22+1 -> 14 | B23: Малый П.А. | C23: ИП Полежаев А.А. | D23: Счёт№51 от 02.12.2025 | E23: .54956 | F23: Устройство калон террасы | G23: Бюджет | I23: Окончательный. ГП-294.295 Договор подряда№ФП-10660-29 ОТ 16.09.2022
A24: =A23+1 -> 15 | B24: Малый П.А. | C24: ИП Полежаев А.А. | D24: Счёт№53 от 20.01.2025 | E24: .842553 | F24: Фасад | I24: ГП-148 Дог№-ФП-25112024-01от 25.11.2024 ПР№2 от 25.11.2024
A25: =A24+1 -> 16 | B25: Лещенко В.А. | C25: ИП Любомирский В.Г. | D25: Счет № 20 от 28.07.2025 | E25: .558077 | F25: Электромонтажные работы | G25: Бюджет | H25: Да | I25: Вн. рынок. Щепкин СПА
A26: =A25+1 -> 17 | B26: Лещенко В.А. | C26: ИП Любомирский В.Г. | D26: Счет № 25 от 23.09.2025 | E26: .210906 | F26: Оплата работ по пр.1/12 от 22.09.25 к дог.№ФП-10660-10/01 от 19.03.2024г | G26: Бюджет | H26: Да | I26: ГП 13. Электрика. 4й этап
A27: =A26+1 -> 18 | B27: Малый П.А. | C27: ИП Кравченко К.Н. | D27: Счёт№542 от 24.10.2025 | E27: .32621,5 | F27: Пиломатериалы | G27: Бюджет | H27: Да | I27: Вн.Рынок. Щепкино, кровля
A28: =A27+1 -> 19 | B28: Малый П.А. | C28: ИП Кравченко К.Н. | D28: Счёт №548 от 28.10.2025 | E28: .38400 | F28: Пиломатериалы | G28: Бюджет | H28: Да | I28: Вн.Рынок. Щепкино,кровля
A29: =A28+1 -> 20 | B29: Малый П.А. | C29: ИП Кравченко К.Н. | D29: Счёт №566 от 19.11.2025 | E29: .38400 | F29: Пиломатериалы | G29: Бюджет | H29: Да | I29: Навес ГП 262
A30: =A29+1 -> 21 | B30: Малый П.А. | C30: ИП Кравченко К.Н. | D30: Счёт № 609 от 22.12.2025 | E30: .128725,35 | F30: Пиломатериалы | G30: Бюджет | I30: Навес ГП 262
A31: =A30+1 -> 22 | B31: Синицына В.В. | C31: ИП Храмова Э.Э. | D31: Счет №2042 от 17.11.2025 | E31: .42000 | F31: Услуги по благоустройству территории с 10.11.2025 по 13.11.2025 | G31: Бюджет | H31: Да
A32: =A31+1 -> 23 | B32: Малый П.А. | C32: ИП Храмова Э.Э | D32: Счёт№2177от 08.12.2025 | E32: .16800 | F32: Благоустройство территории | G32: Бюджет | I32: ГП-103 Дог№ФП-10660-36 Планирование грунта
A33: =A32+1 -> 24 | B33: Малый П.А. | C33: ИП Храмова Э.Э. | D33: Счёт№2233 от 15.12.2025 | E33: .8400 | F33: Благоустройство территории | G33: Бюджет | I33: ГП-218,231,213,214,216,221,188 Дог№10660-36 от 15.032023 чистка преддомовых территорий
A34: =A33+1 -> 25 | B34: Синицына В.В. | C34: ИП Храмова Э.Э. | D34: Счет №2252 от 22.12.2025 | E34: .42000 | F34: Услуги по благоустройству территории | G34: Бюджет
A35: =A34+1 -> 26 | B35: Синицына В.В. | C35: ИП Храмова Э.Э. | D35: Счет №2301 от 25.12.2025г. | E35: .25200 | F35: Услуги по благоустройству территории | G35: Бюджет
A36: =A35+1 -> 27 | B36: Лещенко В.А. | C36: ИП Сердечная О.Ю. | D36: Счет № 291 от 17.09.2025 | E36: .59500 | F36: Договор №3 от 30.03.2022 г. Транспортные услуги по перевозке опалубки, 05.09.2025 г.,16.09.2025 г. | G36: Бюджет | H36: Да | I36: ГП 294. Бассейн.ИП Малый
A37: =A36+1 -> 28 | B37: Лещенко В.А. | C37: ИП Козлова Н.В. | D37: Счет № 27 от 19.11.2024 | E37: .=30500 | F37: Ус-во фасада по дог.№ФП-10660-93 от 01.10.2024 от 19.11.2024 | G37: Бюджет | H37: Да | I37: Окончательный.ГП-211
A38: =A37+1 -> 29 | B38: Лещенко В.А. | C38: ООО "АЛЮМИНИУМ" | D38: Счет № 385 от 03.09.2025 | E38: .386200 | F38: Оплата за алюмииевые конструкции по дог.№ФП-28052024 от 28.05.2025 | G38: Бюджет | H38: Да | I38: ГП 291. Витражи.
A39: =A38+1 -> 30 | B39: Синицына В.В. | C39: ИП Никулов А.В. | D39: Счет №113 от 21.11.2025 | E39: .=146016/2 | F39: Аванс по Приложению 1/14 к Договору №ФП-10660-98 от 04.04.2025 | G39: Бюджет | I39: Монтаж системы полива на придомовой ГП 273, 280
A40: =A39+1 -> 31 | B40: Лещенко В.А. | C40: ИП Стрельцов В.А. | D40: Счет № 23 от 07.11.2025 | E40: .600050 | F40: Устройство приточно-вытяжной вентиляции согласно Приложения №1/13 от 11.06.2025г. к Договору подряда №ФП-10660-53/01 от 08.10.2024 г. | G40: Бюджет | H40: Да | I40: ГП 291. Вентиляция
A41: =A40+1 -> 32 | B41: Малый П.А. | C41: ИП Алты-Садых С.Ю | D41: Счёт№18/2 от 15.12.2025 | E41: .109250 | F41: Окончательный платеж за работы, изготовление,монтаж,шлифовку пропитку и окраску деревянных элементов террасы | G41: Бюджет | H41: да | I41: ГП-148 Дог№-ФП-10660-31 ОТ 14.11.2022
A42: =A41+1 -> 33 | B42: Малый П.А. | C42: ИП Чеботарев А.В. | D42: Счет № 1369 от 11.09.2025 | E42: .107000 | F42: Разработка дизайн проекта. Пр.№ 1/2 к дог.№ФП-10660-101 от 21.08.2025 | G42: Бюджет | H42: Да | I42: ГП 146
A43: =A42+1 -> 34 | B43: Малый П.А. | C43: ИП Глазунов Е.А. | D43: Счёт№15 от 22.01.2026 | E43: .18400 | F43: Уборка помещений | H43: Да
A44: =A43+1 -> 35 | B44: Лещенко В.А. | C44: сз Шкрябина | D44: Счет №24365802 от 04.12.2025г. | E44: .=414800-114800-130000 | F44: Монтаж фасонных изделий | G44: Бюджет | H44: Да | I44: ГП 291-292
A45: =A44+1 -> 36 | B45: Малый П.А. | C45: ИП Чеботарёв | D45: Счёт№281 от 24.02.2026 | E45: .30000 | F45: Авторский надзор | I45: ГП 291 Дог об авторском надзоре№2 от 24.02.2026
A46: =A45+1 -> 37 | B46: Малый П.А. | C46: ИП Доброхотова Н.А. | D46: Счёт№1 от 15.01.2026 | E46: .20000 | F46: ЛДУ | I46: Вн. рынок Ореховая роща Дог№ФП-10660 ОТ 21.02.2024
A47: =A46+1 -> 38 | B47: Малый П.А. | C47: ООО"Ростехплан" | D47: Счёт№06/03 от06.03.2026 | E47: .12000 | F47: Техплан | I47: ГП-326 Дог№04707 от 11.02.2026
A48: =A47+1 -> 39 | B48: Малый П.А. | C48: ИП Храмова Э.Э. | D48: Счёт№389 от 10.03.2026 | E48: .12600 | F48: Услуги по благоустройству територии | H48: Да | I48: Дог №ФП-10660 от 15.03.2023
A49: =A48+1 -> 40 | B49: Малый П.А. | C49: ООО "УСПЕХ" | D49: Счёт№11695от 12.03.2026 | E49: .11119 | F49: Хим препараты для обработки растений | I49: Дендро
A50: =A49+1 -> 41 | B50: Малый П.А. | C50: ИП Кривошлыкова Я.В. | D50: Счёт№45от13.03.2026 | E50: .12500 | F50: Оказание транспортных услуг | I50: ГП-385 ХБП Дог№ФП10022025 ПР№2 от 17.02.2025
A51: =A50+1 -> 42 | B51: Малый П.А | C51: АО Евраз Маркет | D51: Счёт№ИНН00-050099 от13.03.2026 | E51: .60157,20 | F51: Металлопрокат | I51: ГП-385 ХБП Дог№ФП10022025 ПР№2 от 17.02.2025
A52: =A51+1 -> 43 | B52: Малый П.А. | C52: ИП Чередниченко | D52: Счёт № 17 от 05.12.2025. | E52: 112952 | F52: Монтаж натяжных потолков | G52: Бюджет | H52: да | I52: ГП-138 Дог-10660-84/01от01.10.2024 | J52: оплачен
A53: =A52+1 -> 44 | B53: Малый П.А. | C53: ИП Кривошлыкова | D53: Счёт№42 от 11.03.2026 | E53: 27200 | F53: Транспортные услуги | G53: Бюджет | H53: Да | I53: ГП-385 ХБП Дог№ФП10022025 ПР№2 от 17.02.2025 | J53: оплачен
A54: =A53+1 -> 45 | B54: Малый П.А. | C54: ИП Исаев О.Ю. | D54: Счёт№27223от 13.03.2026 | E54: 3850 | F54: Вода питьевая | G54: Бюджет | H54: Да | J54: оплачен
A55: =A54+1 -> 46
A56: =A55+1 -> 47
B57: АХР (Продажи / IT служба / Юр служба / ФЭО /Секретариат)
A58: 1 | B58: Амитон Д.Д. | C58: ООО Яндекс 360 для бизнеса | D58: счёт ЛС-5001476685-1 от 11 марта 2026 г. | E58: 3326 | F58: оплата доступа к сервису электронной почты | G58: Бюджет | H58: Да | J58: оплачен
A59: 2 | B59: Амитон Д.Д. | C59: ПАО Вымпелком | D59: счёт 101189501178 от 28.02.26 | E59: 6019.15 | F59: оплата услуг связи | G59: Бюджет | H59: Да | J59: оплачен
A60: 3
A61: 4
A62: 5
B63: Бухгалтерия (Налоги / ЗП / ЕСН / прочие платежи бух. службы)
A64: 2 | B64: Дмитриева О. В. | C64: ИФНС по ЕНП | D64: КБК 18201061201010000510 | E64: .225000 | F64: Страховые взносы за февраль 2026 г (налоги с фот)
A65: 3 | B65: Дмитриева О. В. | C65: ИФНС по ЕНП | D65: КБК 182 01 06 12 01 01 0000 510 | E65: .42000 | F65: НДФЛ (период с 23.02-28.02.2026) | I65: срок оплаты до 05.03.26
A66: 4 | B66: Дмитриева О. В. | C66: ИФНС по ЕНП | D66: КБК 182 01 06 12 01 01 0000 510 | E66: .73000 | F66: НДФЛ (период с 01.02-22.02.2026) | I66: срок оплаты до 02.03.26
A67: 4 | B67: Попова Е.П. | C67: Кожанов Александр Николаевич | D67: Заяв.на возмещ.ДС от 12.03.2026 | E67: 5119.5 | F67: Заяв.на возмещ.ДС от 12.03.2026 | H67: Да | J67: оплачен
A68: 5
A69: ИТОГО ФАБРИКА ПРОЕКТОВ РАСХОДЫ ПО РЕЕСТРУ | E69: =SUM(E9:E68) -> 158466.65
A70: ДЕФИЦИТ / ПРОФИЦИТ с Остатка на начало дня | E70: =E4-E69 -> 3454.66

Sheet 18
E1: _____________________________ Согласовано
C2: ='17'!C2+1 -> 46099 | F2: Реестр разбит по Юр. лицам!!! КРУТИТЕ ВНИЗ
A4: ФАБРИКА ПРОЕКТОВ | E4: =SUM(E5:E6) -> 43534.66 | F4: Реестр закрыт!!!
A5: Счет Альфа 1674 | E5: 41854.02
A6: счет СБЕР 6989 | E6: 1680.64
A8: № п/п | B8: Инициатор платежа | C8: Контрагент - Получатель | D8: Договор/Счет | E8: Сумма к оплате | F8: Назначение платежа | G8: Бюджет/Статья | H8: Наличие Договора | I8: Примечание | J8: Отметка об оплате | K8: Спец. Распоряжение / Приоритет
B9: Коммерческая деятельность (Закупка ТМЦ Снабжение / Логистика / Транзит)
A10: 1
A11: 2
A12: 3
A13: 4
A14: 5
A15: 6
A16: 7
A17: 8
A18: 9
A19: 10
A20: 11
A21: 12
... A59: 50
B60: АХР (Продажи / IT служба / Юр служба / ФЭО /Секретариат)
A61: 1
A62: 2
A63: 3
A64: 4
A65: 5
B66: Бухгалтерия (Налоги / ЗП / ЕСН / прочие платежи бух. службы)
A67: 1
A68: 2
A69: 3
A70: 4
A71: 5
A72: ИТОГО ФАБРИКА ПРОЕКТОВ РАСХОДЫ ПО РЕЕСТРУ | E72: =SUM(E9:E71) -> 0
A73: ДЕФИЦИТ / ПРОФИЦИТ с Остатка на начало дня | E73: =E4-E72 -> 43534.66

Sheet 19
E1: _____________________________ Согласовано
C2: ='18'!C2+1 -> 46100 | F2: Реестр разбит по Юр. лицам!!! КРУТИТЕ ВНИЗ
A4: ФАБРИКА ПРОЕКТОВ | E4: =SUM(E5:E6) -> 43534.66 | F4: Реестр закрыт!!!
A5: Счет Альфа 1674 | E5: 41854.02
A6: счет СБЕР 6989 | E6: 1680.64
A8: № п/п | B8: Инициатор платежа | C8: Контрагент - Получатель | D8: Договор/Счет | E8: Сумма к оплате | F8: Назначение платежа | G8: Бюджет/Статья | H8: Наличие Договора | I8: Примечание | J8: Отметка об оплате | K8: Спец. Распоряжение / Приоритет
B9: Коммерческая деятельность (Закупка ТМЦ Снабжение / Логистика / Транзит)
A10: 1 | B10: Лещенко В.А. | C10: ООО ГЕРМЕС | D10: Счет № 493 от 24.10.2025 | E10: .218750 | F10: Закупка бетона | G10: Бюджет | H10: Да | I10: ГП 294 Забор. ИП Малый. Договор №ФП31072025 от 31.07.2025 Приложение №2
A11: =A10+1 -> 2 | B11: Лещенко В.А. | C11: ООО "Айрон" | D11: Счет №АИПП-2504 от 21.03.2025 | E11: .=16534 | F11: Закупка металла. | G11: Бюджет | H11: Да | I11: (Щепкино. СПА.стены)ИП Малый Договор подряда №ФП-03022025 от 03.02.2025 Пр. №2 от 03.02.2025 ИП Малый
A12: =A11+1 -> 3 | B12: Лещенко В.А. | C12: ООО "Айрон" | D12: Счет № АИПП-3664 от 25.04.2025 | E12: .126845 | F12: Закупка металла на объект | G12: Бюджет | H12: Да | I12: ГП 204 (Навес) Договор подряда №ФП-27032025 от 27.03.2025 Приложение № 2 от 27.03.2025
A13: =A12+1 -> 4 | B13: Лещенко В.А. | C13: ООО "Айрон" | D13: Счет № АИПП-3754 от 29.04.2025 | E13: .27325 | F13: Закупка металла. | G13: Бюджет | H13: Да | I13: ГП 204(навес) Договор подряда №ФП-27032025 от 27.03.2025 Приложение №2 от 27.03.2025
A14: =A13+1 -> 5 | B14: Лещенко В.А. | C14: ООО "Айрон" | D14: Счет № АИПП-5404 от 30.06.2025 | E14: .150100 | F14: Закупка металла на объект | G14: Бюджет | H14: Да | I14: ГП 294. ХБП ИП Малый Договор подряда №ФП-19062025 от 19.06.2025 Приложение №2 от 19.06.2025
A15: =A14+1 -> 6 | B15: Лещенко В.А. | C15: ООО "Айрон" | D15: Счет № АИПП-5407 от 30.06.2025 | E15: .17300 | F15: Закупка металла на объект | G15: Бюджет | H15: Да | I15: ГП 204. ИП Малый. Договор подряда №ФП-27032025 от 27.03.2025 Приложение №2 от 27.03.2025
A16: =A15+1 -> 7 | B16: Лещенко В.А. | C16: ООО "Айрон" | D16: Счет № АИПП-5408 от 30.06.2025 | E16: .35505 | F16: Закупка металла на объект | G16: Бюджет | H16: Да | I16: ГП 13. (ХБП) ИП Малый. Договор подряда №ФП-10660-72/01 от 12.02.2024 г. Приложение №1/8 от 14.03.2025
A17: =A16+1 -> 8 | B17: Лещенко В.А. | C17: ООО "Айрон" | D17: Счет № АИПП-6301 от 04.08.2025 | E17: .163370 | F17: Закупка металла на объект | G17: Бюджет | H17: Да | I17: ГП 326. Забор ИП Малый
A18: =A17+1 -> 9 | B18: Лещенко В.А. | C18: ООО "Айрон" | D18: Счет № АИПП-6303 от 04.08.2025 | E18: .115500 | F18: Закупка металла на объект | G18: Бюджет | H18: Да | I18: ГП 294. Бассеин ИП Малый
A19: =A18+1 -> 10 | B19: Лещенко В.А. | C19: ООО "Айрон" | D19: Счет № АИПП-6304 от 04.08.2025 | E19: .51000 | F19: Закупка металла на объект | G19: Бюджет | H19: Да | I19: ГП 294. Забор ИП Малый
A20: =A19+1 -> 11 | B20: Лещенко В.А. | C20: ИП Полежаев А.А. | D20: Счет № 42 от 26.09.2025 | E20: .363298 | F20: Устройство фасада с молдингами на ХБП по дог.№ФП-10660-29 от 16.09.2022, пр.№ 1/19 | G20: Бюджет | H20: Да | I20: Окончательный ГП 326
A21: =A20+1 -> 12 | B21: Лещенко В.А. | C21: ИП Полежаев А.А. | D21: Счет № 44 от 30.09.2025 | E21: .313500 | F21: Устройство фасада с молдингами на ХБП. Договор подряда №ФП-10660-29 от 16.09.2022 Приложение № 1/25 | G21: Бюджет | H21: Да | I21: Аванс ГП 294,295
A22: =A21+1 -> 13 | B22: Малый П.А. | C22: ИП Полежаев А.А. | D22: Счёт №50 от 26.11.2025 | E22: .538264 | F22: Устройство фасада с молдингами | G22: Бюджет | H22: Да | I22: Окончательный ГП-243
A23: =A22+1 -> 14 | B23: Малый П.А. | C23: ИП Полежаев А.А. | D23: Счёт№51 от 02.12.2025 | E23: .54956 | F23: Устройство калон террасы | G23: Бюджет | I23: Окончательный. ГП-294.295 Договор подряда№ФП-10660-29 ОТ 16.09.2022
A24: =A23+1 -> 15 | B24: Малый П.А. | C24: ИП Полежаев А.А. | D24: Счёт№53 от 20.01.2025 | E24: .842553 | F24: Фасад | I24: ГП-148 Дог№-ФП-25112024-01от 25.11.2024 ПР№2 от 25.11.2024
A25: =A24+1 -> 16 | B25: Лещенко В.А. | C25: ИП Любомирский В.Г. | D25: Счет № 20 от 28.07.2025 | E25: .558077 | F25: Электромонтажные работы | G25: Бюджет | H25: Да | I25: Вн. рынок. Щепкин СПА
A26: =A25+1 -> 17 | B26: Лещенко В.А. | C26: ИП Любомирский В.Г. | D26: Счет № 25 от 23.09.2025 | E26: .210906 | F26: Оплата работ по пр.1/12 от 22.09.25 к дог.№ФП-10660-10/01 от 19.03.2024г | G26: Бюджет | H26: Да | I26: ГП 13. Электрика. 4й этап
A27: =A26+1 -> 18 | B27: Малый П.А. | C27: ИП Кравченко К.Н. | D27: Счёт№542 от 24.10.2025 | E27: .32621,5 | F27: Пиломатериалы | G27: Бюджет | H27: Да | I27: Вн.Рынок. Щепкино, кровля
A28: =A27+1 -> 19 | B28: Малый П.А. | C28: ИП Кравченко К.Н. | D28: Счёт №548 от 28.10.2025 | E28: .38400 | F28: Пиломатериалы | G28: Бюджет | H28: Да | I28: Вн.Рынок. Щепкино,кровля
A29: =A28+1 -> 20 | B29: Малый П.А. | C29: ИП Кравченко К.Н. | D29: Счёт №566 от 19.11.2025 | E29: .38400 | F29: Пиломатериалы | G29: Бюджет | H29: Да | I29: Навес ГП 262
A30: =A29+1 -> 21 | B30: Малый П.А. | C30: ИП Кравченко К.Н. | D30: Счёт № 609 от 22.12.2025 | E30: .128725,35 | F30: Пиломатериалы | G30: Бюджет | I30: Навес ГП 262
A31: =A30+1 -> 22 | B31: Синицына В.В. | C31: ИП Храмова Э.Э. | D31: Счет №2042 от 17.11.2025 | E31: .42000 | F31: Услуги по благоустройству территории с 10.11.2025 по 13.11.2025 | G31: Бюджет | H31: Да
A32: =A31+1 -> 23 | B32: Малый П.А. | C32: ИП Храмова Э.Э | D32: Счёт№2177от 08.12.2025 | E32: .16800 | F32: Благоустройство территории | G32: Бюджет | I32: ГП-103 Дог№ФП-10660-36 Планирование грунта
A33: =A32+1 -> 24 | B33: Малый П.А. | C33: ИП Храмова Э.Э. | D33: Счёт№2233 от 15.12.2025 | E33: .8400 | F33: Благоустройство территории | G33: Бюджет | I33: ГП-218,231,213,214,216,221,188 Дог№10660-36 от 15.032023 чистка преддомовых территорий
A34: =A33+1 -> 25 | B34: Синицына В.В. | C34: ИП Храмова Э.Э. | D34: Счет №2252 от 22.12.2025 | E34: .42000 | F34: Услуги по благоустройству территории | G34: Бюджет
A35: =A34+1 -> 26 | B35: Синицына В.В. | C35: ИП Храмова Э.Э. | D35: Счет №2301 от 25.12.2025г. | E35: .25200 | F35: Услуги по благоустройству территории | G35: Бюджет
A36: =A35+1 -> 27 | B36: Лещенко В.А. | C36: ИП Сердечная О.Ю. | D36: Счет № 291 от 17.09.2025 | E36: .59500 | F36: Договор №3 от 30.03.2022 г. Транспортные услуги по перевозке опалубки, 05.09.2025 г.,16.09.2025 г. | G36: Бюджет | H36: Да | I36: ГП 294. Бассейн.ИП Малый
A37: =A36+1 -> 28 | B37: Лещенко В.А. | C37: ИП Козлова Н.В. | D37: Счет № 27 от 19.11.2024 | E37: .=30500 | F37: Ус-во фасада по дог.№ФП-10660-93 от 01.10.2024 от 19.11.2024 | G37: Бюджет | H37: Да | I37: Окончательный.ГП-211
A38: =A37+1 -> 29 | B38: Лещенко В.А. | C38: ООО "АЛЮМИНИУМ" | D38: Счет № 385 от 03.09.2025 | E38: .386200 | F38: Оплата за алюмииевые конструкции по дог.№ФП-28052024 от 28.05.2025 | G38: Бюджет | H38: Да | I38: ГП 291. Витражи.
A39: =A38+1 -> 30 | B39: Синицына В.В. | C39: ИП Никулов А.В. | D39: Счет №113 от 21.11.2025 | E39: .=146016/2 | F39: Аванс по Приложению 1/14 к Договору №ФП-10660-98 от 04.04.2025 | G39: Бюджет | I39: Монтаж системы полива на придомовой ГП 273, 280
A40: =A39+1 -> 31 | B40: Лещенко В.А. | C40: ИП Стрельцов В.А. | D40: Счет № 23 от 07.11.2025 | E40: .600050 | F40: Устройство приточно-вытяжной вентиляции согласно Приложения №1/13 от 11.06.2025г. к Договору подряда №ФП-10660-53/01 от 08.10.2024 г. | G40: Бюджет | H40: Да | I40: ГП 291. Вентиляция
A41: =A40+1 -> 32 | B41: Малый П.А. | C41: ИП Алты-Садых С.Ю | D41: Счёт№18/2 от 15.12.2025 | E41: .109250 | F41: Окончательный платеж за работы, изготовление,монтаж,шлифовку пропитку и окраску деревянных элементов террасы | G41: Бюджет | H41: да | I41: ГП-148 Дог№-ФП-10660-31 ОТ 14.11.2022
A42: =A41+1 -> 33 | B42: Малый П.А. | C42: ИП Чеботарев А.В. | D42: Счет № 1369 от 11.09.2025 | E42: .107000 | F42: Разработка дизайн проекта. Пр.№ 1/2 к дог.№ФП-10660-101 от 21.08.2025 | G42: Бюджет | H42: Да | I42: ГП 146
A43: =A42+1 -> 34 | B43: Малый П.А. | C43: ИП Глазунов Е.А. | D43: Счёт№15 от 22.01.2026 | E43: .18400 | F43: Уборка помещений | H43: Да
A44: =A43+1 -> 35 | B44: Лещенко В.А. | C44: сз Шкрябина | D44: Счет №24365802 от 04.12.2025г. | E44: .=414800-114800-130000 | F44: Монтаж фасонных изделий | G44: Бюджет | H44: Да | I44: ГП 291-292
A45: =A44+1 -> 36 | B45: Малый П.А. | C45: ИП Чеботарёв | D45: Счёт№281 от 24.02.2026 | E45: .30000 | F45: Авторский надзор | I45: ГП 291 Дог об авторском надзоре№2 от 24.02.2026
A46: =A45+1 -> 37 | B46: Малый П.А. | C46: ИП Доброхотова Н.А. | D46: Счёт№1 от 15.01.2026 | E46: .20000 | F46: ЛДУ | I46: Вн. рынок Ореховая роща Дог№ФП-10660 ОТ 21.02.2024
A47: =A46+1 -> 38 | B47: Малый П.А. | C47: ИП Храмова Э.Э. | D47: Счёт№389 от 10.03.2026 | E47: .12600 | F47: Услуги по благоустройству територии | H47: Да | I47: Дог №ФП-10660 от 15.03.2023
A48: =A47+1 -> 39 | B48: Малый П.А. | C48: ООО "УСПЕХ" | D48: Счёт№11695от 12.03.2026 | E48: .11119 | F48: Хим препараты для обработки растений | I48: Дендро
A49: =A48+1 -> 40 | B49: Малый П.А | C49: АО Евраз Маркет | D49: Счёт№ИНН00-050099 от13.03.2026 | E49: .60157,20 | F49: Металлопрокат | I49: ГП-385 ХБП Дог№ФП10022025 ПР№2 от 17.02.2025
A50: =A49+1 -> 41 | B50: Малый П.А. | C50: ИП Чередниченко | D50: Счёт№13 от 18.03.2025 | E50: .116000 | F50: Монтаж плинтуса | I50: ГП-138 Дог №ФП-10660-84/01 ОТ 01.10.2024
A51: =A50+1 -> 42 | B51: Малый П.А. | C51: ИП Чередниченко | D51: Счёт№14 от 18.03.2026 | E51: .196745 | F51: Малярные работы (потолки,доп работы | I51: ГП-138 Дог №ФП-10660-84/01 ОТ 01.10.2024
A52: =A51+1 -> 43 | B52: Малый П.А. | C52: ИП Чередниченко | D52: Счёт№15 от 18.03.2026 | E52: .247720 | F52: Монтаж плинтуса | I52: ГП-138 Дог №ФП-10660-84/01 ОТ 01.10.2024
A53: =A52+1 -> 44 | B53: Малый П.А. | C53: ИП Чередниченко | D53: Счёт№16 от18.03.2026 | E53: .77175 | F53: Плиточные работы.дверные откосы | I53: ГП-138 Дог№ФП-10660-84/01 ОТ 01.10.2024
A54: =A53+1 -> 45 | B54: МалыйП.А. | C54: ИП Кривошлыкова Я.В. | D54: Счёт№46 от 16.03 2026 | E54: .40482 | F54: Оказание транспортных услуг | I54: Дог №ФП-10660-85 от 19.07.2024
A55: =A54+1 -> 46 | B55: Малый П.А. | C55: ООО"Ростехплан" | D55: Счёт№06/03 от06.03.2026 | E55: 12000 | F55: Техплан | I55: ГП-326 Дог№04707 от 11.02.2026 | J55: оплачен
A56: =A55+1 -> 47 | B56: Малый П.А. | C56: ИП Кривошлыкова Я.В. | D56: Счёт№45от13.03.2026 | E56: 12500 | F56: Оказание транспортных услуг | I56: ГП-385 ХБП Дог№ФП10022025 ПР№2 от 17.02.2025 | J56: оплачен
A57: =A56+1 -> 48 | B57: Малый П.А. | C57: ООО "ЛЕ МОНЛИД" | E57: 10000 | F57: Пополнение клиентского счета | I57: ГП-385 ХБП Дог№ФП10022025 ПР№2 от 17.02.2025 | J57: оплачен
B58: АХР (Продажи / IT служба / Юр служба / ФЭО /Секретариат)
A59: 1 | B59: Антоненко | C59: ИП Медовник Андрей Сергеевич | D59: Счет на оплату № 231 от 16 марта 2026 г. | E59: .5000 | F59: Адаптация/модификация программ для ЭВМ и баз данных на платформе Prologue-UNI (Тариф: "Визитка", Проект: "abfabrika.ru", Период: "2026 Апрель") | H59: Да
A60: 2
A61: 3
A62: 4
A63: 5
B64: Бухгалтерия (Налоги / ЗП / ЕСН / прочие платежи бух. службы)
A65: 1 | B65: Попова Е.П. | C65: Кожанов Александр Николаевич | D65: Заяв.на возмещ.ДС от 17.03.2026 | E65: 5117 | F65: Заяв.на возмещ.ДС от 17.03.2026 | H65: Да | J65: оплачен
A66: 2 | B66: Дмитриева О. В. | C66: ИФНС по ЕНП | D66: КБК 18201061201010000510 | E66: .225000 | F66: Страховые взносы за февраль 2026 г (налоги с фот)
A67: 3 | B67: Дмитриева О. В. | C67: ИФНС по ЕНП | D67: КБК 182 01 06 12 01 01 0000 510 | E67: .42000 | F67: НДФЛ (период с 23.02-28.02.2026) | I67: срок оплаты до 05.03.26
A68: 4 | B68: Дмитриева О. В. | C68: ИФНС по ЕНП | D68: КБК 182 01 06 12 01 01 0000 510 | E68: .73000 | F68: НДФЛ (период с 01.02-22.02.2026) | I68: срок оплаты до 02.03.26
A69: 5
A70: ИТОГО ФАБРИКА ПРОЕКТОВ РАСХОДЫ ПО РЕЕСТРУ | E70: =SUM(E9:E69) -> 39617
A71: ДЕФИЦИТ / ПРОФИЦИТ с Остатка на начало дня | E71: =E4-E70 -> 3917.66

Sheet 20
E1: _____________________________ Согласовано
C2: ='19'!C2+1 -> 46101 | F2: Реестр разбит по Юр. лицам!!! КРУТИТЕ ВНИЗ
A4: ФАБРИКА ПРОЕКТОВ | E4: =SUM(E5:E6) -> 1013342.2 | F4: Реестр закрыт!!!
A5: Счет Альфа 1674 | E5: 1011661.5
A6: счет СБЕР 6989 | E6: 1680.64
A8: № п/п | B8: Инициатор платежа | C8: Контрагент - Получатель | D8: Договор/Счет | E8: Сумма к оплате | F8: Назначение платежа | G8: Бюджет/Статья | H8: Наличие Договора | I8: Примечание | J8: Отметка об оплате | K8: Спец. Распоряжение / Приоритет
B9: Коммерческая деятельность (Закупка ТМЦ Снабжение / Логистика / Транзит)
A10: 1
A11: 2
A12: 3
A13: 4
A14: 5
A15: 6
A16: 7
A17: 8
A18: 9
A19: 10
A20: 11
A21: 12
... A59: 50
B60: АХР (Продажи / IT служба / Юр служба / ФЭО /Секретариат)
A61: 1
A62: 2
A63: 3
A64: 4
A65: 5
B66: Бухгалтерия (Налоги / ЗП / ЕСН / прочие платежи бух. службы)
A67: 1
A68: 2
A69: 3
A70: 4
A71: 5
A72: ИТОГО ФАБРИКА ПРОЕКТОВ РАСХОДЫ ПО РЕЕСТРУ | E72: =SUM(E9:E71) -> 0
A73: ДЕФИЦИТ / ПРОФИЦИТ с Остатка на начало дня | E73: =E4-E72 -> 1013342.2

Sheet 21
E1: _____________________________ Согласовано
C2: ='20'!C2+1 -> 46102 | F2: Реестр разбит по Юр. лицам!!! КРУТИТЕ ВНИЗ
A4: ФАБРИКА ПРОЕКТОВ | E4: =SUM(E5:E6) -> 0
A5: Счет Альфа 1674
A6: счет СБЕР 6989
A8: № п/п | B8: Инициатор платежа | C8: Контрагент - Получатель | D8: Договор/Счет | E8: Сумма к оплате | F8: Назначение платежа | G8: Бюджет/Статья | H8: Наличие Договора | I8: Примечание | J8: Отметка об оплате | K8: Спец. Распоряжение / Приоритет
B9: Коммерческая деятельность (Закупка ТМЦ Снабжение / Логистика / Транзит)
A10: 1
A11: 2
A12: 3
A13: 4
A14: 5
A15: 6
A16: 7
A17: 8
A18: 9
A19: 10
A20: 11
A21: 12
... A59: 50
B60: АХР (Продажи / IT служба / Юр служба / ФЭО /Секретариат)
A61: 1
A62: 2
A63: 3
A64: 4
A65: 5
B66: Бухгалтерия (Налоги / ЗП / ЕСН / прочие платежи бух. службы)
A67: 1
A68: 2
A69: 3
A70: 4
A71: 5
A72: ИТОГО ФАБРИКА ПРОЕКТОВ РАСХОДЫ ПО РЕЕСТРУ | E72: =SUM(E9:E71) -> 0
A73: ДЕФИЦИТ / ПРОФИЦИТ с Остатка на начало дня | E73: =E4-E72 -> 0

Sheet 22
E1: _____________________________ Согласовано
C2: ='21'!C2+1 -> 46103 | F2: Реестр разбит по Юр. лицам!!! КРУТИТЕ ВНИЗ
A4: ФАБРИКА ПРОЕКТОВ | E4: =SUM(E5:E6) -> 0
A5: Счет Альфа 1674
A6: счет СБЕР 6989
A8: № п/п | B8: Инициатор платежа | C8: Контрагент - Получатель | D8: Договор/Счет | E8: Сумма к оплате | F8: Назначение платежа | G8: Бюджет/Статья | H8: Наличие Договора | I8: Примечание | J8: Отметка об оплате | K8: Спец. Распоряжение / Приоритет
B9: Коммерческая деятельность (Закупка ТМЦ Снабжение / Логистика / Транзит)
A10: 1
A11: 2
A12: 3
A13: 4
A14: 5
A15: 6
A16: 7
A17: 8
A18: 9
A19: 10
A20: 11
A21: 12
... A59: 50
B60: АХР (Продажи / IT служба / Юр служба / ФЭО /Секретариат)
A61: 1
A62: 2
A63: 3
A64: 4
A65: 5
B66: Бухгалтерия (Налоги / ЗП / ЕСН / прочие платежи бух. службы)
A67: 1
A68: 2
A69: 3
A70: 4
A71: 5
A72: ИТОГО ФАБРИКА ПРОЕКТОВ РАСХОДЫ ПО РЕЕСТРУ | E72: =SUM(E9:E71) -> 0
A73: ДЕФИЦИТ / ПРОФИЦИТ с Остатка на начало дня | E73: =E4-E72 -> 0

Sheet 23
E1: _____________________________ Согласовано
C2: ='22'!C2+1 -> 46104 | F2: Реестр разбит по Юр. лицам!!! КРУТИТЕ ВНИЗ
A4: ФАБРИКА ПРОЕКТОВ | E4: =SUM(E5:E6) -> 1060168.2 | F4: Реестр закрыт!!!
A5: Счет Альфа 1674 | E5: 1049561.5
A6: счет СБЕР 6989 | E6: 10606.64
A8: № п/п | B8: Инициатор платежа | C8: Контрагент - Получатель | D8: Договор/Счет | E8: Сумма к оплате | F8: Назначение платежа | G8: Бюджет/Статья | H8: Наличие Договора | I8: Примечание | J8: Отметка об оплате | K8: Спец. Распоряжение / Приоритет
B9: Коммерческая деятельность (Закупка ТМЦ Снабжение / Логистика / Транзит)
A10: 1
A11: 2
A12: 3
A13: 4
A14: 5
A15: 6
A16: 7
A17: 8
A18: 9
A19: 10
A20: 11
A21: 12
... A59: 50
B60: АХР (Продажи / IT служба / Юр служба / ФЭО /Секретариат)
A61: 1
A62: 2
A63: 3
A64: 4
A65: 5
B66: Бухгалтерия (Налоги / ЗП / ЕСН / прочие платежи бух. службы)
A67: 1
A68: 2
A69: 3
A70: 4
A71: 5
A72: ИТОГО ФАБРИКА ПРОЕКТОВ РАСХОДЫ ПО РЕЕСТРУ | E72: =SUM(E9:E71) -> 0
A73: ДЕФИЦИТ / ПРОФИЦИТ с Остатка на начало дня | E73: =E4-E72 -> 1060168.2

Sheet 24
E1: _____________________________ Согласовано
C2: ='23'!C2+1 -> 46105 | F2: Реестр разбит по Юр. лицам!!! КРУТИТЕ ВНИЗ
A4: ФАБРИКА ПРОЕКТОВ | E4: =SUM(E5:E6) -> 1098278.2 | F4: Реестр закрыт!!!
A5: Счет Альфа 1674 | E5: 1087671.5
A6: счет СБЕР 6989 | E6: 10606.64
A8: № п/п | B8: Инициатор платежа | C8: Контрагент - Получатель | D8: Договор/Счет | E8: Сумма к оплате | F8: Назначение платежа | G8: Бюджет/Статья | H8: Наличие Договора | I8: Примечание | J8: Отметка об оплате | K8: Спец. Распоряжение / Приоритет
B9: Коммерческая деятельность (Закупка ТМЦ Снабжение / Логистика / Транзит)
A10: 1 | B10: Лещенко В.А. | C10: ООО ГЕРМЕС | D10: Счет № 493 от 24.10.2025 | E10: .218750 | F10: Закупка бетона | G10: Бюджет | H10: Да | I10: ГП 294 Забор. ИП Малый. Договор №ФП31072025 от 31.07.2025 Приложение №2
A11: =A10+1 -> 2 | B11: Лещенко В.А. | C11: ООО "Айрон" | D11: Счет №АИПП-2504 от 21.03.2025 | E11: .=16534 | F11: Закупка металла. | G11: Бюджет | H11: Да | I11: (Щепкино. СПА.стены)ИП Малый Договор подряда №ФП-03022025 от 03.02.2025 Пр. №2 от 03.02.2025 ИП Малый
A12: =A11+1 -> 3 | B12: Лещенко В.А. | C12: ООО "Айрон" | D12: Счет № АИПП-3664 от 25.04.2025 | E12: .126845 | F12: Закупка металла на объект | G12: Бюджет | H12: Да | I12: ГП 204 (Навес) Договор подряда №ФП-27032025 от 27.03.2025 Приложение № 2 от 27.03.2025
A13: =A12+1 -> 4 | B13: Лещенко В.А. | C13: ООО "Айрон" | D13: Счет № АИПП-3754 от 29.04.2025 | E13: .27325 | F13: Закупка металла. | G13: Бюджет | H13: Да | I13: ГП 204(навес) Договор подряда №ФП-27032025 от 27.03.2025 Приложение №2 от 27.03.2025
A14: =A13+1 -> 5 | B14: Лещенко В.А. | C14: ООО "Айрон" | D14: Счет № АИПП-5404 от 30.06.2025 | E14: .150100 | F14: Закупка металла на объект | G14: Бюджет | H14: Да | I14: ГП 294. ХБП ИП Малый Договор подряда №ФП-19062025 от 19.06.2025 Приложение №2 от 19.06.2025
A15: =A14+1 -> 6 | B15: Лещенко В.А. | C15: ООО "Айрон" | D15: Счет № АИПП-5407 от 30.06.2025 | E15: .17300 | F15: Закупка металла на объект | G15: Бюджет | H15: Да | I15: ГП 204. ИП Малый. Договор подряда №ФП-27032025 от 27.03.2025 Приложение №2 от 27.03.2025
A16: =A15+1 -> 7 | B16: Лещенко В.А. | C16: ООО "Айрон" | D16: Счет № АИПП-5408 от 30.06.2025 | E16: .35505 | F16: Закупка металла на объект | G16: Бюджет | H16: Да | I16: ГП 13. (ХБП) ИП Малый. Договор подряда №ФП-10660-72/01 от 12.02.2024 г. Приложение №1/8 от 14.03.2025
A17: =A16+1 -> 8 | B17: Лещенко В.А. | C17: ООО "Айрон" | D17: Счет № АИПП-6301 от 04.08.2025 | E17: .163370 | F17: Закупка металла на объект | G17: Бюджет | H17: Да | I17: ГП 326. Забор ИП Малый
A18: =A17+1 -> 9 | B18: Лещенко В.А. | C18: ООО "Айрон" | D18: Счет № АИПП-6303 от 04.08.2025 | E18: .115500 | F18: Закупка металла на объект | G18: Бюджет | H18: Да | I18: ГП 294. Бассеин ИП Малый
A19: =A18+1 -> 10 | B19: Лещенко В.А. | C19: ООО "Айрон" | D19: Счет № АИПП-6304 от 04.08.2025 | E19: .51000 | F19: Закупка металла на объект | G19: Бюджет | H19: Да | I19: ГП 294. Забор ИП Малый
A20: =A19+1 -> 11 | B20: Лещенко В.А. | C20: ИП Полежаев А.А. | D20: Счет № 42 от 26.09.2025 | E20: .363298 | F20: Устройство фасада с молдингами на ХБП по дог.№ФП-10660-29 от 16.09.2022, пр.№ 1/19 | G20: Бюджет | H20: Да | I20: Окончательный ГП 326
A21: =A20+1 -> 12 | B21: Лещенко В.А. | C21: ИП Полежаев А.А. | D21: Счет № 44 от 30.09.2025 | E21: .313500 | F21: Устройство фасада с молдингами на ХБП. Договор подряда №ФП-10660-29 от 16.09.2022 Приложение № 1/25 | G21: Бюджет | H21: Да | I21: Аванс ГП 294,295
A22: =A21+1 -> 13 | B22: Малый П.А. | C22: ИП Полежаев А.А. | D22: Счёт №50 от 26.11.2025 | E22: .538264 | F22: Устройство фасада с молдингами | G22: Бюджет | H22: Да | I22: Окончательный ГП-243
A23: =A22+1 -> 14 | B23: Малый П.А. | C23: ИП Полежаев А.А. | D23: Счёт№51 от 02.12.2025 | E23: .54956 | F23: Устройство калон террасы | G23: Бюджет | H23: Да | I23: Окончательный. ГП-294.295 Договор подряда№ФП-10660-29 ОТ 16.09.2022
A24: =A23+1 -> 15 | B24: Малый П.А. | C24: ИП Полежаев А.А. | D24: Счёт№53 от 20.01.2025 | E24: .842553 | F24: Фасад | H24: Да | I24: ГП-148 Дог№-ФП-25112024-01от 25.11.2024 ПР№2 от 25.11.2024
A25: =A24+1 -> 16 | B25: Лещенко В.А. | C25: ИП Любомирский В.Г. | D25: Счет № 20 от 28.07.2025 | E25: .558077 | F25: Электромонтажные работы | G25: Бюджет | H25: Да | I25: Вн. рынок. Щепкин СПА
A26: =A25+1 -> 17 | B26: Лещенко В.А. | C26: ИП Любомирский В.Г. | D26: Счет № 25 от 23.09.2025 | E26: .210906 | F26: Оплата работ по пр.1/12 от 22.09.25 к дог.№ФП-10660-10/01 от 19.03.2024г | G26: Бюджет | H26: Да | I26: ГП 13. Электрика. 4й этап
A27: =A26+1 -> 18 | B27: Малый П.А. | C27: ИП Кравченко К.Н. | D27: Счёт№542 от 24.10.2025 | E27: .32621,5 | F27: Пиломатериалы | G27: Бюджет | H27: Да | I27: Вн.Рынок. Щепкино, кровля
A28: =A27+1 -> 19 | B28: Малый П.А. | C28: ИП Кравченко К.Н. | D28: Счёт №548 от 28.10.2025 | E28: .38400 | F28: Пиломатериалы | G28: Бюджет | H28: Да | I28: Вн.Рынок. Щепкино,кровля
A29: =A28+1 -> 20 | B29: Малый П.А. | C29: ИП Кравченко К.Н. | D29: Счёт №566 от 19.11.2025 | E29: .38400 | F29: Пиломатериалы | G29: Бюджет | H29: Да | I29: Навес ГП 262
A30: =A29+1 -> 21 | B30: Малый П.А. | C30: ИП Кравченко К.Н. | D30: Счёт № 609 от 22.12.2025 | E30: .128725,35 | F30: Пиломатериалы | G30: Бюджет | H30: Да | I30: Навес ГП 262
A31: =A30+1 -> 22 | B31: Синицына В.В. | C31: ИП Храмова Э.Э. | D31: Счет №2042 от 17.11.2025 | E31: .42000 | F31: Услуги по благоустройству территории с 10.11.2025 по 13.11.2025 | G31: Бюджет | H31: Да
A32: =A31+1 -> 23 | B32: Малый П.А. | C32: ИП Храмова Э.Э | D32: Счёт№2177от 08.12.2025 | E32: .16800 | F32: Благоустройство территории | G32: Бюджет | H32: Да | I32: ГП-103 Дог№ФП-10660-36 Планирование грунта
A33: =A32+1 -> 24 | B33: Малый П.А. | C33: ИП Храмова Э.Э. | D33: Счёт№2233 от 15.12.2025 | E33: .8400 | F33: Благоустройство территории | G33: Бюджет | H33: Да | I33: ГП-218,231,213,214,216,221,188 Дог№10660-36 от 15.032023 чистка преддомовых территорий
A34: =A33+1 -> 25 | B34: Синицына В.В. | C34: ИП Храмова Э.Э. | D34: Счет №2252 от 22.12.2025 | E34: .42000 | F34: Услуги по благоустройству территории | G34: Бюджет | H34: Да
A35: =A34+1 -> 26 | B35: Синицына В.В. | C35: ИП Храмова Э.Э. | D35: Счет №2301 от 25.12.2025г. | E35: .25200 | F35: Услуги по благоустройству территории | G35: Бюджет | H35: Да
A36: =A35+1 -> 27 | B36: Лещенко В.А. | C36: ИП Сердечная О.Ю. | D36: Счет № 291 от 17.09.2025 | E36: .59500 | F36: Договор №3 от 30.03.2022 г. Транспортные услуги по перевозке опалубки, 05.09.2025 г.,16.09.2025 г. | G36: Бюджет | H36: Да | I36: ГП 294. Бассейн.ИП Малый
A37: =A36+1 -> 28 | B37: Лещенко В.А. | C37: ИП Козлова Н.В. | D37: Счет № 27 от 19.11.2024 | E37: .=30500 | F37: Ус-во фасада по дог.№ФП-10660-93 от 01.10.2024 от 19.11.2024 | G37: Бюджет | H37: Да | I37: Окончательный.ГП-211
A38: =A37+1 -> 29 | B38: Лещенко В.А. | C38: ООО "АЛЮМИНИУМ" | D38: Счет № 385 от 03.09.2025 | E38: .386200 | F38: Оплата за алюмииевые конструкции по дог.№ФП-28052024 от 28.05.2025 | G38: Бюджет | H38: Да | I38: ГП 291. Витражи.
A39: =A38+1 -> 30 | B39: Синицына В.В. | C39: ИП Никулов А.В. | D39: Счет №113 от 21.11.2025 | E39: .=146016/2 | F39: Аванс по Приложению 1/14 к Договору №ФП-10660-98 от 04.04.2025 | G39: Бюджет | H39: Да | I39: Монтаж системы полива на придомовой ГП 273, 280
A40: =A39+1 -> 31 | B40: Лещенко В.А. | C40: ИП Стрельцов В.А. | D40: Счет № 23 от 07.11.2025 | E40: .600050 | F40: Устройство приточно-вытяжной вентиляции согласно Приложения №1/13 от 11.06.2025г. к Договору подряда №ФП-10660-53/01 от 08.10.2024 г. | G40: Бюджет | H40: Да | I40: ГП 291. Вентиляция
A41: =A40+1 -> 32 | B41: Малый П.А. | C41: ИП Алты-Садых С.Ю | D41: Счёт№18/2 от 15.12.2025 | E41: .109250 | F41: Окончательный платеж за работы, изготовление,монтаж,шлифовку пропитку и окраску деревянных элементов террасы | G41: Бюджет | H41: Да | I41: ГП-148 Дог№-ФП-10660-31 ОТ 14.11.2022
A42: =A41+1 -> 33 | B42: Малый П.А. | C42: ИП Чеботарев А.В. | D42: Счет № 1369 от 11.09.2025 | E42: .107000 | F42: Разработка дизайн проекта. Пр.№ 1/2 к дог.№ФП-10660-101 от 21.08.2025 | G42: Бюджет | H42: Да | I42: ГП 146
A43: =A42+1 -> 34 | B43: Малый П.А. | C43: ИП Глазунов Е.А. | D43: Счёт№15 от 22.01.2026 | E43: .18400 | F43: Уборка помещений | H43: Да
A44: =A43+1 -> 35 | B44: Лещенко В.А. | C44: сз Шкрябина | D44: Счет №24365802 от 04.12.2025г. | E44: .=414800-114800-130000 | F44: Монтаж фасонных изделий | G44: Бюджет | H44: Да | I44: ГП 291-292
A45: =A44+1 -> 36 | B45: Малый П.А. | C45: ИП Чеботарёв | D45: Счёт№281 от 24.02.2026 | E45: .30000 | F45: Авторский надзор | H45: Да | I45: ГП 291 Дог об авторском надзоре№2 от 24.02.2026
A46: =A45+1 -> 37 | B46: Малый П.А. | C46: ИП Доброхотова Н.А. | D46: Счёт№1 от 15.01.2026 | E46: .20000 | F46: ЛДУ | H46: Да | I46: Вн. рынок Ореховая роща Дог№ФП-10660 ОТ 21.02.2024
A47: =A46+1 -> 38 | B47: Малый П.А. | C47: ИП Храмова Э.Э. | D47: Счёт№389 от 10.03.2026 | E47: .12600 | F47: Услуги по благоустройству територии | H47: Да | I47: Дог №ФП-10660 от 15.03.2023
A48: =A47+1 -> 39 | B48: Малый П.А. | C48: ООО "УСПЕХ" | D48: Счёт№11695от 12.03.2026 | E48: .11119 | F48: Хим препараты для обработки растений | H48: Да | I48: Дендро
A49: =A48+1 -> 40 | B49: Малый П.А | C49: АО Евраз Маркет | D49: Счёт№ИНН00-050099 от13.03.2026 | E49: .60157,20 | F49: Металлопрокат | H49: Да | I49: ГП-385 ХБП Дог№ФП10022025 ПР№2 от 17.02.2025
A50: =A49+1 -> 41 | B50: Малый П.А. | C50: ИП Чередниченко | D50: Счёт№13 от 18.03.2025 | E50: .116000 | F50: Монтаж плинтуса | H50: Да | I50: ГП-138 Дог №ФП-10660-84/01 ОТ 01.10.2024
A51: =A50+1 -> 42 | B51: Малый П.А. | C51: ИП Чередниченко | D51: Счёт№14 от 18.03.2026 | E51: 196745 | F51: Малярные работы (потолки,доп работы | H51: Да | I51: ГП-138 Дог №ФП-10660-84/01 ОТ 01.10.2024
A52: =A51+1 -> 43 | B52: Малый П.А. | C52: ИП Чередниченко | D52: Счёт№15 от 18.03.2026 | E52: .247720 | F52: Монтаж плинтуса | H52: Да | I52: ГП-138 Дог №ФП-10660-84/01 ОТ 01.10.2024
A53: =A52+1 -> 44 | B53: Малый П.А. | C53: ИП Чередниченко | D53: Счёт№16 от18.03.2026 | E53: 77175 | F53: Плиточные работы.дверные откосы | H53: Да | I53: ГП-138 Дог№ФП-10660-84/01 ОТ 01.10.2024
A54: =A53+1 -> 45 | B54: МалыйП.А. | C54: ИП Кривошлыкова Я.В. | D54: Счёт№46 от 16.03 2026 | E54: 40482 | F54: Оказание транспортных услуг | H54: Да | I54: Дог №ФП-10660-85 от 19.07.2024
A55: 46 | B55: Малый П.А. | C55: ИП Храмова | D55: Счёт№443 от 16.03.2026 | E55: .25200 | F55: Услуги по благоустройству территории с 11.03.2026 по 12.03.2026 | I55: Дог №ФП-10660-36 ОТ 15.03.2023
A56: 47 | B56: Малый П.А. | C56: ООО "РостАвтоБетон" | D56: Счёт№6 от 14.03.2026 | E56: .105400 | F56: Бетон | I56: ГП-385
A57: 48 | B57: Малый П.А. | C57: ИП Доброхотова Н.А. | D57: Счёт№5 от 19.03.2026 | E57: .21400 | F57: Аванс | I57: ГП-235Дог№ФП-10660-73 от21.02.2024Пр-1/9
A58: 49 | B58: Малый П.А. | C58: ИП Никулов А.В. | D58: Счёт №16 от 20.03.2026 | E58: .26000 | F58: Запуск системы полива | I58: Дог№ФП-10660-98 от 04.04.2025ПР№1/15 от 16.03.2026
A59: 50 | B59: Малый П.А. | C59: ИП Стрельцов В.А. | D59: Счёт№25 от 19.03.2026 | E59: 394300 | F59: Авансовый платёж за отопление и водоснабжение,водоотведение | I59: ГП-146 Дог№ФП-10660-53/01 ОТ 08.10.2024 ПР№1/16 от 29.12.2025
A60: 51 | B60: Малый П.А. | C60: ООО"Агроцентр Дон" | D60: Счёт№31 от 19.03.2026 | E60: .28320 | F60: Препараты для растений | I60: Дендро
A61: 52 | B61: МалыйП.А. | C61: ООО ПК"Пуршат" | D61: Счёт№РМ-3235 от 18.03.2026 | E61: .9497 | F61: Препараты для растений | I61: Дендро
A62: 53 | B62: Малый П.А. | C62: ООО"ВСЕ ИНСТРУМЕНТЫ.РУ" | D62: Счёт№2603-182351-62749 от 23.03.2026 | E62: .4094 | F62: Батарея акумуляторная к опрыскователю | I62: Дендро
A63: 54 | B63: Малый П.А. | C63: ИП Доброхотова Н.А. | D63: Счёт№6 от23.03.2026 | E63: .19920 | F63: ЛДУ | I63: ГП-163Дог№ФП-10660-73 ОТ 21.02.2024 ПР-1/10
A64: 55
B65: АХР (Продажи / IT служба / Юр служба / ФЭО /Секретариат)
A66: 1 | B66: Антоненко | C66: ИП Медовник Андрей Сергеевич | D66: Счет на оплату № 231 от 16 марта 2026 г. | E66: .5000 | F66: Адаптация/модификация программ для ЭВМ и баз данных на платформе Prologue-UNI (Тариф: "Визитка", Проект: "abfabrika.ru", Период: "2026 Апрель") | H66: Да
A67: 2 | B67: Антоненко | C67: ООО "Телемир" | D67: Счет на оплату № 30154 от 22 марта 2026 г. | E67: .2200 | F67: Предоставление услуг связи по договору TN65/2/260324 за период 01.04.2026 - 30.04.2026 для проекта abfabrika.ru | H67: Да | I67: В назначении платежа необходимо указывать: "Оплата по счету №30154 от 22 марта 2026 г, в том числе НДС 22%, 396,72 руб."
A68: 3
A69: 4
A70: 5
B71: Бухгалтерия (Налоги / ЗП / ЕСН / прочие платежи бух. службы)
A72: 1 | B72: Дмитриева О. В. | C72: ИФНС по ЕНП | D72: КБК 18201061201010000510 | E72: .225000 | F72: Страховые взносы за февраль 2026 г (налоги с фот)
A73: 2 | B73: Дмитриева О. В. | C73: ИФНС по ЕНП | D73: КБК 182 01 06 12 01 01 0000 510 | E73: 42000 | F73: НДФЛ (период с 23.02-28.02.2026) | I73: срок оплаты до 05.03.26
A74: 3 | B74: Дмитриева О. В. | C74: ИФНС по ЕНП | D74: КБК 182 01 06 12 01 01 0000 510 | E74: 73000 | F74: НДФЛ (период с 01.02-22.02.2026) | I74: срок оплаты до 02.03.26
A75: 4
A76: 5
A77: ИТОГО ФАБРИКА ПРОЕКТОВ РАСХОДЫ ПО РЕЕСТРУ | E77: =SUM(E9:E76) -> 823702
A78: ДЕФИЦИТ / ПРОФИЦИТ с Остатка на начало дня | E78: =E4-E77 -> 274576.16

Sheet 25
E1: _____________________________ Согласовано
C2: ='24'!C2+1 -> 46106 | F2: Реестр разбит по Юр. лицам!!! КРУТИТЕ ВНИЗ
A4: ФАБРИКА ПРОЕКТОВ | E4: =SUM(E5:E6) -> 1098278.2 | F4: Реестр закрыт!!!
A5: Счет Альфа 1674 | E5: 1087671.5
A6: счет СБЕР 6989 | E6: 10606.64
A8: № п/п | B8: Инициатор платежа | C8: Контрагент - Получатель | D8: Договор/Счет | E8: Сумма к оплате | F8: Назначение платежа | G8: Бюджет/Статья | H8: Наличие Договора | I8: Примечание | J8: Отметка об оплате | K8: Спец. Распоряжение / Приоритет
B9: Коммерческая деятельность (Закупка ТМЦ Снабжение / Логистика / Транзит)
A10: 1 | B10: Малый П.А. | C10: ИП Стрельцов В.А. | D10: Счёт№25 от 19.03.2026 | E10: 394300 | F10: Авансовый платёж за отопление и водоснабжение,водоотведение | G10: Бюджет | H10: Да | I10: ГП-146 Дог№ФП-10660-53/01 ОТ 08.10.2024 ПР№1/16 от 29.12.2025 | J10: оплачен
A11: =A10+1 -> 2 | B11: МалыйП.А. | C11: ИП Кривошлыкова Я.В. | D11: Счёт№46 от 16.03 2026 | E11: 40482 | F11: Оказание транспортных услуг | G11: Бюджет | H11: Да | I11: Дог №ФП-10660-85 от 19.07.2024 | J11: оплачен
A12: =A11+1 -> 3 | B12: Малый П.А. | C12: ИП Чередниченко | D12: Счёт№14 от 18.03.2026 | E12: 196745 | F12: Малярные работы (потолки,доп работы | G12: Бюджет | H12: Да | I12: ГП-138 Дог №ФП-10660-84/01 ОТ 01.10.2024 | J12: оплачен
A13: =A12+1 -> 4 | B13: Малый П.А. | C13: ИП Чередниченко | D13: Счёт№16 от18.03.2026 | E13: 77175 | F13: Плиточные работы.дверные откосы | G13: Бюджет | H13: Да | I13: ГП-138 Дог№ФП-10660-84/01 ОТ 01.10.2024 | J13: оплачен
A14: =A13+1 -> 5 | B14: Малый П.А. | C14: ИП Чеботарёв | D14: Счёт№281 от 24.02.2026 | E14: 30000 | F14: Авторский надзор | G14: Бюджет | H14: Да | I14: ГП 291 Дог об авторском надзоре№2 от 24.02.2026 | J14: оплачен
A15: =A14+1 -> 6 | B15: МалыйП.А. | C15: ООО ПК"Пуршат" | D15: Счёт№РМ-3235 от 18.03.2026 | E15: 9497 | F15: Препараты для растений | G15: Бюджет | H15: Да | I15: Дендро | J15: оплачен
A16: =A15+1 -> 7
B17: АХР (Продажи / IT служба / Юр служба / ФЭО /Секретариат)
A18: 1 | B18: Антоненко | C18: ИП ПОГУДИН ГРИГОРИЙ АНДРЕЕВИЧ | D18: Счет на оплату № 523 от 25 марта 2026 г. | E18: 3000 | F18: Дизайн-макет буклета 6 полос, 2 биговки, А4 | J18: оплачен
A19: 2
A20: 3
A21: 4
A22: 5
B23: Бухгалтерия (Налоги / ЗП / ЕСН / прочие платежи бух. службы)
A24: 1 | B24: Дмитриева О. В. | C24: Альфа-Банк | D24: реестр | E24: 225431.29 | F24: зарплата за первую половину марта 2026 г. | J24: оплачен
A25: 2 | B25: Дмитриева О. В. | C25: ИФНС по ЕНП | D25: КБК 182 01 06 12 01 01 0000 510 | E25: .49000 | F25: НДФЛ (период с 01.03-22.03.2026) | I25: срок оплаты до 27.03.26
A26: 2 | B26: Дмитриева О. В. | C26: ИФНС по ЕНП | D26: КБК 182 01 06 12 01 01 0000 510 | E26: 42000 | F26: НДФЛ (период с 23.02-28.02.2026) | I26: срок оплаты до 05.03.26 | J26: оплачен
A27: 3 | B27: Дмитриева О. В. | C27: ИФНС по ЕНП | D27: КБК 182 01 06 12 01 01 0000 510 | E27: 73000 | F27: НДФЛ (период с 01.02-22.02.2026) | I27: срок оплаты до 02.03.26 | J27: оплачен
A28: 5
A29: ИТОГО ФАБРИКА ПРОЕКТОВ РАСХОДЫ ПО РЕЕСТРУ | E29: =SUM(E9:E28) -> 1091630.3
A30: ДЕФИЦИТ / ПРОФИЦИТ с Остатка на начало дня | E30: =E4-E29 -> 6647.87

Sheet 26
E1: _____________________________ Согласовано
C2: ='25'!C2+1 -> 46107 | F2: Реестр разбит по Юр. лицам!!! КРУТИТЕ ВНИЗ
A4: ФАБРИКА ПРОЕКТОВ | E4: =SUM(E5:E6) -> 859861.87 | F4: Реестр закрыт!!!
A5: Счет Альфа 1674 | E5: 849255.23 | F5: ОСТАВЛЯЙТЕ НА КОМИССИЮ
A6: счет СБЕР 6989 | E6: 10606.64
A8: № п/п | B8: Инициатор платежа | C8: Контрагент - Получатель | D8: Договор/Счет | E8: Сумма к оплате | F8: Назначение платежа | G8: Бюджет/Статья | H8: Наличие Договора | I8: Примечание | J8: Отметка об оплате | K8: Спец. Распоряжение / Приоритет
B9: Коммерческая деятельность (Закупка ТМЦ Снабжение / Логистика / Транзит)
A10: 1 | B10: Лещенко В.А. | C10: ООО ГЕРМЕС | D10: Счет № 493 от 24.10.2025 | E10: .218750 | F10: Закупка бетона | G10: Бюджет | H10: Да | I10: ГП 294 Забор. ИП Малый. Договор №ФП31072025 от 31.07.2025 Приложение №2
A11: =A10+1 -> 2 | B11: Лещенко В.А. | C11: ООО "Айрон" | D11: Счет №АИПП-2504 от 21.03.2025 | E11: .=16534 | F11: Закупка металла. | G11: Бюджет | H11: Да | I11: (Щепкино. СПА.стены)ИП Малый Договор подряда №ФП-03022025 от 03.02.2025 Пр. №2 от 03.02.2025 ИП Малый
A12: =A11+1 -> 3 | B12: Лещенко В.А. | C12: ООО "Айрон" | D12: Счет № АИПП-3664 от 25.04.2025 | E12: .126845 | F12: Закупка металла на объект | G12: Бюджет | H12: Да | I12: ГП 204 (Навес) Договор подряда №ФП-27032025 от 27.03.2025 Приложение № 2 от 27.03.2025
A13: =A12+1 -> 4 | B13: Лещенко В.А. | C13: ООО "Айрон" | D13: Счет № АИПП-3754 от 29.04.2025 | E13: .27325 | F13: Закупка металла. | G13: Бюджет | H13: Да | I13: ГП 204(навес) Договор подряда №ФП-27032025 от 27.03.2025 Приложение №2 от 27.03.2025
A14: =A13+1 -> 5 | B14: Лещенко В.А. | C14: ООО "Айрон" | D14: Счет № АИПП-5404 от 30.06.2025 | E14: .150100 | F14: Закупка металла на объект | G14: Бюджет | H14: Да | I14: ГП 294. ХБП ИП Малый Договор подряда №ФП-19062025 от 19.06.2025 Приложение №2 от 19.06.2025
A15: =A14+1 -> 6 | B15: Лещенко В.А. | C15: ООО "Айрон" | D15: Счет № АИПП-5407 от 30.06.2025 | E15: .17300 | F15: Закупка металла на объект | G15: Бюджет | H15: Да | I15: ГП 204. ИП Малый. Договор подряда №ФП-27032025 от 27.03.2025 Приложение №2 от 27.03.2025
A16: =A15+1 -> 7 | B16: Лещенко В.А. | C16: ООО "Айрон" | D16: Счет № АИПП-5408 от 30.06.2025 | E16: .35505 | F16: Закупка металла на объект | G16: Бюджет | H16: Да | I16: ГП 13. (ХБП) ИП Малый. Договор подряда №ФП-10660-72/01 от 12.02.2024 г. Приложение №1/8 от 14.03.2025
A17: =A16+1 -> 8 | B17: Лещенко В.А. | C17: ООО "Айрон" | D17: Счет № АИПП-6301 от 04.08.2025 | E17: .163370 | F17: Закупка металла на объект | G17: Бюджет | H17: Да | I17: ГП 326. Забор ИП Малый
A18: =A17+1 -> 9 | B18: Лещенко В.А. | C18: ООО "Айрон" | D18: Счет № АИПП-6303 от 04.08.2025 | E18: .115500 | F18: Закупка металла на объект | G18: Бюджет | H18: Да | I18: ГП 294. Бассеин ИП Малый
A19: =A18+1 -> 10 | B19: Лещенко В.А. | C19: ООО "Айрон" | D19: Счет № АИПП-6304 от 04.08.2025 | E19: .51000 | F19: Закупка металла на объект | G19: Бюджет | H19: Да | I19: ГП 294. Забор ИП Малый
A20: =A19+1 -> 11 | B20: Лещенко В.А. | C20: ИП Полежаев А.А. | D20: Счет № 42 от 26.09.2025 | E20: .363298 | F20: Устройство фасада с молдингами на ХБП по дог.№ФП-10660-29 от 16.09.2022, пр.№ 1/19 | G20: Бюджет | H20: Да | I20: Окончательный ГП 326
A21: =A20+1 -> 12 | B21: Лещенко В.А. | C21: ИП Полежаев А.А. | D21: Счет № 44 от 30.09.2025 | E21: .313500 | F21: Устройство фасада с молдингами на ХБП. Договор подряда №ФП-10660-29 от 16.09.2022 Приложение № 1/25 | G21: Бюджет | H21: Да | I21: Аванс ГП 294,295
A22: =A21+1 -> 13 | B22: Малый П.А. | C22: ИП Полежаев А.А. | D22: Счёт №50 от 26.11.2025 | E22: .538264 | F22: Устройство фасада с молдингами | G22: Бюджет | H22: Да | I22: Окончательный ГП-243
... A30: =A29+1 -> 21 | B30: Малый П.А. | C30: ИП Кравченко К.Н. | D30: Счёт № 609 от 22.12.2025 | E30: .128725,35 | F30: Пиломатериалы | G30: Бюджет | H30: Да | I30: Навес ГП 262
A31: =A30+1 -> 22 | B31: Синицына В.В. | C31: ИП Храмова Э.Э. | D31: Счет №2042 от 17.11.2025 | E31: .42000 | F31: Услуги по благоустройству территории с 10.11.2025 по 13.11.2025 | G31: Бюджет | H31: Да
A32: =A31+1 -> 23 | B32: Синицына В.В. | C32: ИП Храмова Э.Э. | D32: Счет №2252 от 22.12.2025 | E32: .42000 | F32: Услуги по благоустройству территории | G32: Бюджет | H32: Да
A33: =A32+1 -> 24 | B33: Синицына В.В. | C33: ИП Храмова Э.Э. | D33: Счет №2301 от 25.12.2025г. | E33: .25200 | F33: Услуги по благоустройству территории | G33: Бюджет | H33: Да
A34: =A33+1 -> 25 | B34: Лещенко В.А. | C34: ИП Сердечная О.Ю. | D34: Счет № 291 от 17.09.2025 | E34: .59500 | F34: Договор №3 от 30.03.2022 г. Транспортные услуги по перевозке опалубки, 05.09.2025 г.,16.09.2025 г. | G34: Бюджет | H34: Да | I34: ГП 294. Бассейн.ИП Малый
A35: =A34+1 -> 26 | B35: Лещенко В.А. | C35: ИП Козлова Н.В. | D35: Счет № 27 от 19.11.2024 | E35: .=30500 | F35: Ус-во фасада по дог.№ФП-10660-93 от 01.10.2024 от 19.11.2024 | G35: Бюджет | H35: Да | I35: Окончательный.ГП-211
A36: =A35+1 -> 27 | B36: Лещенко В.А. | C36: ООО "АЛЮМИНИУМ" | D36: Счет № 385 от 03.09.2025 | E36: .386200 | F36: Оплата за алюмииевые конструкции по дог.№ФП-28052024 от 28.05.2025 | G36: Бюджет | H36: Да | I36: ГП 291. Витражи.
A37: =A36+1 -> 28 | B37: Синицына В.В. | C37: ИП Никулов А.В. | D37: Счет №113 от 21.11.2025 | E37: .=146016/2 | F37: Аванс по Приложению 1/14 к Договору №ФП-10660-98 от 04.04.2025 | G37: Бюджет | H37: Да | I37: Монтаж системы полива на придомовой ГП 273, 280
A38: =A37+1 -> 29 | B38: Лещенко В.А. | C38: ИП Стрельцов В.А. | D38: Счет № 23 от 07.11.2025 | E38: .600050 | F38: Устройство приточно-вытяжной вентиляции согласно Приложения №1/13 от 11.06.2025г. к Договору подряда №ФП-10660-53/01 от 08.10.2024 г. | G38: Бюджет | H38: Да | I38: ГП 291. Вентиляция
A39: =A38+1 -> 30 | B39: Малый П.А. | C39: ИП Алты-Садых С.Ю | D39: Счёт№18/2 от 15.12.2025 | E39: .109250 | F39: Окончательный платеж за работы, изготовление,монтаж,шлифовку пропитку и окраску деревянных элементов террасы | G39: Бюджет | H39: Да | I39: ГП-148 Дог№-ФП-10660-31 ОТ 14.11.2022
A40: =A39+1 -> 31 | B40: Малый П.А. | C40: ИП Чеботарев А.В. | D40: Счет № 1369 от 11.09.2025 | E40: .107000 | F40: Разработка дизайн проекта. Пр.№ 1/2 к дог.№ФП-10660-101 от 21.08.2025 | G40: Бюджет | H40: Да | I40: ГП 146
A41: =A40+1 -> 32 | B41: Малый П.А. | C41: ИП Глазунов Е.А. | D41: Счёт№15 от 22.01.2026 | E41: .18400 | F41: Уборка помещений | H41: Да
A42: =A41+1 -> 33 | B42: Лещенко В.А. | C42: сз Шкрябина | D42: Счет №24365802 от 04.12.2025г. | E42: .=414800-114800-130000 | F42: Монтаж фасонных изделий | G42: Бюджет | H42: Да | I42: ГП 291-292
A43: =A42+1 -> 34 | B43: Малый П.А. | C43: ИП Доброхотова Н.А. | D43: Счёт№1 от 15.01.2026 | E43: .20000 | F43: ЛДУ | H43: Да | I43: Вн. рынок Ореховая роща Дог№ФП-10660 ОТ 21.02.2024
A44: =A43+1 -> 35 | B44: Малый П.А. | C44: ИП Храмова Э.Э. | D44: Счёт№389 от 10.03.2026 | E44: .12600 | F44: Услуги по благоустройству територии | H44: Да | I44: Дог №ФП-10660 от 15.03.2023
A45: =A44+1 -> 36 | B45: Малый П.А. | C45: ООО "УСПЕХ" | D45: Счёт№11695от 12.03.2026 | E45: .11119 | F45: Хим препараты для обработки растений | H45: Да | I45: Дендро
A46: =A45+1 -> 37 | B46: Малый П.А. | C46: ИП Чередниченко | D46: Счёт№13 от 18.03.2025 | E46: .116000 | F46: Монтаж плинтуса | H46: Да | I46: ГП-138 Дог №ФП-10660-84/01 ОТ 01.10.2024
A47: =A46+1 -> 38 | B47: Малый П.А. | C47: ИП Чередниченко | D47: Счёт№15 от 18.03.2026 | E47: .247720 | F47: Монтаж плинтуса | H47: Да | I47: ГП-138 Дог №ФП-10660-84/01 ОТ 01.10.2024
A48: =A47+1 -> 39 | B48: Малый П.А. | C48: ИП Храмова | D48: Счёт№443 от 16.03.2026 | E48: .25200 | F48: Услуги по благоустройству территории с 11.03.2026 по 12.03.2026 | I48: Дог №ФП-10660-36 ОТ 15.03.2023
A49: =A48+1 -> 40 | B49: Малый П.А. | C49: ООО "РостАвтоБетон" | D49: Счёт№6 от 14.03.2026 | E49: .105400 | F49: Бетон | I49: ГП-385
A50: =A49+1 -> 41 | B50: Малый П.А. | C50: ИП Доброхотова Н.А. | D50: Счёт№5 от 19.03.2026 | E50: .21400 | F50: Аванс | I50: ГП-235Дог№ФП-10660-73 от21.02.2024Пр-1/9
A51: =A50+1 -> 42 | B51: Малый П.А. | C51: ИП Никулов А.В. | D51: Счёт №16 от 20.03.2026 | E51: .26000 | F51: Запуск системы полива | I51: Дог№ФП-10660-98 от 04.04.2025ПР№1/15 от 16.03.2026
A52: =A51+1 -> 43 | B52: Малый П.А. | C52: ООО"Агроцентр Дон" | D52: Счёт№31 от 19.03.2026 | E52: .28320 | F52: Препараты для растений | I52: Дендро
A53: =A52+1 -> 44 | B53: Малый П.А. | C53: ООО"ВСЕ ИНСТРУМЕНТЫ.РУ" | D53: Счёт№2603-182351-62749 от 23.03.2026 | E53: .4094 | F53: Батарея акумуляторная к опрыскователю | I53: Дендро
A54: =A53+1 -> 45 | B54: Малый П.А. | C54: ИП Доброхотова Н.А. | D54: Счёт№6 от23.03.2026 | E54: .19920 | F54: ЛДУ | I54: ГП-163Дог№ФП-10660-73 ОТ 21.02.2024 ПР-1/10
A55: =A54+1 -> 46 | B55: Малый П.А. | C55: ИП Храмова | D55: Счёт№493 от 23.03.2026 | E55: .42000 | F55: Услуги по благоустройству
A56: =A55+1 -> 47 | B56: Малый П.А. | C56: ИП Глазунов Е.А. | D56: Счёт№126от24.03.2026 | E56: .18400 | F56: Ежедневная уборка
A57: =A56+1 -> 48 | B57: МалыйП.А. | C57: ООО"АРТГРИН" | D57: Счёт№УТ-5 от26.03.2025 | E57: .156000 | F57: растения
A58: =A57+1 -> 49 | B58: МалыйП.А. | C58: ИП Богачёв А.С. | D58: Счёт№18от 20.03.2026 | E58: 241762.5 | F58: Стяжка | G58: Бюджет | H58: Да | I58: ГП-326 | J58: оплачен
A59: =A58+1 -> 50 | B59: Малый П.А. | C59: ИП Стрельцов В.А. | D59: Счёт№2 от 26.03.2026 | E59: 220062 | F59: Монтаж труб водоснабжения | G59: Бюджет | H59: Да | I59: ГП-385,398 Дог№ФП-10660-53/01 ОТ08.10.2024ПР№1/17 от 25.03.2026 | J59: оплачен
A60: =A59+1 -> 51 | B60: Малый П.А. | C60: СЗ Ботика | D60: Счёт№27657086 от 26.03.2026 | E60: 290000 | F60: Строительство забора | G60: Бюджет | H60: Да | I60: ГП 326 | J60: оплачен
A61: =A60+1 -> 52 | B61: Малый П.А. | C61: ИП Храмова Э.Э | D61: Счёт№2177от 08.12.2025 | E61: 16800 | F61: Благоустройство территории | G61: Бюджет | H61: Да | I61: ГП-103 Дог№ФП-10660-36 Планирование грунта | J61: оплачен
A62: =A61+1 -> 53 | B62: Малый П.А. | C62: ИП Храмова Э.Э. | D62: Счёт№2233 от 15.12.2025 | E62: 8400 | F62: Благоустройство территории | G62: Бюджет | H62: Да | I62: ГП-218,231,213,214,216,221,188 Дог№10660-36 от 15.032023 чистка преддомовых территорий | J62: оплачен
A63: =A62+1 -> 54 | B63: Малый П.А | C63: АО Евраз Маркет | D63: Счёт№ИНН00-050099 от13.03.2026 | E63: 60157.2 | F63: Металлопрокат | G63: Бюджет | H63: Да | I63: ГП-385 ХБП Дог№ФП10022025 ПР№2 от 17.02.2025 | J63: оплачен
A64: =A63+1 -> 55 | B64: Малый П.А. | C64: ООО"Грузтехстрой" | D64: Счёт№ЦБ-205 от25.03.2026 | E64: .3700 | F64: Щебень | G64: Бюджет | H64: да | I64: ГП-273,280 ПР1/5
A65: =A64+1 -> 56 | B65: Малый П.А. | C65: ООО"Грузтехстрой" | D65: Счёт№ЦБ-205 от25.03.2026 | E65: 15000 | F65: Щебень | G65: Бюджет | H65: да | I65: ГП-273,280 ПР1/5 | J65: оплачен
A66: =A65+1 -> 57
A67: =A66+1 -> 58
A68: =A67+1 -> 59
A69: =A68+1 -> 60
B70: Бухгалтерия (Налоги / ЗП / ЕСН / прочие платежи бух. службы)
A71: 1 | B71: Дмитриева О. В. | C71: ИФНС по ЕНП | D71: КБК 18201061201010000510 | E71: .225000 | F71: Страховые взносы за февраль 2026 г (налоги с фот)
A72: 2 | B72: Дмитриева О. В. | C72: ИФНС по ЕНП | D72: КБК 182 01 06 12 01 01 0000 510 | E72: .49000 | F72: НДФЛ (период с 01.03-22.03.2026) | I72: срок оплаты до 27.03.26
A73: 3
A74: 4
A75: 5
A76: ИТОГО ФАБРИКА ПРОЕКТОВ РАСХОДЫ ПО РЕЕСТРУ | E76: =SUM(E9:E75) -> 852181.7
A77: ДЕФИЦИТ / ПРОФИЦИТ с Остатка на начало дня | E77: =E4-E76 -> 7680.17

Sheet 27
E1: _____________________________ Согласовано
C2: ='26'!C2+1 -> 46108 | F2: Реестр разбит по Юр. лицам!!! КРУТИТЕ ВНИЗ
A4: ФАБРИКА ПРОЕКТОВ | E4: =SUM(E5:E6) -> 3200.17 | F4: Реестр закрыт!!!
A5: Счет Альфа 1674 | E5: 993.53
A6: счет СБЕР 6989 | E6: 2206.64
A8: № п/п | B8: Инициатор платежа | C8: Контрагент - Получатель | D8: Договор/Счет | E8: Сумма к оплате | F8: Назначение платежа | G8: Бюджет/Статья | H8: Наличие Договора | I8: Примечание | J8: Отметка об оплате | K8: Спец. Распоряжение / Приоритет
B9: Коммерческая деятельность (Закупка ТМЦ Снабжение / Логистика / Транзит)
A10: 1
A11: 2
A12: 3
A13: 4
A14: 5
A15: 6
A16: 7
A17: 8
A18: 9
A19: 10
A20: 11
A21: 12
... A59: 50
B60: АХР (Продажи / IT служба / Юр служба / ФЭО /Секретариат)
A61: 1
A62: 2
A63: 3
A64: 4
A65: 5
B66: Бухгалтерия (Налоги / ЗП / ЕСН / прочие платежи бух. службы)
A67: 1 | B67: Дмитриева О. В. | C67: Альфа-Банк | D67: реестр | E67: 17242.17 | F67: отпускные за март 2026 г. | J67: оплачен
A68: 2
A69: 3
A70: 4
A71: 5
A72: ИТОГО ФАБРИКА ПРОЕКТОВ РАСХОДЫ ПО РЕЕСТРУ | E72: =SUM(E9:E71) -> 17242.17
A73: ДЕФИЦИТ / ПРОФИЦИТ с Остатка на начало дня | E73: =E4-E72 -> -14042

Sheet 28
E1: _____________________________ Согласовано
C2: ='27'!C2+1 -> 46109 | F2: Реестр разбит по Юр. лицам!!! КРУТИТЕ ВНИЗ
A4: ФАБРИКА ПРОЕКТОВ | E4: =SUM(E5:E6) -> 0
A5: Счет Альфа 1674
A6: счет СБЕР 6989
A8: № п/п | B8: Инициатор платежа | C8: Контрагент - Получатель | D8: Договор/Счет | E8: Сумма к оплате | F8: Назначение платежа | G8: Бюджет/Статья | H8: Наличие Договора | I8: Примечание | J8: Отметка об оплате | K8: Спец. Распоряжение / Приоритет
B9: Коммерческая деятельность (Закупка ТМЦ Снабжение / Логистика / Транзит)
A10: 1
A11: 2
A12: 3
A13: 4
A14: 5
A15: 6
A16: 7
A17: 8
A18: 9
A19: 10
A20: 11
A21: 12
... A59: 50
B60: АХР (Продажи / IT служба / Юр служба / ФЭО /Секретариат)
A61: 1
A62: 2
A63: 3
A64: 4
A65: 5
B66: Бухгалтерия (Налоги / ЗП / ЕСН / прочие платежи бух. службы)
A67: 1
A68: 2
A69: 3
A70: 4
A71: 5
A72: ИТОГО ФАБРИКА ПРОЕКТОВ РАСХОДЫ ПО РЕЕСТРУ | E72: =SUM(E9:E71) -> 0
A73: ДЕФИЦИТ / ПРОФИЦИТ с Остатка на начало дня | E73: =E4-E72 -> 0

Sheet 29
E1: _____________________________ Согласовано
C2: ='28'!C2+1 -> 46110 | F2: Реестр разбит по Юр. лицам!!! КРУТИТЕ ВНИЗ
A4: ФАБРИКА ПРОЕКТОВ | E4: =SUM(E5:E6) -> 0
A5: Счет Альфа 1674
A6: счет СБЕР 6989
A8: № п/п | B8: Инициатор платежа | C8: Контрагент - Получатель | D8: Договор/Счет | E8: Сумма к оплате | F8: Назначение платежа | G8: Бюджет/Статья | H8: Наличие Договора | I8: Примечание | J8: Отметка об оплате | K8: Спец. Распоряжение / Приоритет
B9: Коммерческая деятельность (Закупка ТМЦ Снабжение / Логистика / Транзит)
A10: 1
A11: 2
A12: 3
A13: 4
A14: 5
A15: 6
A16: 7
A17: 8
A18: 9
A19: 10
A20: 11
A21: 12
... A59: 50
B60: АХР (Продажи / IT служба / Юр служба / ФЭО /Секретариат)
A61: 1
A62: 2
A63: 3
A64: 4
A65: 5
B66: Бухгалтерия (Налоги / ЗП / ЕСН / прочие платежи бух. службы)
A67: 1
A68: 2
A69: 3
A70: 4
A71: 5
A72: ИТОГО ФАБРИКА ПРОЕКТОВ РАСХОДЫ ПО РЕЕСТРУ | E72: =SUM(E9:E71) -> 0
A73: ДЕФИЦИТ / ПРОФИЦИТ с Остатка на начало дня | E73: =E4-E72 -> 0

Sheet 30
E1: _____________________________ Согласовано
C2: ='29'!C2+1 -> 46111 | F2: Реестр разбит по Юр. лицам!!! КРУТИТЕ ВНИЗ
A4: ФАБРИКА ПРОЕКТОВ | E4: =SUM(E5:E6) -> 20558 | F4: Реестр закрыт!!!
A5: Счет Альфа 1674 | E5: 18351.36
A6: счет СБЕР 6989 | E6: 2206.64
A8: № п/п | B8: Инициатор платежа | C8: Контрагент - Получатель | D8: Договор/Счет | E8: Сумма к оплате | F8: Назначение платежа | G8: Бюджет/Статья | H8: Наличие Договора | I8: Примечание | J8: Отметка об оплате | K8: Спец. Распоряжение / Приоритет
B9: Коммерческая деятельность (Закупка ТМЦ Снабжение / Логистика / Транзит)
A10: 1
A11: 2
A12: 3
A13: 4
A14: 5
A15: 6
A16: 7
A17: 8
A18: 9
A19: 10
A20: 11
A21: 12
... A59: 50
B60: АХР (Продажи / IT служба / Юр служба / ФЭО /Секретариат)
A61: 1
A62: 2
A63: 3
A64: 4
A65: 5
B66: Бухгалтерия (Налоги / ЗП / ЕСН / прочие платежи бух. службы)
A67: 1
A68: 2
A69: 3
A70: 4
A71: 5
A72: ИТОГО ФАБРИКА ПРОЕКТОВ РАСХОДЫ ПО РЕЕСТРУ | E72: =SUM(E9:E71) -> 0
A73: ДЕФИЦИТ / ПРОФИЦИТ с Остатка на начало дня | E73: =E4-E72 -> 20558

Sheet 31
E1: _____________________________ Согласовано
C2: ='30'!C2+1 -> 46112 | F2: Реестр разбит по Юр. лицам!!! КРУТИТЕ ВНИЗ
A4: ФАБРИКА ПРОЕКТОВ | E4: =SUM(E5:E6) -> 1533021.8 | F4: Реестр закрыт!!!
A5: Счет Альфа 1674 | E5: 750351.36
A6: счет СБЕР 6989 | E6: 782670.42
A8: № п/п | B8: Инициатор платежа | C8: Контрагент - Получатель | D8: Договор/Счет | E8: Сумма к оплате | F8: Назначение платежа | G8: Бюджет/Статья | H8: Наличие Договора | I8: Примечание | J8: Отметка об оплате | K8: Спец. Распоряжение / Приоритет
B9: Коммерческая деятельность (Закупка ТМЦ Снабжение / Логистика / Транзит)
A10: 1 | B10: Лещенко В.А. | C10: ООО ГЕРМЕС | D10: Счет № 493 от 24.10.2025 | E10: .218750 | F10: Закупка бетона | G10: Бюджет | H10: Да | I10: ГП 294 Забор. ИП Малый. Договор №ФП31072025 от 31.07.2025 Приложение №2
A11: =A10+1 -> 2 | B11: Лещенко В.А. | C11: ООО "Айрон" | D11: Счет №АИПП-2504 от 21.03.2025 | E11: .=16534 | F11: Закупка металла. | G11: Бюджет | H11: Да | I11: (Щепкино. СПА.стены)ИП Малый Договор подряда №ФП-03022025 от 03.02.2025 Пр. №2 от 03.02.2025 ИП Малый
A12: =A11+1 -> 3 | B12: Лещенко В.А. | C12: ООО "Айрон" | D12: Счет № АИПП-3664 от 25.04.2025 | E12: .126845 | F12: Закупка металла на объект | G12: Бюджет | H12: Да | I12: ГП 204 (Навес) Договор подряда №ФП-27032025 от 27.03.2025 Приложение № 2 от 27.03.2025
A13: =A12+1 -> 4 | B13: Лещенко В.А. | C13: ООО "Айрон" | D13: Счет № АИПП-3754 от 29.04.2025 | E13: .27325 | F13: Закупка металла. | G13: Бюджет | H13: Да | I13: ГП 204(навес) Договор подряда №ФП-27032025 от 27.03.2025 Приложение №2 от 27.03.2025
A14: =A13+1 -> 5 | B14: Лещенко В.А. | C14: ООО "Айрон" | D14: Счет № АИПП-5404 от 30.06.2025 | E14: .150100 | F14: Закупка металла на объект | G14: Бюджет | H14: Да | I14: ГП 294. ХБП ИП Малый Договор подряда №ФП-19062025 от 19.06.2025 Приложение №2 от 19.06.2025
A15: =A14+1 -> 6 | B15: Лещенко В.А. | C15: ООО "Айрон" | D15: Счет № АИПП-5407 от 30.06.2025 | E15: .17300 | F15: Закупка металла на объект | G15: Бюджет | H15: Да | I15: ГП 204. ИП Малый. Договор подряда №ФП-27032025 от 27.03.2025 Приложение №2 от 27.03.2025
A16: =A15+1 -> 7 | B16: Лещенко В.А. | C16: ООО "Айрон" | D16: Счет № АИПП-5408 от 30.06.2025 | E16: .35505 | F16: Закупка металла на объект | G16: Бюджет | H16: Да | I16: ГП 13. (ХБП) ИП Малый. Договор подряда №ФП-10660-72/01 от 12.02.2024 г. Приложение №1/8 от 14.03.2025
A17: =A16+1 -> 8 | B17: Лещенко В.А. | C17: ООО "Айрон" | D17: Счет № АИПП-6301 от 04.08.2025 | E17: .163370 | F17: Закупка металла на объект | G17: Бюджет | H17: Да | I17: ГП 326. Забор ИП Малый
A18: =A17+1 -> 9 | B18: Лещенко В.А. | C18: ООО "Айрон" | D18: Счет № АИПП-6303 от 04.08.2025 | E18: .115500 | F18: Закупка металла на объект | G18: Бюджет | H18: Да | I18: ГП 294. Бассеин ИП Малый
A19: =A18+1 -> 10 | B19: Лещенко В.А. | C19: ООО "Айрон" | D19: Счет № АИПП-6304 от 04.08.2025 | E19: .51000 | F19: Закупка металла на объект | G19: Бюджет | H19: Да | I19: ГП 294. Забор ИП Малый
A20: =A19+1 -> 11 | B20: Лещенко В.А. | C20: ИП Полежаев А.А. | D20: Счет № 42 от 26.09.2025 | E20: .363298 | F20: Устройство фасада с молдингами на ХБП по дог.№ФП-10660-29 от 16.09.2022, пр.№ 1/19 | G20: Бюджет | H20: Да | I20: Окончательный ГП 326
A21: =A20+1 -> 12 | B21: Малый П.А. | C21: ИП Полежаев А.А. | D21: Счёт №50 от 26.11.2025 | E21: .538264 | F21: Устройство фасада с молдингами | G21: Бюджет | H21: Да | I21: Окончательный ГП-243
A22: =A21+1 -> 13 | B22: Малый П.А. | C22: ИП Полежаев А.А. | D22: Счёт№51 от 02.12.2025 | E22: .54956 | F22: Устройство калон террасы | G22: Бюджет | H22: Да | I22: Окончательный. ГП-294.295 Договор подряда№ФП-10660-29 ОТ 16.09.2022
... A29: =A28+1 -> 20 | B29: Малый П.А. | C29: ИП Кравченко К.Н. | D29: Счёт № 609 от 22.12.2025 | E29: .128725,35 | F29: Пиломатериалы | G29: Бюджет | H29: Да | I29: Навес ГП 262
A30: =A29+1 -> 21 | B30: Синицына В.В. | C30: ИП Храмова Э.Э. | D30: Счет №2252 от 22.12.2025 | E30: .42000 | F30: Услуги по благоустройству территории | G30: Бюджет | H30: Да
A31: =A30+1 -> 22 | B31: Синицына В.В. | C31: ИП Храмова Э.Э. | D31: Счет №2301 от 25.12.2025г. | E31: .25200 | F31: Услуги по благоустройству территории | G31: Бюджет | H31: Да
A32: =A31+1 -> 23 | B32: Лещенко В.А. | C32: ИП Сердечная О.Ю. | D32: Счет № 291 от 17.09.2025 | E32: .59500 | F32: Договор №3 от 30.03.2022 г. Транспортные услуги по перевозке опалубки, 05.09.2025 г.,16.09.2025 г. | G32: Бюджет | H32: Да | I32: ГП 294. Бассейн.ИП Малый
A33: =A32+1 -> 24 | B33: Лещенко В.А. | C33: ИП Козлова Н.В. | D33: Счет № 27 от 19.11.2024 | E33: .=30500 | F33: Ус-во фасада по дог.№ФП-10660-93 от 01.10.2024 от 19.11.2024 | G33: Бюджет | H33: Да | I33: Окончательный.ГП-211
A34: =A33+1 -> 25 | B34: Лещенко В.А. | C34: ООО "АЛЮМИНИУМ" | D34: Счет № 385 от 03.09.2025 | E34: .386200 | F34: Оплата за алюмииевые конструкции по дог.№ФП-28052024 от 28.05.2025 | G34: Бюджет | H34: Да | I34: ГП 291. Витражи.
A35: =A34+1 -> 26 | B35: Синицына В.В. | C35: ИП Никулов А.В. | D35: Счет №113 от 21.11.2025 | E35: .=146016/2 | F35: Аванс по Приложению 1/14 к Договору №ФП-10660-98 от 04.04.2025 | G35: Бюджет | H35: Да | I35: Монтаж системы полива на придомовой ГП 273, 280
A36: =A35+1 -> 27 | B36: Лещенко В.А. | C36: ИП Стрельцов В.А. | D36: Счет № 23 от 07.11.2025 | E36: .600050 | F36: Устройство приточно-вытяжной вентиляции согласно Приложения №1/13 от 11.06.2025г. к Договору подряда №ФП-10660-53/01 от 08.10.2024 г. | G36: Бюджет | H36: Да | I36: ГП 291. Вентиляция
A37: =A36+1 -> 28 | B37: Малый П.А. | C37: ИП Алты-Садых С.Ю | D37: Счёт№18/2 от 15.12.2025 | E37: .109250 | F37: Окончательный платеж за работы, изготовление,монтаж,шлифовку пропитку и окраску деревянных элементов террасы | G37: Бюджет | H37: Да | I37: ГП-148 Дог№-ФП-10660-31 ОТ 14.11.2022
A38: =A37+1 -> 29 | B38: Малый П.А. | C38: ИП Чеботарев А.В. | D38: Счет № 1369 от 11.09.2025 | E38: .107000 | F38: Разработка дизайн проекта. Пр.№ 1/2 к дог.№ФП-10660-101 от 21.08.2025 | G38: Бюджет | H38: Да | I38: ГП 146
A39: =A38+1 -> 30 | B39: Малый П.А. | C39: ИП Доброхотова Н.А. | D39: Счёт№1 от 15.01.2026 | E39: .20000 | F39: ЛДУ | H39: Да | I39: Вн. рынок Ореховая роща Дог№ФП-10660 ОТ 21.02.2024
A40: =A39+1 -> 31 | B40: Малый П.А. | C40: ИП Храмова Э.Э. | D40: Счёт№389 от 10.03.2026 | E40: .12600 | F40: Услуги по благоустройству територии | H40: Да | I40: Дог №ФП-10660 от 15.03.2023
A41: =A40+1 -> 32 | B41: Малый П.А. | C41: ООО "УСПЕХ" | D41: Счёт№11695от 12.03.2026 | E41: .11119 | F41: Хим препараты для обработки растений | H41: Да | I41: Дендро
A42: =A41+1 -> 33 | B42: Малый П.А. | C42: ИП Храмова | D42: Счёт№443 от 16.03.2026 | E42: .25200 | F42: Услуги по благоустройству территории с 11.03.2026 по 12.03.2026 | H42: Да | I42: Дог №ФП-10660-36 ОТ 15.03.2023
A43: =A42+1 -> 34 | B43: Малый П.А. | C43: ИП Никулов А.В. | D43: Счёт №16 от 20.03.2026 | E43: .26000 | F43: Запуск системы полива | H43: Да | I43: Дог№ФП-10660-98 от 04.04.2025ПР№1/15 от 16.03.2026
A44: =A43+1 -> 35 | B44: Малый П.А. | C44: ООО"Агроцентр Дон" | D44: Счёт№31 от 19.03.2026 | E44: .28320 | F44: Препараты для растений | H44: Да | I44: Дендро
A45: =A44+1 -> 36 | B45: Малый П.А. | C45: ООО"ВСЕ ИНСТРУМЕНТЫ.РУ" | D45: Счёт№2603-182351-62749 от 23.03.2026 | E45: .4094 | F45: Батарея акумуляторная к опрыскователю | H45: Да | I45: Дендро
A46: =A45+1 -> 37 | B46: Малый П.А. | C46: ИП Доброхотова Н.А. | D46: Счёт№6 от23.03.2026 | E46: .19920 | F46: ЛДУ | H46: Да | I46: ГП-163Дог№ФП-10660-73 ОТ 21.02.2024 ПР-1/10
A47: =A46+1 -> 38 | B47: Малый П.А. | C47: ИП Храмова | D47: Счёт№493 от 23.03.2026 | E47: .42000 | F47: Услуги по благоустройству | H47: Да
A48: =A47+1 -> 39 | B48: Малый П.А. | C48: ИП Глазунов Е.А. | D48: Счёт№126от24.03.2026 | E48: .18400 | F48: Ежедневная уборка март | H48: Да
A49: =A48+1 -> 40 | B49: Малый П.А. | C49: ООО "РостАвтоБетон" | D49: Счёт№6 от 14.03.2026 | E49: 105400 | F49: Бетон | G49: Бюджет | H49: Да | I49: ГП-385 | J49: оплачен
A50: =A49+1 -> 41 | B50: Малый П.А. | C50: ИП Доброхотова Н.А. | D50: Счёт№5 от 19.03.2026 | E50: 21400 | F50: Аванс | G50: Бюджет | H50: Да | I50: ГП-235Дог№ФП-10660-73 от21.02.2024Пр-1/9 | J50: оплачен
A51: =A50+1 -> 42 | B51: Малый П.А. | C51: ИП Чередниченко | D51: Счёт№13 от 18.03.2025 | E51: 116000 | F51: Монтаж плинтуса | G51: Бюджет | H51: Да | I51: ГП-138 Дог №ФП-10660-84/01 ОТ 01.10.2024 | J51: оплачен
A52: =A51+1 -> 43 | B52: Малый П.А. | C52: ИП Чередниченко | D52: Счёт№15 от 18.03.2026 | E52: 247720 | F52: Монтаж плинтуса | G52: Бюджет | H52: Да | I52: ГП-138 Дог №ФП-10660-84/01 ОТ 01.10.2024 | J52: оплачен
A53: =A52+1 -> 44 | B53: Малый П.А. | C53: ИП Глазунов Е.А. | D53: Счёт№15 от 22.01.2026 | E53: 18400 | F53: Уборка помещений февраль | G53: Бюджет | H53: Да | J53: оплачен
A54: =A53+1 -> 45 | B54: Лещенко В.А. | C54: сз Шкрябина | D54: Счет №24365802 от 04.12.2025г. | E54: =414800-114800-130000 -> 170000 | F54: Монтаж фасонных изделий | G54: Бюджет | H54: Да | I54: ГП 291-292 | J54: оплачен
A55: =A54+1 -> 46 | B55: Синицына В.В. | C55: ИП Храмова Э.Э. | D55: Счет №2042 от 17.11.2025 | E55: 42000 | F55: Услуги по благоустройству территории с 10.11.2025 по 13.11.2025 | G55: Бюджет | H55: Да | J55: оплачен
A56: =A55+1 -> 47 | B56: Лещенко В.А. | C56: ИП Полежаев А.А. | D56: Счет № 44 от 30.09.2025 | E56: 313500 | F56: Устройство фасада с молдингами на ХБП. Договор подряда №ФП-10660-29 от 16.09.2022 Приложение № 1/25 | G56: Бюджет | H56: Да | I56: Аванс ГП 294,295 | J56: оплачен
A57: =A56+1 -> 48 | B57: Малый П.А. | C57: ООО"АРТГРИН" | D57: Счёт№УТ-5 от26.03.2025 | E57: 156000 | F57: растения | G57: Бюджет | H57: Да | J57: оплачен
A58: =A57+1 -> 49 | B58: Малый П.А. | C58: ООО"Грузтехстрой" | D58: Счёт№ЦБ-205 от25.03.2026 | E58: 3700 | F58: Щебень | G58: Бюджет | H58: да | I58: ГП-273,280 ПР1/5 | J58: оплачен
A59: =A58+1 -> 50 | B59: Малый П.А | C59: АО Евраз Маркет | D59: Счёт№ИН00-064660 от 30.03.2026 | E59: 682.92 | F59: Доплата по счету за Металлопрокат | G59: Бюджет | H59: Да | I59: ГП-385 ХБП Дог№ФП10022025 ПР№2 от 17.02.2025 | J59: оплачен
A60: =A59+1 -> 51 | B60: Малый П.А. | C60: СЗ Ботика | D60: Счёт№27657086 от 26.03.2026 | E60: 310000 | F60: Строительство забора | G60: Бюджет | H60: Да | I60: ГП 326 | J60: оплачен
A61: =A60+1 -> 52 | B61: Малый П.А. | C61: ООО "ЛЕ МОНЛИД" | E61: 10000 | F61: Пополнение клиентского счета | G61: Бюджет | H61: Да | I61: ГП-385 ХБП Дог№ФП10022025 ПР№2 от 17.02.2025 | J61: оплачен
A62: =A61+1 -> 53 | B62: Малый П.А. | C62: ООО "Кровельный Торговый Дом" | D62: Акт сверки | E62: 3476.98 | F62: Оплата по Акту сверки | J62: оплачен
B63: АХР (Продажи / IT служба / Юр служба / ФЭО /Секретариат)
A64: 1 | B64: Антоненко | C64: ИП Медовник Андрей Сергеевич | D64: Счет на оплату № 231 от 16 марта 2026 г. | E64: 5000 | F64: Адаптация/модификация программ для ЭВМ и баз данных на платформе Prologue-UNI (Тариф: "Визитка", Проект: "abfabrika.ru", Период: "2026 Апрель") | G64: Бюджет | H64: Да | J64: оплачен
A65: 2 | B65: Антоненко | C65: ООО "Телемир" | D65: Счет на оплату № 30154 от 22 марта 2026 г. | E65: 2200 | F65: Предоставление услуг связи по договору TN65/2/260324 за период 01.04.2026 - 30.04.2026 для проекта abfabrika.ru | G65: Бюджет | H65: Да | I65: В назначении платежа необходимо указывать: "Оплата по счету №30154 от 22 марта 2026 г, в том числе НДС 22%, 396,72 руб." | J65: оплачен
A66: 3 | B66: Антоненко | C66: ООО "МАРЭКС" | D66: Счет на оплату № 29 от 17 марта 2026 г. | E66: .18400 | F66: Печать буклета А4 фальц до евроформата, безадресное распространение
A67: 4
A68: 5
B69: Бухгалтерия (Налоги / ЗП / ЕСН / прочие платежи бух. службы)
A70: 1 | B70: Дмитриева О. В. | C70: ИФНС по ЕНП | D70: КБК 18201061201010000510 | E70: .225000 | F70: Страховые взносы за февраль 2026 г (налоги с фот) | I70: Переплата на ЕНС (сумма считается оплаченой)
A71: 2 | B71: Дмитриева О. В. | C71: ИФНС по ЕНП | D71: КБК 182 01 06 12 01 01 0000 510 | E71: .49000 | F71: НДФЛ (период с 01.03-22.03.2026) | I71: Переплата на ЕНС (сумма считается оплаченой)
A72: 3 | B72: Попова Е.П. | C72: ООО "Алекс-Юг" | D72: Письмо на возврат | E72: 1036 | F72: Возврат ДС согласно письму | G72: Бюджет | H72: Да | J72: оплачен
A73: 4
A74: 5
A75: ИТОГО ФАБРИКА ПРОЕКТОВ РАСХОДЫ ПО РЕЕСТРУ | E75: =SUM(E9:E74) -> 1526515.9
A76: ДЕФИЦИТ / ПРОФИЦИТ с Остатка на начало дня | E76: =E4-E75 -> 6505.88

Sheet Тех.Лист
A1: Да
A2: Нет
